Workbook
Name Customer: #REF!
Name RFQType: #REF!
Name TEAM: #REF!

Sheet FAK-SCHEDULE
B1: TYPE | C1: USER | D1: ACCOUNT | E1: OWNER | G1: VALIDITY & FREQUENCY | N1: ORIGIN/DESINATION VALIDITY | R1: OFR SURCHARGES VALIDITY | AA1: UPDATES | AC1: 46132
B2: REGIONAL/ GLOBAL | C2: RFQ HANDLER | D2: WWA CUSTOMER | E2: GLOBAL/REGIONAL ACCOUNT OWNER | F2: RFQ OWNER | G2: FREQUENCY (FOB/PLC) | H2: FREQUENCY (OFR) | I2: FREQUENCY (OFR SURCHARGES) | J2: FOB/PLC VALIDITY EFFECTIVE DATE | K2: FOB/PLC VALIDITY EXPIRY DATE | L2: OFR VALIDITY EFFECTIVE DATE | M2: OFR VALIDITY EXPIRY DATE | N2: ORIGIN E-INF SURCHARGE | O2: DESTINATION E-INF SURCHARGE | P2: MPCI FILING FEE | Q2: DMCE FILING FEE | R2: IMO2020 SURCHARGES | S2: GRI SURCHARGES | T2: ETSS/FEMS SURCHARGES | U2: ESF SURCHARGES | V2: E-PSS SURCHARGES | W2: LWS/PCS SURCHARGES | X2: E-BAF SURCHARGES | Y2: WRS SURCHARGES | Z2: REMARKS | AA2: FOB/PLC FOLLOW-UP | AB2: OFR FOLLOW-UP
A3: =VLOOKUP(D3,'[1]WWA Timelines '!$A:$A,1,0) -> AIT (RA) | B3: REGIONAL | C3: Sunil | D3: AIT (RA) | E3: KEVIN TAYLOR | F3: HELEN LI | G3: YEARLY | H3: YEARLY | I3: BI-WEEKLY (1-15: Member; 16-31: Advisory) | J3: 46143 | K3: 46387 | L3: 46143 | M3: 46387 | R3: MONTHLY (MEMBERS) | S3: MONTHLY (MEMBERS) | T3: MONTHLY (MEMBERS) | U3: BI-WEEKLY (MEMBERS/ADVISORY) | V3: BI-WEEKLY (MEMBERS/ADVISORY) | W3: BI-WEEKLY (MEMBERS/ADVISORY) | X3: BI-WEEKLY (MEMBERS/ADVISORY) | Y3: BI-WEEKLY (ADVISORY) | AA3: =IFERROR(NETWORKDAYS(K3,$AC$1),"-") -> -184 | AB3: =IFERROR(NETWORKDAYS(M3,$AC$1),"-") -> -184
A4: =VLOOKUP(D4,'[1]WWA Timelines '!$A:$A,1,0) -> APL LOGISTICS | B4: GLOBAL | C4: Sonali | D4: APL LOGISTICS | E4: MICHELLE YU | F4: IRTASIA | G4: QUARTERLY | H4: QUARTERLY | I4: BI-WEEKLY (MEMBERS) | J4: 46204 | K4: 46295 | L4: 46204 | M4: 46295 | N4: BI-WEEKLY (ADVISORY) | O4: BI-WEEKLY (ADVISORY) | R4: QUARTERLY | S4: BI-WEEKLY (MEMBERS) | T4: QUARTERLY | U4: BI-WEEKLY (MEMBERS) | V4: BI-WEEKLY (MEMBERS) | W4: BI-WEEKLY (MEMBERS) | X4: BI-WEEKLY (MEMBERS) | Y4: BI-WEEKLY (ADVISORY) | AA4: =IFERROR(NETWORKDAYS(K4,$AC$1),"-") -> -118 | AB4: =IFERROR(NETWORKDAYS(M4,$AC$1),"-") -> -118
A5: =VLOOKUP(D5,'[1]WWA Timelines '!$A:$A,1,0) -> ARAMEX (RA) | B5: REGIONAL | C5: Rohan | D5: ARAMEX (RA) | E5: ELVIRA TAKX / MARY ANNE CHUA | F5: IRTASIA | G5: YEARLY | H5: MONTHLY | I5: BI-WEEKLY (1-15: Member; 16-31: Advisory) | J5: 46023 | K5: 46387 | L5: 46174 | M5: 46203 | R5: MONTHLY (MEMBERS) | S5: MONTHLY (MEMBERS) | T5: MONTHLY (MEMBERS) | U5: BI-WEEKLY (MEMBERS/ADVISORY) | V5: BI-WEEKLY (MEMBERS/ADVISORY) | W5: BI-WEEKLY (MEMBERS/ADVISORY) | X5: BI-WEEKLY (MEMBERS/ADVISORY) | Y5: BI-WEEKLY (ADVISORY) | Z5: 1st Half - Members involvement 2nd Half - As per Advisory | AA5: =IFERROR(NETWORKDAYS(K5,$AC$1),"-") -> -184 | AB5: =IFERROR(NETWORKDAYS(M5,$AC$1),"-") -> -52
A6: =VLOOKUP(D6,'[1]WWA Timelines '!$A:$A,1,0) -> BARSAN (RA) | B6: REGIONAL | C6: Rohan | D6: BARSAN (RA) | E6: RYAN ROBERT HOWELL | F6: HELEN LI | G6: YEARLY | H6: MONTHLY | I6: BI-WEEKLY (1-15: Member; 16-31: Advisory) | J6: 46023 | K6: 46387 | L6: 46174 | M6: 46203 | R6: MONTHLY (MEMBERS) | S6: MONTHLY (MEMBERS) | T6: MONTHLY (MEMBERS) | U6: BI-WEEKLY (MEMBERS/ADVISORY) | V6: BI-WEEKLY (MEMBERS/ADVISORY) | W6: BI-WEEKLY (MEMBERS/ADVISORY) | X6: BI-WEEKLY (MEMBERS/ADVISORY) | Y6: EXCL. AS PER ADVISORY | Z6: 1st Half - Members involvement 2nd Half - As per Advisory | AA6: =IFERROR(NETWORKDAYS(K6,$AC$1),"-") -> -184 | AB6: =IFERROR(NETWORKDAYS(M6,$AC$1),"-") -> -52
A7: =VLOOKUP(D7,'[1]WWA Timelines '!$A:$A,1,0) -> CARGO PARTNER | B7: GLOBAL | C7: Sunil | D7: CARGO PARTNER | E7: MARTIN SCHULZ | F7: DENNIS FRANKOWSKI | G7: YEARLY | H7: MONTHLY | I7: BI-WEEKLY (1-15: Member; 16-31: Advisory) | J7: 46023 | K7: 46387 | L7: 46174 | M7: 46203 | N7: BI-WEEKLY (ADVISORY) | O7: BI-WEEKLY (ADVISORY) | R7: MONTHLY (MEMBERS) | S7: MONTHLY (MEMBERS) | T7: MONTHLY (MEMBERS) | U7: BI-WEEKLY (MEMBERS/ADVISORY) | V7: BI-WEEKLY (MEMBERS/ADVISORY) | W7: BI-WEEKLY (MEMBERS/ADVISORY) | X7: BI-WEEKLY (MEMBERS/ADVISORY) | Y7: BI-WEEKLY (ADVISORY) | Z7: 1st Half - Members involvement 2nd Half - As per Advisory | AA7: =IFERROR(NETWORKDAYS(K7,$AC$1),"-") -> -184 | AB7: =IFERROR(NETWORKDAYS(M7,$AC$1),"-") -> -52
A8: =VLOOKUP(D8,'[1]WWA Timelines '!$A:$A,1,0) -> CEVA | B8: GLOBAL | C8: Kajal | D8: CEVA | E8: JAKOB BLUHME | F8: SANTIAGO | G8: YEARLY | H8: YEARLY | I8: BI-WEEKLY (MEMBERS) | J8: 46023 | K8: 46387 | L8: 46082 | M8: 46387 | N8: BI-WEEKLY (ADVISORY) | O8: BI-WEEKLY (ADVISORY) | R8: MONTHLY (MEMBERS) | S8: MONTHLY (MEMBERS) | T8: MONTHLY (MEMBERS) | U8: BI-WEEKLY (MEMBERS) | V8: BI-WEEKLY (MEMBERS) | W8: BI-WEEKLY (MEMBERS) | X8: BI-WEEKLY (ADVISORY) | Y8: BI-WEEKLY (ADVISORY) | Z8: IMO2020/GRI/ESF/E-PSS/LWS/PCS UNDER RATE ADJUSTMENT COLUMN | AA8: =IFERROR(NETWORKDAYS(K8,$AC$1),"-") -> -184 | AB8: =IFERROR(NETWORKDAYS(M8,$AC$1),"-") -> -184
A9: =VLOOKUP(D9,'[1]WWA Timelines '!$A:$A,1,0) -> CH ROBINSON | B9: GLOBAL | C9: Sonali | D9: CH ROBINSON | E9: BRUCE ERICSON | F9: HELEN LI | G9: 6 MONTHS | H9: BI-WEEKLY | I9: BI-WEEKLY (MEMBERS) | J9: 46188 | K9: 46401 | L9: 46188 | M9: 46217 | N9: BI-WEEKLY (AGREEMENT) | O9: BI-WEEKLY (AGREEMENT) | R9: BI-WEEKLY (MEMBERS) | S9: BI-WEEKLY (MEMBERS) | T9: QUARTERLY | U9: BI-WEEKLY (MEMBERS) | V9: BI-WEEKLY (MEMBERS) | W9: BI-WEEKLY (MEMBERS) | X9: BI-WEEKLY (ADVISORY) | Y9: EXCL. AS PER ADVISORY | AA9: =IFERROR(NETWORKDAYS(K9,$AC$1),"-") -> -194 | AB9: =IFERROR(NETWORKDAYS(M9,$AC$1),"-") -> -62
A10: =VLOOKUP(D10,'[1]WWA Timelines '!$A:$A,1,0) -> CRANE WORLDWIDE | B10: GLOBAL | C10: Aseem | D10: CRANE WORLDWIDE | E10: METTE KARAPETIAN | F10: CHRIS CROWDER / HELEN LI | G10: MONTHLY | H10: MONTHLY | I10: BI-WEEKLY (1-15: Member; 16-31: Advisory) | J10: 46204 | K10: 46234 | L10: 46174 | M10: 46203 | N10: BI-WEEKLY (ADVISORY) | O10: BI-WEEKLY (ADVISORY) | R10: MONTHLY (MEMBERS) | S10: MONTHLY (MEMBERS) | T10: MONTHLY (MEMBERS) | U10: BI-WEEKLY (MEMBERS/ADVISORY) | V10: BI-WEEKLY (MEMBERS/ADVISORY) | W10: BI-WEEKLY (MEMBERS/ADVISORY) | X10: BI-WEEKLY (MEMBERS/ADVISORY) | Y10: BI-WEEKLY (ADVISORY) | Z10: 1st Half - Members involvement 2nd Half - As per Advisory | AA10: =IFERROR(NETWORKDAYS(K10,$AC$1),"-") -> -75 | AB10: =IFERROR(NETWORKDAYS(M10,$AC$1),"-") -> -52
A11: =VLOOKUP(D11,'[1]WWA Timelines '!$A:$A,1,0) -> DACHSER (EXCL. INTRA ASIA) | B11: GLOBAL | C11: Sachin | D11: DACHSER (EXCL. INTRA ASIA) | E11: MARTIN SCHULZ | F11: NADINE | G11: YEARLY | H11: MONTHLY | I11: BI-WEEKLY (1-15: Member; 16-31: Advisory) | J11: 46023 | K11: 46387 | L11: 46174 | M11: 46203 | R11: MONTHLY (MEMBERS) | S11: MONTHLY (MEMBERS) | T11: QUARTERLY (MEMBERS) | U11: BI-WEEKLY (MEMBERS/ADVISORY) | V11: BI-WEEKLY (MEMBERS/ADVISORY) | W11: BI-WEEKLY (MEMBERS/ADVISORY) | X11: BI-WEEKLY (MEMBERS/ADVISORY) | Y11: BI-WEEKLY (ADVISORY) | Z11: 1st Half - Members involvement 2nd Half - As per Advisory | AA11: =IFERROR(NETWORKDAYS(K11,$AC$1),"-") -> -184 | AB11: =IFERROR(NETWORKDAYS(M11,$AC$1),"-") -> -52
A12: =VLOOKUP(D12,'[1]WWA Timelines '!$A:$A,1,0) -> #N/A | B12: GLOBAL | C12: Sachin | D12: DACHSER (AU/NZ) | E12: JENS POTTSCHUL | F12: IRTASIA/MARIA GIRLIE | G12: YEARLY | H12: QUARTERLY | I12: - | J12: 45809 | K12: 46203 | L12: 46082 | M12: 46203 | R12: QUARTERLY | S12: QUARTERLY | T12: NA | U12: INCL. IN OFR | V12: INCL. IN OFR | W12: INCL. IN OFR | X12: EXCL. AS PER ADVISORY | Y12: EXCL. AS PER ADVISORY | Z12: SAME AS OFR VALIDITY | AA12: =IFERROR(NETWORKDAYS(K12,$AC$1),"-") -> -52 | AB12: =IFERROR(NETWORKDAYS(M12,$AC$1),"-") -> -52
A13: =VLOOKUP(D13,'[1]WWA Timelines '!$A:$A,1,0) -> DACHSER INTRA ASIA | B13: GLOBAL | C13: Sachin | D13: DACHSER INTRA ASIA | E13: JENS POTTSCHUL | F13: IRTASIA/MARIA GIRLIE | G13: YEARLY | H13: YEARLY | I13: - | J13: 45809 | K13: 46203 | L13: 45809 | M13: 46203 | R13: YEARLY | S13: YEARLY | T13: NA | U13: INCL. IN OFR | V13: INCL. IN OFR | W13: INCL. IN OFR | X13: BI-WEEKLY (ADVISORY) | Y13: EXCL. AS PER ADVISORY | Z13: SAME AS OFR VALIDITY | AA13: =IFERROR(NETWORKDAYS(K13,$AC$1),"-") -> -52 | AB13: =IFERROR(NETWORKDAYS(M13,$AC$1),"-") -> -52
A14: =VLOOKUP(D14,'[1]WWA Timelines '!$A:$A,1,0) -> DHL | B14: GLOBAL | C14: Kajal | D14: DHL | E14: JAKOB BLUHME | F14: SANTIAGO | G14: YEARLY | H14: YEARLY | I14: QUARTERLY (MEMBERS) | J14: 46023 | K14: 46387 | L14: 46113 | M14: 46387 | N14: BI-WEEKLY (AGREEMENT) | O14: BI-WEEKLY (AGREEMENT) | R14: YEARLY | S14: YEARLY | T14: YEARLY | U14: QUARTERLY (MEMBERS) | V14: QUARTERLY (MEMBERS) | W14: QUARTERLY (MEMBERS) | X14: All US Origins to All Destinations Worldwide USD 6.00 w/m, INTRA ASIA USD 3.00 w/m, All other trade lanes WW USD 7.00 w/m. | Y14: EXCL. AS PER ADVISORY | Z14: UNDER ECRS (ESF,E-PSS,LWS/PCS) | AA14: =IFERROR(NETWORKDAYS(K14,$AC$1),"-") -> -184 | AB14: =IFERROR(NETWORKDAYS(M14,$AC$1),"-") -> -184
A15: =VLOOKUP(D15,'[1]WWA Timelines '!$A:$A,1,0) -> DP WORLD | B15: GLOBAL | C15: Aseem | D15: DP WORLD | E15: MARTIN SCHULZ | F15: NADINE/SANTIAGO | G15: YEARLY | H15: MONTHLY | I15: BI-WEEKLY (1-15: Member; 16-31: Advisory) | J15: 46023 | K15: 46387 | L15: 46174 | M15: 46203 | N15: BI-WEEKLY (ADVISORY) | O15: BI-WEEKLY (ADVISORY) | R15: MONTHLY (MEMBERS) | S15: MONTHLY (MEMBERS) | T15: MONTHLY (MEMBERS) | U15: BI-WEEKLY (MEMBERS/ADVISORY) | V15: BI-WEEKLY (MEMBERS/ADVISORY) | W15: BI-WEEKLY (MEMBERS/ADVISORY) | X15: BI-WEEKLY (MEMBERS/ADVISORY) | Y15: BI-WEEKLY (ADVISORY) | AA15: =IFERROR(NETWORKDAYS(K15,$AC$1),"-") -> -184 | AB15: =IFERROR(NETWORKDAYS(M15,$AC$1),"-") -> -52
A16: =VLOOKUP(D16,'[1]WWA Timelines '!$A:$A,1,0) -> DSV GLOBAL (RFQ & NON-RFQ LANES) | B16: GLOBAL | C16: Aseem | D16: DSV GLOBAL (RFQ & NON-RFQ LANES) | E16: JAKOB BLUHME | F16: SANTIAGO | G16: YEARLY | H16: YEARLY | I16: MONTHLY (MEMBERS) | J16: 46113 | K16: 46477 | L16: 46113 | M16: 46477 | N16: BI-WEEKLY (ADVISORY) | O16: BI-WEEKLY (ADVISORY) | R16: MONTHLY (MEMBERS) | S16: MONTHLY (MEMBERS) | T16: MONTHLY (MEMBERS) | U16: MONTHLY (MEMBERS) | V16: MONTHLY (MEMBERS) | W16: MONTHLY (MEMBERS) | X16: MONTHLY (MEMBERS) | Y16: MONTHLY (AS PER ANNOUNCEMENT) | Z16: IMO2020/GRI/ETSS/FEMS/ESF/E-PSS/LWS/PCS UNDER RATE ADJUSTMENT COLUMN | AA16: =IFERROR(NETWORKDAYS(K16,$AC$1),"-") -> -248 | AB16: =IFERROR(NETWORKDAYS(M16,$AC$1),"-") -> -248
A17: =VLOOKUP(D17,'[1]WWA Timelines '!$A:$A,1,0) -> #N/A | B17: GLOBAL | C17: Rohan | D17: EFL | E17: HELEN LI | F17: - | G17: YEARLY | H17: MONTHLY | I17: BI-WEEKLY (ADVISORY) | J17: 46189 | K17: 46387 | L17: 46189 | M17: 46203 | N17: BI-WEEKLY (ADVISORY) | O17: BI-WEEKLY (ADVISORY) | R17: MONTHLY (MEMBERS) | S17: MONTHLY (MEMBERS) | T17: MONTHLY (MEMBERS) | U17: BI-WEEKLY (ADVISORY) | V17: BI-WEEKLY (ADVISORY) | W17: BI-WEEKLY (ADVISORY) | X17: BI-WEEKLY (ADVISORY) | Y17: BI-WEEKLY (ADVISORY) | AA17: =IFERROR(NETWORKDAYS(K17,$AC$1),"-") -> -184 | AB17: =IFERROR(NETWORKDAYS(M17,$AC$1),"-") -> -52
A18: =VLOOKUP(D18,'[1]WWA Timelines '!$A:$A,1,0) -> EV CARGO (RA) | B18: REGIONAL | C18: Sachin | D18: EV CARGO (RA) | E18: MARY-ANNE CHUA/CHRISTINE ZHENG | F18: IRTASIA | G18: YEARLY | H18: QUARTERLY | I18: BI-WEEKLY (ADVISORY) | J18: 46023 | K18: 46387 | L18: 46204 | M18: 46295 | N18: BI-WEEKLY (ADVISORY) | O18: BI-WEEKLY (ADVISORY) | R18: QUARTERLY | S18: QUARTERLY | T18: QUARTERLY | U18: BI-WEEKLY (ADVISORY) | V18: BI-WEEKLY (ADVISORY) | W18: BI-WEEKLY (ADVISORY) | X18: BI-WEEKLY (ADVISORY) | Y18: BI-WEEKLY (ADVISORY) | AA18: =IFERROR(NETWORKDAYS(K18,$AC$1),"-") -> -184 | AB18: =IFERROR(NETWORKDAYS(M18,$AC$1),"-") -> -118
A19: =VLOOKUP(D19,'[1]WWA Timelines '!$A:$A,1,0) -> EXPEDITORS | B19: GLOBAL | C19: Sachin | D19: EXPEDITORS | E19: METTE KARAPETIAN/SYLVIA LATHOUWERS | F19: - | G19: 6 MONTHS | H19: MONTHLY | I19: BI-WEEKLY (1-15: Member; 16-31: Advisory) | J19: 46204 | K19: 46387 | L19: 46174 | M19: 46203 | N19: BI-WEEKLY (ADVISORY) | O19: BI-WEEKLY (ADVISORY) | P19: PRE-DEFINED (AGREEMENT) | R19: MONTHLY (MEMBERS) | S19: MONTHLY (MEMBERS) | T19: MONTHLY (MEMBERS) | U19: BI-WEEKLY (MEMBERS/ADVISORY) | V19: BI-WEEKLY (MEMBERS/ADVISORY) | W19: MONTHLY (MEMBERS) | X19: BI-WEEKLY (ADVISORY) | Y19: BI-WEEKLY (ADVISORY) | Z19: 1st Half - Members involvement 2nd Half - As per Advisory | AA19: =IFERROR(NETWORKDAYS(K19,$AC$1),"-") -> -184 | AB19: =IFERROR(NETWORKDAYS(M19,$AC$1),"-") -> -52
A20: =VLOOKUP(D20,'[1]WWA Timelines '!$A:$A,1,0) -> FEDEXTRADE | B20: GLOBAL | C20: Sonali | D20: FEDEXTRADE | E20: METTE KARAPETIAN/SANTIAGO MILIAN | F20: HELEN | G20: YEARLY | H20: MONTHLY | I20: BI-WEEKLY (1-15: Member; 16-31: Advisory) | J20: 46023 | K20: 46387 | L20: 46174 | M20: 46203 | R20: MONTHLY (MEMBERS) | S20: MONTHLY (MEMBERS) | T20: MONTHLY (MEMBERS) | U20: BI-WEEKLY (MEMBERS/ADVISORY) | V20: BI-WEEKLY (MEMBERS/ADVISORY) | W20: MONTHLY (MEMBERS) | X20: MONTHLY (MEMBERS) | Y20: BI-WEEKLY (ADVISORY) | Z20: 1st Half - Members involvement 2nd Half - As per Advisory | AA20: =IFERROR(NETWORKDAYS(K20,$AC$1),"-") -> -184 | AB20: =IFERROR(NETWORKDAYS(M20,$AC$1),"-") -> -52
A21: =VLOOKUP(D21,'[1]WWA Timelines '!$A:$A,1,0) -> FIBS (RA) | B21: REGIONAL | C21: Rohan | D21: FIBS (RA) | E21: MARY-ANNE CHUA/CHRISTINE ZHENG | F21: IRTASIA | G21: YEARLY | H21: QUARTERLY | I21: BI-WEEKLY (ADVISORY) | J21: 46023 | K21: 46387 | L21: 46204 | M21: 46295 | N21: BI-WEEKLY (ADVISORY) | O21: BI-WEEKLY (ADVISORY) | R21: QUARTERLY | S21: QUARTERLY | T21: QUARTERLY | U21: BI-WEEKLY (ADVISORY) | V21: BI-WEEKLY (ADVISORY) | W21: BI-WEEKLY (ADVISORY) | X21: BI-WEEKLY (ADVISORY) | Y21: BI-WEEKLY (ADVISORY) | AA21: =IFERROR(NETWORKDAYS(K21,$AC$1),"-") -> -184 | AB21: =IFERROR(NETWORKDAYS(M21,$AC$1),"-") -> -118
A22: =VLOOKUP(D22,'[1]WWA Timelines '!$A:$A,1,0) -> FIVE STAR (RA) | B22: REGIONAL | C22: Sachin | D22: FIVE STAR (RA) | E22: MARTIN SCHULZ | F22: DENNIS FRANKOWSKI | G22: YEARLY | H22: MONTHLY | I22: BI-WEEKLY (1-15: Member; 16-31: Advisory) | J22: 46023 | K22: 46387 | L22: 46174 | M22: 46203 | N22: BI-WEEKLY (ADVISORY) | O22: BI-WEEKLY (ADVISORY) | P22: PRE-DEFINED (AGREEMENT) | R22: MONTHLY (MEMBERS) | S22: MONTHLY (MEMBERS) | T22: QUARTERLY | U22: BI-WEEKLY (MEMBERS/ADVISORY) | V22: BI-WEEKLY (MEMBERS/ADVISORY) | W22: BI-WEEKLY (MEMBERS/ADVISORY) | X22: BI-WEEKLY (MEMBERS/ADVISORY) | Y22: BI-WEEKLY (ADVISORY) | Z22: 1st Half - Members involvement 2nd Half - As per Advisory | AA22: =IFERROR(NETWORKDAYS(K22,$AC$1),"-") -> -184 | AB22: =IFERROR(NETWORKDAYS(M22,$AC$1),"-") -> -52
A23: =VLOOKUP(D23,'[1]WWA Timelines '!$A:$A,1,0) -> FLEXPORT | B23: GLOBAL | C23: Sachin | D23: FLEXPORT | E23: JENS POTTSCHUL | F23: MICHELLE YU CC. MARIA GIRLIE & IRT ASIA | G23: YEARLY | H23: MONTHLY | I23: BI-WEEKLY (1-15: Member; 16-31: Advisory) | J23: 46023 | K23: 46387 | L23: 46174 | M23: 46203 | N23: BI-WEEKLY (ADVISORY) | O23: BI-WEEKLY (ADVISORY) | R23: MONTHLY (MEMBERS) | S23: MONTHLY (MEMBERS) | T23: QUARTERLY (MEMBERS) | U23: BI-WEEKLY (MEMBERS/ADVISORY) | V23: BI-WEEKLY (MEMBERS/ADVISORY) | W23: BI-WEEKLY (MEMBERS/ADVISORY) | X23: BI-WEEKLY (MEMBERS/ADVISORY) | Y23: BI-WEEKLY (ADVISORY) | Z23: 1st Half - Members involvement 2nd Half - As per Advisory | AA23: =IFERROR(NETWORKDAYS(K23,$AC$1),"-") -> -184 | AB23: =IFERROR(NETWORKDAYS(M23,$AC$1),"-") -> -52
A24: =VLOOKUP(D24,'[1]WWA Timelines '!$A:$A,1,0) -> GEBR. WEISS | B24: GLOBAL | C24: Aseem | D24: GEBR. WEISS | E24: JAKOB BLUHME | F24: SANTIAGO | G24: YEARLY | H24: MONTHLY | I24: BI-WEEKLY (1-15: Member; 16-31: Advisory) | J24: 46023 | K24: 46387 | L24: 46174 | M24: 46203 | N24: BI-WEEKLY (ADVISORY) | O24: BI-WEEKLY (ADVISORY) | R24: MONTHLY (MEMBERS) | S24: MONTHLY (MEMBERS) | T24: MONTHLY (MEMBERS) | U24: BI-WEEKLY (MEMBERS/ADVISORY) | V24: BI-WEEKLY (MEMBERS/ADVISORY) | W24: BI-WEEKLY (MEMBERS/ADVISORY) | X24: BI-WEEKLY (MEMBERS/ADVISORY) | Y24: BI-WEEKLY (ADVISORY) | Z24: 1st Half - Members involvement 2nd Half - As per Advisory | AA24: =IFERROR(NETWORKDAYS(K24,$AC$1),"-") -> -184 | AB24: =IFERROR(NETWORKDAYS(M24,$AC$1),"-") -> -52
A25: =VLOOKUP(D25,'[1]WWA Timelines '!$A:$A,1,0) -> GEODIS | B25: GLOBAL | C25: Shraddha | D25: GEODIS | E25: MARTIN SCHULZ/SUSANNE ELSBORG-JENSEN | F25: SUSANNE | G25: YEARLY | H25: MONTHLY | I25: BI-WEEKLY (1-15: Member; 16-31: Advisory) | J25: 46023 | K25: 46387 | L25: 46174 | M25: 46203 | R25: MONTHLY (MEMBERS) | S25: MONTHLY (MEMBERS) | T25: MONTHLY (MEMBERS) | U25: BI-WEEKLY (MEMBERS/ADVISORY) | V25: BI-WEEKLY (MEMBERS/ADVISORY) | W25: BI-WEEKLY (MEMBERS/ADVISORY) | X25: BI-WEEKLY (MEMBERS/ADVISORY) | Y25: BI-WEEKLY (ADVISORY) | Z25: 1st Half - Members involvement 2nd Half - As per Advisory | AA25: =IFERROR(NETWORKDAYS(K25,$AC$1),"-") -> -184 | AB25: =IFERROR(NETWORKDAYS(M25,$AC$1),"-") -> -52
A26: =VLOOKUP(D26,'[1]WWA Timelines '!$A:$A,1,0) -> HELLMANN | B26: GLOBAL | C26: Shraddha | D26: HELLMANN | E26: MARTIN SCHULZ/NADINE BEER | F26: NADINE | G26: YEARLY | H26: QUARTERLY | I26: BI-WEEKLY (MEMBERS) | J26: 46054 | K26: 46387 | L26: 46143 | M26: 46265 | N26: BI-WEEKLY (ADVISORY) | O26: BI-WEEKLY (ADVISORY) | R26: QUARTERLY | S26: QUARTERLY | T26: QUARTERLY | U26: BI-WEEKLY (MEMBERS) | V26: BI-WEEKLY (MEMBERS) | W26: BI-WEEKLY (MEMBERS) | X26: PRE-DEFINED (AGREEMENT) | Y26: PRE-DEFINED (AGREEMENT) | Z26: Members involvement | AA26: =IFERROR(NETWORKDAYS(K26,$AC$1),"-") -> -184 | AB26: =IFERROR(NETWORKDAYS(M26,$AC$1),"-") -> -96
A27: =VLOOKUP(D27,'[1]WWA Timelines '!$A:$A,1,0) -> HELLMANN INTRA ASIA | B27: GLOBAL | C27: Shraddha | D27: HELLMANN INTRA ASIA | E27: JENS POTTSCHUL | F27: IRTASIA | G27: YEARLY | H27: QUARTERLY | I27: BI-WEEKLY (ADVISORY) | J27: 46023 | K27: 46387 | L27: 46204 | M27: 46295 | R27: QUARTERLY | S27: QUARTERLY | T27: NA | U27: BI-WEEKLY (ADVISORY) | V27: BI-WEEKLY (ADVISORY) | W27: BI-WEEKLY (ADVISORY) | X27: BI-WEEKLY (ADVISORY) | Y27: EXCL. AS PER ADVISORY | AA27: =IFERROR(NETWORKDAYS(K27,$AC$1),"-") -> -184 | AB27: =IFERROR(NETWORKDAYS(M27,$AC$1),"-") -> -118
A28: =VLOOKUP(D28,'[1]WWA Timelines '!$A:$A,1,0) -> JAS OCEAN | B28: GLOBAL | C28: Sonali | D28: JAS OCEAN | E28: CHRIS CROWDER | F28: HELEN | G28: YEARLY | H28: MONTHLY | I28: BI-WEEKLY (1-15: Member; 16-31: Advisory) | J28: 46023 | K28: 46387 | L28: 46174 | M28: 46203 | Q28: YEARLY | R28: MONTHLY (MEMBERS) | S28: MONTHLY (MEMBERS) | T28: MONTHLY (MEMBERS) | U28: BI-WEEKLY (MEMBERS/ADVISORY) | V28: BI-WEEKLY (MEMBERS/ADVISORY) | W28: BI-WEEKLY (MEMBERS/ADVISORY) | X28: BI-WEEKLY (MEMBERS/ADVISORY) | Y28: BI-WEEKLY (ADVISORY) | Z28: 1st Half - Members involvement 2nd Half - As per Advisory DMCE: Rates effective 1st June 2026 | AA28: =IFERROR(NETWORKDAYS(K28,$AC$1),"-") -> -184 | AB28: =IFERROR(NETWORKDAYS(M28,$AC$1),"-") -> -52
A29: =VLOOKUP(D29,'[1]WWA Timelines '!$A:$A,1,0) -> KLN | B29: GLOBAL | C29: Sunil | D29: KLN | E29: JENS POTTSCHUL | F29: IRTASIA | G29: QUARTERLY | H29: MONTHLY | I29: BI-WEEKLY (1-15: Member; 16-31: Advisory) | J29: 46204 | K29: 46295 | L29: 46174 | M29: 46203 | N29: BI-WEEKLY (ADVISORY) | O29: BI-WEEKLY (ADVISORY) | R29: MONTHLY (MEMBERS) | S29: MONTHLY (MEMBERS) | T29: QUARTERLY (MEMBERS) | U29: BI-WEEKLY (MEMBERS/ADVISORY) | V29: BI-WEEKLY (MEMBERS/ADVISORY) | W29: BI-WEEKLY (MEMBERS/ADVISORY) | X29: BI-WEEKLY (MEMBERS/ADVISORY) | Y29: BI-WEEKLY (ADVISORY) | Z29: 1st Half - Members involvement 2nd Half - As per Advisory | AA29: =IFERROR(NETWORKDAYS(K29,$AC$1),"-") -> -118 | AB29: =IFERROR(NETWORKDAYS(M29,$AC$1),"-") -> -52
A30: =VLOOKUP(D30,'[1]WWA Timelines '!$A:$A,1,0) -> KINTETSU | B30: GLOBAL | C30: Sunil | D30: KINTETSU | E30: JENS POTTSCHUL/MICHELLE YU | F30: IRTASIA | G30: 6 MONTHS | H30: MONTHLY | I30: BI-WEEKLY (1-15: Member; 16-31: Advisory) | J30: 46204 | K30: 46387 | L30: 46174 | M30: 46203 | R30: MONTHLY (MEMBERS) | S30: MONTHLY (MEMBERS) | T30: MONTHLY (MEMBERS) | U30: BI-WEEKLY (MEMBERS/ADVISORY) | V30: BI-WEEKLY (MEMBERS/ADVISORY) | W30: BI-WEEKLY (MEMBERS/ADVISORY) | X30: BI-WEEKLY (MEMBERS/ADVISORY) | Y30: BI-WEEKLY (ADVISORY) | Z30: 1st Half - Members involvement 2nd Half - As per Advisory | AA30: =IFERROR(NETWORKDAYS(K30,$AC$1),"-") -> -184 | AB30: =IFERROR(NETWORKDAYS(M30,$AC$1),"-") -> -52
A31: =VLOOKUP(D31,'[1]WWA Timelines '!$A:$A,1,0) -> KUEHNE & NAGEL | B31: GLOBAL | C31: Aseem | D31: KUEHNE & NAGEL | E31: MARTIN SCHULZ/NADINE BEER | F31: NADINE | G31: YEARLY | H31: MONTHLY | I31: MONTHLY (MEMBERS) | J31: 46023 | K31: 46387 | L31: 46174 | M31: 46203 | N31: BI-WEEKLY (ADVISORY) | O31: BI-WEEKLY (ADVISORY) | R31: MONTHLY (MEMBERS) | S31: MONTHLY (MEMBERS) | T31: INCL. IN OFR | U31: MONTHLY (MEMBERS) | V31: MONTHLY (MEMBERS) | W31: MONTHLY (MEMBERS) | X31: MONTHLY (MEMBERS) | Y31: MONTHLY (MEMBERS) | Z31: UNDER EDS | AA31: =IFERROR(NETWORKDAYS(K31,$AC$1),"-") -> -184 | AB31: =IFERROR(NETWORKDAYS(M31,$AC$1),"-") -> -52
A32: =VLOOKUP(D32,'[1]WWA Timelines '!$A:$A,1,0) -> LESCHACO | B32: GLOBAL | C32: Rohan | D32: LESCHACO | E32: MARTIN SCHULZ/NADINE BEER | F32: NADINE | G32: YEARLY | H32: MONTHLY | I32: BI-WEEKLY (1-15: Member; 16-31: Advisory) | J32: 46023 | K32: 46387 | L32: 46174 | M32: 46203 | N32: BI-WEEKLY (ADVISORY) | O32: BI-WEEKLY (ADVISORY) | R32: MONTHLY (MEMBERS) | S32: MONTHLY (MEMBERS) | T32: MONTHLY (MEMBERS) | U32: BI-WEEKLY (MEMBERS/ADVISORY) | V32: BI-WEEKLY (MEMBERS/ADVISORY) | W32: BI-WEEKLY (MEMBERS/ADVISORY) | X32: EXCL. AS PER ADVISORY | Y32: EXCL. AS PER ADVISORY | Z32: 1st Half - Members involvement 2nd Half - As per Advisory | AA32: =IFERROR(NETWORKDAYS(K32,$AC$1),"-") -> -184 | AB32: =IFERROR(NETWORKDAYS(M32,$AC$1),"-") -> -52
A33: =VLOOKUP(D33,'[1]WWA Timelines '!$A:$A,1,0) -> LIGENTIA (RA) | B33: REGIONAL | C33: Rohan | D33: LIGENTIA (RA) | E33: MARY-ANNE CHUA/CHRISTINE ZHENG | F33: IRTASIA | G33: YEARLY | H33: MONTHLY | I33: BI-WEEKLY (1-15: Member; 16-31: Advisory) | J33: 46023 | K33: 46387 | L33: 46174 | M33: 46203 | N33: BI-WEEKLY (ADVISORY) | O33: BI-WEEKLY (ADVISORY) | R33: MONTHLY (MEMBERS) | S33: MONTHLY (MEMBERS) | T33: MONTHLY (MEMBERS) | U33: BI-WEEKLY (MEMBERS/ADVISORY) | V33: BI-WEEKLY (MEMBERS/ADVISORY) | W33: BI-WEEKLY (MEMBERS/ADVISORY) | X33: BI-WEEKLY (MEMBERS/ADVISORY) | Y33: EXCL. AS PER ADVISORY | Z33: 1st Half - Members involvement 2nd Half - As per Advisory | AA33: =IFERROR(NETWORKDAYS(K33,$AC$1),"-") -> -184 | AB33: =IFERROR(NETWORKDAYS(M33,$AC$1),"-") -> -52
A34: =VLOOKUP(D34,'[1]WWA Timelines '!$A:$A,1,0) -> LOGISTEED (RA) | B34: REGIONAL | C34: Sonali | D34: LOGISTEED (RA) | E34: MARY-ANNE CHUA | F34: IRTASIA | G34: YEARLY | H34: MONTHLY | I34: BI-WEEKLY (1-15: Member; 16-31: Advisory) | J34: 46023 | K34: 46387 | L34: 46174 | M34: 46203 | N34: BI-WEEKLY (ADVISORY) | O34: BI-WEEKLY (ADVISORY) | R34: MONTHLY (MEMBERS) | S34: MONTHLY (MEMBERS) | T34: MONTHLY (MEMBERS) | U34: BI-WEEKLY (MEMBERS/ADVISORY) | V34: BI-WEEKLY (MEMBERS/ADVISORY) | W34: BI-WEEKLY (MEMBERS/ADVISORY) | X34: BI-WEEKLY (MEMBERS/ADVISORY) | Y34: BI-WEEKLY (ADVISORY) | Z34: 1st Half - Members involvement 2nd Half - As per Advisory | AA34: =IFERROR(NETWORKDAYS(K34,$AC$1),"-") -> -184 | AB34: =IFERROR(NETWORKDAYS(M34,$AC$1),"-") -> -52
A35: =VLOOKUP(D35,'[1]WWA Timelines '!$A:$A,1,0) -> MAERSK LOGISTICS GLOBAL | B35: GLOBAL | C35: Sonali | D35: MAERSK LOGISTICS GLOBAL | E35: SUSANNE ELSBORG-JENSEN | F35: SANTIAGO | G35: 6 MONTHS | H35: MONTHLY | I35: BI-WEEKLY (1-15: Member; 16-31: Advisory) | J35: 46204 | K35: 46387 | L35: 46174 | M35: 46203 | R35: MONTHLY (MEMBERS) | S35: MONTHLY (MEMBERS) | T35: MONTHLY (MEMBERS) | U35: BI-WEEKLY (MEMBERS/ADVISORY) | V35: BI-WEEKLY (MEMBERS/ADVISORY) | W35: BI-WEEKLY (MEMBERS/ADVISORY) | X35: BI-WEEKLY (MEMBERS/ADVISORY) | Y35: BI-WEEKLY (ADVISORY) | Z35: 1st Half - Members involvement 2nd Half - As per Advisory | AA35: =IFERROR(NETWORKDAYS(K35,$AC$1),"-") -> -184 | AB35: =IFERROR(NETWORKDAYS(M35,$AC$1),"-") -> -52
A36: =VLOOKUP(D36,'[1]WWA Timelines '!$A:$A,1,0) -> MONDIALE VGL (RA) | B36: REGIONAL | C36: Sachin | D36: MONDIALE VGL (RA) | E36: JOHN FORSTER | F36: KERRY HIRST | G36: QUARTERLY | H36: QUARTERLY | I36: BI-WEEKLY (1-15: Member; 16-31: Advisory) | J36: 46204 | K36: 46295 | L36: 46204 | M36: 46295 | N36: BI-WEEKLY (ADVISORY) | O36: BI-WEEKLY (ADVISORY) | R36: MONTHLY (MEMBERS) | S36: MONTHLY (MEMBERS) | T36: INCL. IN OFR | U36: BI-WEEKLY (MEMBERS/ADVISORY) | V36: BI-WEEKLY (MEMBERS/ADVISORY) | W36: BI-WEEKLY (MEMBERS/ADVISORY) | X36: BI-WEEKLY (MEMBERS/ADVISORY) | Y36: EXCL. AS PER ADVISORY | Z36: 1st Half - Members involvement 2nd Half - As per Advisory | AA36: =IFERROR(NETWORKDAYS(K36,$AC$1),"-") -> -118 | AB36: =IFERROR(NETWORKDAYS(M36,$AC$1),"-") -> -118
A37: =VLOOKUP(D37,'[1]WWA Timelines '!$A:$A,1,0) -> MORRISON EXPRESS (RA) | B37: REGIONAL | C37: Rohan | D37: MORRISON EXPRESS (RA) | E37: KEVIN TAYLOR | F37: RONAN TEOH | G37: YEARLY | H37: MONTHLY | I37: BI-WEEKLY (1-15: Member; 16-31: Advisory) | J37: 46023 | K37: 46387 | L37: 46174 | M37: 46203 | N37: BI-WEEKLY (ADVISORY) | O37: BI-WEEKLY (ADVISORY) | R37: MONTHLY (MEMBERS) | S37: MONTHLY (MEMBERS) | T37: MONTHLY (MEMBERS) | U37: BI-WEEKLY (MEMBERS/ADVISORY) | V37: BI-WEEKLY (MEMBERS/ADVISORY) | W37: BI-WEEKLY (MEMBERS/ADVISORY) | X37: BI-WEEKLY (MEMBERS/ADVISORY) | Y37: EXCL. AS PER ADVISORY | Z37: 1st Half - Members involvement 2nd Half - As per Advisory | AA37: =IFERROR(NETWORKDAYS(K37,$AC$1),"-") -> -184 | AB37: =IFERROR(NETWORKDAYS(M37,$AC$1),"-") -> -52
A38: =VLOOKUP(D38,'[1]WWA Timelines '!$A:$A,1,0) -> NIPPON NX | B38: GLOBAL | C38: Sachin | D38: NIPPON NX | E38: JENS POTTSCHUL | F38: IRTASIA | G38: YEARLY | H38: QUARTERLY | I38: BI-WEEKLY (ADVISORY) | J38: 46023 | K38: 46387 | L38: 46204 | M38: 46295 | N38: BI-WEEKLY (ADVISORY) | O38: BI-WEEKLY (ADVISORY) | R38: QUARTERLY | S38: QUARTERLY | T38: QUARTERLY | U38: BI-WEEKLY (ADVISORY) | V38: BI-WEEKLY (ADVISORY) | W38: BI-WEEKLY (ADVISORY) | X38: BI-WEEKLY (ADVISORY) | Y38: BI-WEEKLY (ADVISORY) | AA38: =IFERROR(NETWORKDAYS(K38,$AC$1),"-") -> -184 | AB38: =IFERROR(NETWORKDAYS(M38,$AC$1),"-") -> -118
A39: =VLOOKUP(D39,'[1]WWA Timelines '!$A:$A,1,0) -> NNR | B39: GLOBAL | C39: Krushna | D39: NNR | E39: JENS POTTSCHUL | F39: - | G39: BI-WEEKLY | H39: BI-WEEKLY | I39: BI-WEEKLY (GRDB) | J39: 46189 | K39: 46203 | L39: 46189 | M39: 46203 | R39: GRDB | S39: GRDB | T39: GRDB | U39: BI-WEEKLY (ADVISORY) | V39: BI-WEEKLY (ADVISORY) | W39: BI-WEEKLY (ADVISORY) | AA39: =IFERROR(NETWORKDAYS(K39,$AC$1),"-") -> -52 | AB39: =IFERROR(NETWORKDAYS(M39,$AC$1),"-") -> -52
A40: =VLOOKUP(D40,'[1]WWA Timelines '!$A:$A,1,0) -> NTG AIR & OCEAN | B40: GLOBAL | C40: Krushna | D40: NTG AIR & OCEAN | E40: SUSANNE ELSBORG-JENSEN | F40: SANTIAGO | G40: YEARLY | H40: MONTHLY | I40: BI-WEEKLY (1-15: Member; 16-31: Advisory) | J40: 46174 | K40: 46387 | L40: 46174 | M40: 46203 | N40: BI-WEEKLY (ADVISORY) | O40: BI-WEEKLY (ADVISORY) | R40: MONTHLY (MEMBERS) | S40: MONTHLY (MEMBERS) | T40: MONTHLY (MEMBERS) | U40: BI-WEEKLY (MEMBERS/ADVISORY) | V40: BI-WEEKLY (MEMBERS/ADVISORY) | W40: BI-WEEKLY (MEMBERS/ADVISORY) | X40: BI-WEEKLY (MEMBERS/ADVISORY) | Y40: BI-WEEKLY (ADVISORY) | AA40: =IFERROR(NETWORKDAYS(K40,$AC$1),"-") -> -184 | AB40: =IFERROR(NETWORKDAYS(M40,$AC$1),"-") -> -52
A41: =VLOOKUP(D41,'[1]WWA Timelines '!$A:$A,1,0) -> OIA | B41: GLOBAL | C41: Aseem | D41: OIA | E41: KEVIN TAYLOR | F41: HELEN | G41: QUARTERLY | H41: QUARTERLY | I41: BI-WEEKLY (1-15: Member; 16-31: Advisory) | J41: 46204 | K41: 46295 | L41: 46204 | M41: 46295 | R41: MONTHLY (MEMBERS) | S41: MONTHLY (MEMBERS) | T41: QUARTERLY (MEMBERS) | U41: BI-WEEKLY (MEMBERS/ADVISORY) | V41: BI-WEEKLY (MEMBERS/ADVISORY) | W41: BI-WEEKLY (MEMBERS/ADVISORY) | X41: BI-WEEKLY (MEMBERS/ADVISORY) | Y41: BI-WEEKLY (ADVISORY) | Z41: 1st Half - Members involvement 2nd Half - As per Advisory | AA41: =IFERROR(NETWORKDAYS(K41,$AC$1),"-") -> -118 | AB41: =IFERROR(NETWORKDAYS(M41,$AC$1),"-") -> -118
A42: =VLOOKUP(D42,'[1]WWA Timelines '!$A:$A,1,0) -> PSA BDP | B42: GLOBAL | C42: Sonali | D42: PSA BDP | E42: JAKOB BLUHME | F42: SANTIAGO | G42: YEARLY | H42: MONTHLY | I42: BI-WEEKLY (1-15: Member; 16-31: Advisory) | J42: 46023 | K42: 46387 | L42: 46174 | M42: 46203 | N42: BI-WEEKLY (ADVISORY) | O42: BI-WEEKLY (ADVISORY) | R42: MONTHLY (MEMBERS) | S42: MONTHLY (MEMBERS) | T42: MONTHLY (MEMBERS) | U42: BI-WEEKLY (MEMBERS/ADVISORY) | V42: BI-WEEKLY (MEMBERS/ADVISORY) | W42: BI-WEEKLY (MEMBERS/ADVISORY) | X42: BI-WEEKLY (MEMBERS/ADVISORY) | Y42: BI-WEEKLY (ADVISORY) | Z42: 1st Half - Members involvement 2nd Half - As per Advisory | AA42: =IFERROR(NETWORKDAYS(K42,$AC$1),"-") -> -184 | AB42: =IFERROR(NETWORKDAYS(M42,$AC$1),"-") -> -52
A43: =VLOOKUP(D43,'[1]WWA Timelines '!$A:$A,1,0) -> RHENUS | B43: GLOBAL | C43: Sunil | D43: RHENUS | E43: JENS POTTSCHUL | F43: IRTASIA | G43: YEARLY | H43: MONTHLY | I43: BI-WEEKLY (1-15: Member; 16-31: Advisory) | J43: 45748 | K43: 46477 | L43: 46174 | M43: 46203 | N43: BI-WEEKLY (ADVISORY) | O43: BI-WEEKLY (ADVISORY) | R43: MONTHLY (MEMBERS) | S43: MONTHLY (MEMBERS) | T43: QUARTERLY | U43: BI-WEEKLY (MEMBERS/ADVISORY) | V43: BI-WEEKLY (MEMBERS/ADVISORY) | W43: BI-WEEKLY (MEMBERS/ADVISORY) | X43: BI-WEEKLY (MEMBERS/ADVISORY) | Y43: EXCL. AS PER ADVISORY | AA43: =IFERROR(NETWORKDAYS(K43,$AC$1),"-") -> -248 | AB43: =IFERROR(NETWORKDAYS(M43,$AC$1),"-") -> -52
A44: =VLOOKUP(D44,'[1]WWA Timelines '!$A:$A,1,0) -> RIM LOGISTICS | B44: GLOBAL | C44: Sunil | D44: RIM LOGISTICS | E44: RYAN ROBERT HOWELL | F44: SANTIAGO | G44: YEARLY | H44: MONTHLY | I44: BI-WEEKLY (1-15: Member; 16-31: Advisory) | J44: 46023 | K44: 46387 | L44: 46174 | M44: 46203 | N44: BI-WEEKLY (ADVISORY) | O44: BI-WEEKLY (ADVISORY) | R44: MONTHLY (MEMBERS) | S44: MONTHLY (MEMBERS) | T44: QUARTERLY | U44: BI-WEEKLY (MEMBERS/ADVISORY) | V44: BI-WEEKLY (MEMBERS/ADVISORY) | W44: BI-WEEKLY (MEMBERS/ADVISORY) | X44: BI-WEEKLY (MEMBERS/ADVISORY) | Y44: BI-WEEKLY (ADVISORY) | Z44: 1st Half - Members involvement 2nd Half - As per Advisory | AA44: =IFERROR(NETWORKDAYS(K44,$AC$1),"-") -> -184 | AB44: =IFERROR(NETWORKDAYS(M44,$AC$1),"-") -> -52
A45: =VLOOKUP(D45,'[1]WWA Timelines '!$A:$A,1,0) -> ROHLIG | B45: GLOBAL | C45: Sunil | D45: ROHLIG | E45: MARTIN SCHULZ/NADINE BEER | F45: NADINE | G45: YEARLY | H45: MONTHLY | I45: BI-WEEKLY (1-15: Member; 16-31: Advisory) | J45: 46023 | K45: 46387 | L45: 46174 | M45: 46203 | N45: BI-WEEKLY (ADVISORY) | O45: BI-WEEKLY (ADVISORY) | R45: MONTHLY (MEMBERS) | S45: MONTHLY (MEMBERS) | T45: QUARTERLY | U45: BI-WEEKLY (MEMBERS/ADVISORY) | V45: BI-WEEKLY (MEMBERS/ADVISORY) | W45: BI-WEEKLY (MEMBERS/ADVISORY) | X45: BI-WEEKLY (MEMBERS/ADVISORY) | Y45: EXCL. AS PER ADVISORY | Z45: 1st Half - Members involvement 2nd Half - As per Advisory | AA45: =IFERROR(NETWORKDAYS(K45,$AC$1),"-") -> -184 | AB45: =IFERROR(NETWORKDAYS(M45,$AC$1),"-") -> -52
A46: =VLOOKUP(D46,'[1]WWA Timelines '!$A:$A,1,0) -> SCAN GLOBAL LOGISTICS | B46: GLOBAL | C46: Shraddha | D46: SCAN GLOBAL LOGISTICS | E46: SUSANNE ELSBORG-JENSEN | F46: SANTIAGO | G46: YEARLY | H46: BI-WEEKLY | I46: BI-WEEKLY (MEMBERS) | J46: 46023 | K46: 46387 | L46: 46189 | M46: 46203 | N46: BI-WEEKLY (ADVISORY) | O46: BI-WEEKLY (ADVISORY) | R46: BI-WEEKLY (MEMBERS) | S46: BI-WEEKLY (MEMBERS) | T46: BI-WEEKLY (MEMBERS) | U46: BI-WEEKLY (MEMBERS) | V46: BI-WEEKLY (MEMBERS) | W46: BI-WEEKLY (MEMBERS) | X46: BI-WEEKLY (MEMBERS) | Y46: BI-WEEKLY (ADVISORY) | AA46: =IFERROR(NETWORKDAYS(K46,$AC$1),"-") -> -184 | AB46: =IFERROR(NETWORKDAYS(M46,$AC$1),"-") -> -52
A47: =VLOOKUP(D47,'[1]WWA Timelines '!$A:$A,1,0) -> SCAN-SHIPPING (RA) | B47: REGIONAL | C47: Sonali | D47: SCAN-SHIPPING (RA) | E47: METTE KARAPETIAN / SUSANNE ELSBORG-JENSEN | F47: SUSANNE / SANTIAGO | G47: YEARLY | H47: MONTHLY | I47: BI-WEEKLY (1-15: Member; 16-31: Advisory) | J47: 46023 | K47: 46387 | L47: 46174 | M47: 46203 | R47: MONTHLY (MEMBERS) | S47: MONTHLY (MEMBERS) | T47: MONTHLY (MEMBERS) | U47: BI-WEEKLY (MEMBERS/ADVISORY) | V47: BI-WEEKLY (MEMBERS/ADVISORY) | W47: BI-WEEKLY (MEMBERS/ADVISORY) | X47: BI-WEEKLY (MEMBERS/ADVISORY) | Y47: BI-WEEKLY (ADVISORY) | Z47: 1st Half - Members involvement 2nd Half - As per Advisory | AA47: =IFERROR(NETWORKDAYS(K47,$AC$1),"-") -> -184 | AB47: =IFERROR(NETWORKDAYS(M47,$AC$1),"-") -> -52
A48: =VLOOKUP(D48,'[1]WWA Timelines '!$A:$A,1,0) -> SEKO | B48: GLOBAL | C48: Aseem | D48: SEKO | E48: JENS POTTSCHUL | F48: IRTASIA | G48: 9 MONTHS | H48: MONTHLY | I48: BI-WEEKLY (1-15: Member; 16-31: Advisory) | J48: 46113 | K48: 46387 | L48: 46174 | M48: 46203 | N48: BI-WEEKLY (ADVISORY) | O48: BI-WEEKLY (ADVISORY) | R48: MONTHLY (MEMBERS) | S48: MONTHLY (MEMBERS) | T48: MONTHLY (MEMBERS) | U48: BI-WEEKLY (MEMBERS/ADVISORY) | V48: BI-WEEKLY (MEMBERS/ADVISORY) | W48: BI-WEEKLY (MEMBERS/ADVISORY) | X48: BI-WEEKLY (MEMBERS/ADVISORY) | Y48: BI-WEEKLY (MEMBERS/ADVISORY) | Z48: 1st Half - Members involvement 2nd Half - As per Advisory | AA48: =IFERROR(NETWORKDAYS(K48,$AC$1),"-") -> -184 | AB48: =IFERROR(NETWORKDAYS(M48,$AC$1),"-") -> -52
A49: =VLOOKUP(D49,'[1]WWA Timelines '!$A:$A,1,0) -> TOLL GLOBAL FORWARDING | B49: GLOBAL | C49: Shraddha | D49: TOLL GLOBAL FORWARDING | E49: JENS POTTSCHUL | F49: IRTASIA | G49: YEARLY | H49: MONTHLY | I49: BI-WEEKLY (1-15: Member; 16-31: Advisory) | J49: 46023 | K49: 46387 | L49: 46174 | M49: 46203 | N49: BI-WEEKLY (ADVISORY) | O49: BI-WEEKLY (ADVISORY) | R49: MONTHLY (MEMBERS) | S49: MONTHLY (MEMBERS) | T49: QUARTERLY | U49: BI-WEEKLY (MEMBERS/ADVISORY) | V49: BI-WEEKLY (MEMBERS/ADVISORY) | W49: BI-WEEKLY (MEMBERS/ADVISORY) | X49: BI-WEEKLY (MEMBERS/ADVISORY) | Y49: EXCL. AS PER ADVISORY | AA49: =IFERROR(NETWORKDAYS(K49,$AC$1),"-") -> -184 | AB49: =IFERROR(NETWORKDAYS(M49,$AC$1),"-") -> -52
A50: =VLOOKUP(D50,'[1]WWA Timelines '!$A:$A,1,0) -> UPS GLOBAL | B50: GLOBAL | C50: Samuel | D50: UPS GLOBAL | E50: DIANE KAISER | F50: DIANE KAISER | G50: YEARLY | H50: MONTHLY | I50: BI-WEEKLY (MEMBERS) | J50: 46082 | K50: 46387 | L50: 46174 | M50: 46203 | N50: BI-WEEKLY (ADVISORY) | O50: BI-WEEKLY (ADVISORY) | R50: MONTHLY (MEMBERS) | S50: MONTHLY (MEMBERS) | T50: MONTHLY (MEMBERS) | U50: BI-WEEKLY (MEMBERS) | V50: BI-WEEKLY (MEMBERS) | W50: BI-WEEKLY (MEMBERS) | X50: BI-WEEKLY (MEMBERS) | Y50: EXCL. AS PER ADVISORY | AA50: =IFERROR(NETWORKDAYS(K50,$AC$1),"-") -> -184 | AB50: =IFERROR(NETWORKDAYS(M50,$AC$1),"-") -> -52
A51: =VLOOKUP(D51,'[1]WWA Timelines '!$A:$A,1,0) -> YUSEN INTRA ASIA | B51: GLOBAL | C51: Kajal | D51: YUSEN INTRA ASIA | E51: JENS POTTSCHUL | F51: IRTASIA | G51: 6 MONTHS | H51: 6 MONTHS | I51: BI-WEEKLY (1-15: Member; 16-31: Advisory) | J51: 46113 | K51: 46295 | L51: 46113 | M51: 46295 | R51: MONTHLY (MEMBERS) | S51: MONTHLY (MEMBERS) | T51: NA | U51: BI-WEEKLY (MEMBERS/ADVISORY) | V51: BI-WEEKLY (MEMBERS/ADVISORY) | W51: BI-WEEKLY (MEMBERS/ADVISORY) | X51: BI-WEEKLY (MEMBERS/ADVISORY) | Y51: BI-WEEKLY (ADVISORY) | Z51: 1st Half - Members involvement 2nd Half - As per Advisory | AA51: =IFERROR(NETWORKDAYS(K51,$AC$1),"-") -> -118 | AB51: =IFERROR(NETWORKDAYS(M51,$AC$1),"-") -> -118
A52: =VLOOKUP(D52,'[1]WWA Timelines '!$A:$A,1,0) -> YUSEN (USA) IMP/EXP | B52: GLOBAL | C52: Kajal | D52: YUSEN (USA) IMP/EXP | E52: BRUCE ERICSON | F52: HELEN | G52: QUARTERLY | H52: QUARTERLY | I52: BI-WEEKLY (1-15: Member; 16-31: Advisory) | J52: 46204 | K52: 46295 | L52: 46204 | M52: 46295 | N52: BI-WEEKLY (ADVISORY) | O52: BI-WEEKLY (ADVISORY) | R52: MONTHLY (MEMBERS) | S52: MONTHLY (MEMBERS) | T52: QUARTERLY | U52: BI-WEEKLY (MEMBERS/ADVISORY) | V52: BI-WEEKLY (MEMBERS/ADVISORY) | W52: BI-WEEKLY (MEMBERS/ADVISORY) | X52: BI-WEEKLY (MEMBERS/ADVISORY) | Y52: BI-WEEKLY (ADVISORY) | Z52: 1st Half - Members involvement 2nd Half - As per Advisory | AA52: =IFERROR(NETWORKDAYS(K52,$AC$1),"-") -> -118 | AB52: =IFERROR(NETWORKDAYS(M52,$AC$1),"-") -> -118
A53: =VLOOKUP(D53,'[1]WWA Timelines '!$A:$A,1,0) -> YUSEN EUROPE | B53: GLOBAL | C53: Kajal | D53: YUSEN EUROPE | E53: SYLVIA LATHOUWERS | F53: NADINE BEER | G53: QUARTERLY | H53: QUARTERLY | I53: BI-WEEKLY (1-15: Member; 16-31: Advisory) | J53: 46204 | K53: 46295 | L53: 46204 | M53: 46295 | R53: MONTHLY (MEMBERS) | S53: MONTHLY (MEMBERS) | T53: QUARTERLY (MEMBERS) | U53: BI-WEEKLY (MEMBERS/ADVISORY) | V53: BI-WEEKLY (MEMBERS/ADVISORY) | W53: BI-WEEKLY (MEMBERS/ADVISORY) | X53: BI-WEEKLY (MEMBERS/ADVISORY) | Y53: EXCL. AS PER ADVISORY | AA53: =IFERROR(NETWORKDAYS(K53,$AC$1),"-") -> -118 | AB53: =IFERROR(NETWORKDAYS(M53,$AC$1),"-") -> -118
A54: =VLOOKUP(D54,'[1]WWA Timelines '!$A:$A,1,0) -> YUSEN LATAM (IMPORT) | B54: GLOBAL | C54: Kajal | D54: YUSEN LATAM (IMPORT) | E54: JENS POTTSCHUL | F54: IRTASIA | G54: 6 MONTHS | H54: 6 MONTHS | I54: BI-WEEKLY (1-15: Member; 16-31: Advisory) | J54: 46113 | K54: 46295 | L54: 46113 | M54: 46295 | R54: MONTHLY (MEMBERS) | S54: MONTHLY (MEMBERS) | T54: QUARTERLY | U54: BI-WEEKLY (MEMBERS/ADVISORY) | V54: BI-WEEKLY (MEMBERS/ADVISORY) | W54: BI-WEEKLY (MEMBERS/ADVISORY) | X54: BI-WEEKLY (MEMBERS/ADVISORY) | Y54: BI-WEEKLY (ADVISORY) | Z54: 1st Half - Members involvement 2nd Half - As per Advisory | AA54: =IFERROR(NETWORKDAYS(K54,$AC$1),"-") -> -118 | AB54: =IFERROR(NETWORKDAYS(M54,$AC$1),"-") -> -118

Sheet FAK_Mastersheet
A1: 46198 | B1: GENERAL OVERVIEW | M1: OWNER | O1: SURCHARGES UPDATE OVERVIEW | AD1: CONDITIONAL CHARGES AVAILABLE IN RATE CARD | AJ1: GENERAL
A2: WWA CUSTOMER | B2: FREQUENCY (FOB/PLC) | C2: FREQUENCY (OFR) | D2: FREQUENCY (OFR SURCHARGES) | E2: FOB/PLC VALIDITY EFFECTIVE DATE | F2: FOB/PLC VALIDITY EXPIRY DATE | G2: OFR VALIDITY EFFECTIVE DATE | H2: OFR VALIDITY EXPIRY DATE | I2: FOB/PLC FOLLOW-UP | J2: OFR FOLLOW-UP | K2: UPDATE TYPE | L2: HANDLE VIA | M2: GLOBAL/REGIONAL ACCOUNT OWNER | N2: RFQ OWNER | O2: SOLAS | P2: FILING | Q2: MANDATORY ICS2 ADMIN FEE | R2: CONDITIONAL ICS2 FILING FEE | S2: ORIGIN E-INF | T2: DESTINATION E-INF | U2: MPCI FILING FEE | V2: IMO2020 | W2: GRI | X2: ETSS_FEMS | Y2: ESF | Z2: E-PSS | AA2: LWS_PCS | AB2: E-BAF | AC2: WRS | AD2: HAZ | AE2: 3RD PARTY CFS | AF2: NON-STACKABLE | AG2: STORAGE FREE DAYS | AH2: STORAGE CHARGES | AI2: BMSB | AJ2: Commodity | AK2: Cargo Ratio | AL2: Currency (FOB-PLC) | AM2: Currency (OFR) | AN2: ALTERNATIVE CFS | AO2: NEGATIVE RATES ACCEPTED (Y/N) | AP2: APPROVAL NEEDED FOR OFF CYCLE UPDATE | AQ2: SUBMISSION BEFORE EFFECTIVE DATE | AR2: DIRECT SHARING WITH MEMBERS (Y/N) | AS2: (NON) CENTRALIZED | AT2: OWNER COMMENTS (IF ANY)
A3: AIT (RA) | B3: Yearly | C3: Yearly | D3: Bi-Weekly | E3: 46143 | F3: 46387 | G3: 46143 | H3: 46387 | I3: =IFERROR(NETWORKDAYS($A$1,Table1[[#This Row],[FOB/PLC VALIDITY EXPIRY DATE ]]),"-") -> 136 | J3: =IFERROR(NETWORKDAYS($A$1,Table1[[#This Row],[OFR VALIDITY EXPIRY DATE ]]),"-") -> 136 | K3: OFR & Service Update Request | L3: RFQ TOOL - https://rfqtool.wwalliance.com | M3: Kevin Taylor | N3: Helen Li | O3: Yearly | P3: Yearly | Q3: Yearly | R3: Yearly | S3: Bi-Weekly | T3: Bi-Weekly | U3: Bi-Weekly | V3: Monthly | W3: Monthly | X3: Monthly | Y3: Bi-Weekly | Z3: Bi-Weekly | AA3: Bi-Weekly | AB3: Bi-Weekly | AC3: Bi-Weekly | AD3: Quote Separately For Class 3,6,8,9 | AE3: Quote Separately | AF3: Excluded | AG3: Quote Separately | AH3: Quote Separately | AI3: Excluded | AJ3: General Cargo FAK, (Non HAZ & HAZ Class 3,6,8,9) | AK3: 1:1000 | AL3: USD | AM3: USD | AN3: Not Allowed | AO3: Yes | AP3: No | AQ3: 3 | AR3: Yes | AS3: Yes | AT3: Regional account
A4: APL LOGISTICS | B4: Quarterly | C4: Quarterly | D4: Bi-Weekly | E4: 46204 | F4: 46295 | G4: 46204 | H4: 46295 | I4: =IFERROR(NETWORKDAYS($A$1,Table1[[#This Row],[FOB/PLC VALIDITY EXPIRY DATE ]]),"-") -> 70 | J4: =IFERROR(NETWORKDAYS($A$1,Table1[[#This Row],[OFR VALIDITY EXPIRY DATE ]]),"-") -> 70 | K4: OFR & Service Update Request | L4: CENTRIC - https://centric.wwalliance.com | M4: Michelly Yu | N4: IRTAsia | O4: Quarterly | P4: Quarterly | Q4: Quarterly | R4: Quarterly | S4: Bi-Weekly | T4: Bi-Weekly | U4: Bi-Weekly | V4: Quarterly | W4: Bi-Weekly | X4: Quarterly | Y4: Bi-Weekly | Z4: Bi-Weekly | AA4: Bi-Weekly | AB4: Bi-Weekly | AC4: Bi-Weekly | AD4: Excluded | AE4: Excluded | AF4: Excluded | AG4: Excluded | AH4: Excluded | AI4: Excluded | AJ4: General Cargo FAK, (Non HAZ) | AK4: 1 cbm = 1000 kgs | AL4: USD | AM4: USD | AN4: Allowed | AO4: No | AP4: Yes | AQ4: 12 | AR4: No | AS4: No | AT4: On an exceptional basis Rate Reductions can be made. But need to inform APLL and get their approval first. Also in general this should happen mainly through the adjustment of the surcharges.
A5: ARAMEX (RA) | B5: Yearly | C5: Monthly | D5: Bi-Weekly | E5: 46023 | F5: 46387 | G5: 46174 | H5: 46203 | I5: =IFERROR(NETWORKDAYS($A$1,Table1[[#This Row],[FOB/PLC VALIDITY EXPIRY DATE ]]),"-") -> 136 | J5: =IFERROR(NETWORKDAYS($A$1,Table1[[#This Row],[OFR VALIDITY EXPIRY DATE ]]),"-") -> 4 | K5: OFR & Service Update Request | L5: RFQ TOOL - https://rfqtool.wwalliance.com | M5: Elvira Takx / Mary Anne Chua | N5: IRTAsia | O5: Yearly | P5: Yearly | Q5: Yearly | R5: Yearly | S5: Bi-Weekly | T5: Bi-Weekly | U5: Bi-Weekly | V5: Monthly | W5: Monthly | X5: Monthly | Y5: Bi-Weekly | Z5: Bi-Weekly | AA5: Bi-Weekly | AB5: Bi-Weekly | AC5: Bi-Weekly | AD5: Excluded | AE5: Quote Separately | AF5: Excluded | AG5: Excluded | AH5: Excluded | AI5: Excluded | AJ5: General Cargo FAK, (Non HAZ) | AK5: 1:1 | AL5: Local Currency | AM5: USD | AN5: Allowed | AO5: No | AP5: Yes | AQ5: 5 | AR5: Yes | AS5: Yes | AT5: Regional Account
A6: BARSAN (RA) | B6: Yearly | C6: Monthly | D6: Bi-Weekly | E6: 46023 | F6: 46387 | G6: 46174 | H6: 46203 | I6: =IFERROR(NETWORKDAYS($A$1,Table1[[#This Row],[FOB/PLC VALIDITY EXPIRY DATE ]]),"-") -> 136 | J6: =IFERROR(NETWORKDAYS($A$1,Table1[[#This Row],[OFR VALIDITY EXPIRY DATE ]]),"-") -> 4 | K6: OFR & Service Update Request | L6: CENTRIC - https://centric.wwalliance.com | M6: Ryan Robert Howell | N6: Helen Li | O6: Yearly | P6: Yearly | Q6: Yearly | R6: Yearly | S6: Bi-Weekly | T6: Bi-Weekly | U6: Bi-Weekly | V6: Monthly | W6: Monthly | X6: Monthly | Y6: Bi-Weekly | Z6: Bi-Weekly | AA6: Bi-Weekly | AB6: Bi-Weekly | AC6: Excl. As Per Advisory | AD6: Excluded | AE6: Excluded | AF6: Excluded | AG6: Excluded | AH6: Excluded | AI6: Excluded | AJ6: General Cargo FAK, (Non HAZ) | AK6: 1:1 | AL6: Local Currency | AM6: USD | AN6: Not Allowed | AO6: Yes | AP6: Yes | AQ6: 3 | AR6: Yes | AS6: Yes | AT6: Regional Account
A7: CARGO PARTNER | B7: Yearly | C7: Monthly | D7: Bi-Weekly | E7: 46023 | F7: 46387 | G7: 46174 | H7: 46203 | I7: =IFERROR(NETWORKDAYS($A$1,Table1[[#This Row],[FOB/PLC VALIDITY EXPIRY DATE ]]),"-") -> 136 | J7: =IFERROR(NETWORKDAYS($A$1,Table1[[#This Row],[OFR VALIDITY EXPIRY DATE ]]),"-") -> 4 | K7: OFR & Service Update Request | L7: RFQ TOOL - https://rfqtool.wwalliance.com | M7: Martin Schulz | N7: Dennis Frankowski | O7: Yearly | P7: Yearly | Q7: Yearly | R7: Yearly | S7: Bi-Weekly | T7: Bi-Weekly | U7: Bi-Weekly | V7: Monthly | W7: Monthly | X7: Monthly | Y7: Bi-Weekly | Z7: Bi-Weekly | AA7: Bi-Weekly | AB7: Bi-Weekly | AC7: Bi-Weekly | AD7: Quote Separately For Class 3,6,8,9 | AE7: Excluded | AF7: Excluded | AG7: Excluded | AH7: Excluded | AI7: Quote Separately | AJ7: General Cargo FAK, (Non HAZ & HAZ Class 3,6,8,9) | AK7: 1:3 | AL7: USD/EUR | AM7: USD/EUR | AN7: Not Allowed | AO7: Yes | AP7: Yes | AQ7: 3 | AR7: Yes | AS7: Yes | AT7: Negative Rates Are Accepted As Long As End To End Rates Remain Positive, As Per March 1St 2026, Ofr Validity Will Become Monthly.
A8: CEVA | B8: Yearly | C8: Yearly | D8: Bi-Weekly | E8: 46023 | F8: 46387 | G8: 46082 | H8: 46387 | I8: =IFERROR(NETWORKDAYS($A$1,Table1[[#This Row],[FOB/PLC VALIDITY EXPIRY DATE ]]),"-") -> 136 | J8: =IFERROR(NETWORKDAYS($A$1,Table1[[#This Row],[OFR VALIDITY EXPIRY DATE ]]),"-") -> 136 | K8: OFR & Service Update Request | L8: CENTRIC - https://centric.wwalliance.com | M8: Jakob Bluhme | N8: Santiago | O8: Yearly | P8: Yearly | Q8: Yearly | R8: Yearly | S8: Bi-Weekly | T8: Bi-Weekly | U8: Bi-Weekly | V8: Monthly | W8: Monthly | X8: Monthly | Y8: Bi-Weekly | Z8: Bi-Weekly | AA8: Bi-Weekly | AB8: Bi-Weekly | AC8: Bi-Weekly | AD8: Quote Separately For Class 3,6,8,9 | AE8: Quote Separately | AF8: Excluded | AG8: Quote Separately | AH8: Quote Separately | AI8: Excluded | AJ8: General Cargo FAK, (Non HAZ & HAZ Class 3,6,8,9) | AK8: 1:1000 | AL8: Local Currency | AM8: USD/EUR | AN8: Not Allowed | AO8: Yes (Except OFR Surcharges) | AP8: Yes | AQ8: 3 | AR8: Yes | AS8: Yes | AT8: No Pre-Defined Eff: 1St Of Jan 2026 E-Inf - Maintained Separately In Bd Sheet, Combined In Rate Card Under "Landslide Surcharges"
A9: CH ROBINSON | B9: 6 Months | C9: Bi-Weekly | D9: Bi-Weekly | E9: 46188 | F9: 46401 | G9: 46188 | H9: 46217 | I9: =IFERROR(NETWORKDAYS($A$1,Table1[[#This Row],[FOB/PLC VALIDITY EXPIRY DATE ]]),"-") -> 146 | J9: =IFERROR(NETWORKDAYS($A$1,Table1[[#This Row],[OFR VALIDITY EXPIRY DATE ]]),"-") -> 14 | K9: OFR & Service Update Request | L9: RFQ TOOL - https://rfqtool.wwalliance.com | M9: Bruce Ericson | N9: Helen Li | O9: 6 Months | P9: 6 Months | Q9: 6 Months | R9: 6 Months | S9: Bi-Weekly | T9: Bi-Weekly | U9: Bi-Weekly | V9: Bi-Weekly | W9: Bi-Weekly | X9: Quarterly | Y9: Bi-Weekly | Z9: Bi-Weekly | AA9: Bi-Weekly | AB9: Bi-Weekly | AC9: Excl. As Per Advisory | AD9: Excluded | AE9: Excluded | AF9: Excluded | AG9: Excluded | AH9: Excluded | AI9: Excluded | AJ9: General Cargo FAK, (Non HAZ) | AK9: 1:1 | AL9: Local Currency | AM9: USD/EUR | AN9: Not Allowed | AO9: No | AP9: Yes-Increase; No-Decrease | AQ9: 6 | AR9: Yes | AS9: Yes | AT9: Demand From Chr Is To Submit 4 Business Days Prior Effective Date. / Customer Request That Pricing Be Adjusted Mid Term If There Are Large Fluctuation In Cost. Need To Notify Customer Of Lanes Changed And Reason. Explanation Provided For The Change Submitted E-Inf: Global Application: Please Apply Usd $3 W/M For All Landside Movements. This Amount Should Be Converted Into Local Currency Charges And Applied To Fob/Plc. United Kingdom Application: Please Apply Usd $5 W/M For Exports & Usd $3 W/M For Imports. These Amounts Should Also Be Converted Into Local Currency Charges And Applied To Fob/Plc. Usa Exception: Usa Is Exempt From This Exercise, As E-Inf Has Already Been Incorporated Into Fob/Plc. Euro Countries: All Countries Invoicing Fob/Plc In Euro Should Apply Eur €3 W/M Instead Of Usd. The Uk Remains Excluded From This Euro Application And Should Continue Applying E-Inf In Usd.
A10: CRANE WORLDWIDE | B10: Monthly | C10: Monthly | D10: Bi-Weekly | E10: 46204 | F10: 46234 | G10: 46174 | H10: 46203 | I10: =IFERROR(NETWORKDAYS($A$1,Table1[[#This Row],[FOB/PLC VALIDITY EXPIRY DATE ]]),"-") -> 27 | J10: =IFERROR(NETWORKDAYS($A$1,Table1[[#This Row],[OFR VALIDITY EXPIRY DATE ]]),"-") -> 4 | K10: OFR & Service Update Request | L10: CENTRIC - https://centric.wwalliance.com | M10: Mette Karapetian | N10: Chris Crowder / Helen Li | O10: Monthly | P10: Monthly | Q10: Monthly | R10: Monthly | S10: Bi-Weekly | T10: Bi-Weekly | U10: Bi-Weekly | V10: Monthly | W10: Monthly | X10: Monthly | Y10: Bi-Weekly | Z10: Bi-Weekly | AA10: Bi-Weekly | AB10: Bi-Weekly | AC10: Bi-Weekly | AD10: Quote Separately For Class 3,6,8,9 | AE10: Quote Separately | AF10: Excluded | AG10: Quote Separately | AH10: Quote Separately | AI10: Quote Separately | AJ10: General Cargo FAK, (Non HAZ & HAZ Class 3,6,8,9) | AK10: 1:1 | AL10: Local Currency | AM10: Usd | AN10: Not Allowed | AO10: Yes | AP10: Yes-Increase; No-Decrease | AQ10: 3 | AR10: Yes | AS10: Yes | AT10: -
A11: DACHSER (EXCL. INTRA ASIA) | B11: Yearly | C11: Monthly | D11: Bi-Weekly | E11: 46023 | F11: 46387 | G11: 46174 | H11: 46203 | I11: =IFERROR(NETWORKDAYS($A$1,Table1[[#This Row],[FOB/PLC VALIDITY EXPIRY DATE ]]),"-") -> 136 | J11: =IFERROR(NETWORKDAYS($A$1,Table1[[#This Row],[OFR VALIDITY EXPIRY DATE ]]),"-") -> 4 | K11: OFR & Service Update Request | L11: RFQ TOOL - https://rfqtool.wwalliance.com | M11: Martin Schulz | N11: Nadine | O11: Yearly | P11: Yearly | Q11: Yearly | R11: Yearly | S11: Bi-Weekly | T11: Bi-Weekly | U11: Bi-Weekly | V11: Monthly | W11: Monthly | X11: Monthly | Y11: Bi-Weekly | Z11: Bi-Weekly | AA11: Bi-Weekly | AB11: Bi-Weekly | AC11: Bi-Weekly | AD11: Quote Separately For Class 3,6,8,9 | AE11: Quote Separately | AF11: Excluded | AG11: Quote Separately | AH11: Quote Separately | AI11: Excluded | AJ11: General Cargo FAK, (Non HAZ & HAZ Class 3,6,8,9) | AK11: 1:1 | AL11: Local Currency | AM11: USD/EUR | AN11: Not Allowed | AO11: No | AP11: Yes | AQ11: 3 | AR11: Yes | AS11: Yes | AT11: Rates Are Transfered To Portrix. Hq Have An Issue With Too Many Updates Throughout The Month.
A12: DACHSER (AU/NZ) | B12: Yearly | C12: Quarterly | D12: - | E12: 45809 | F12: 46203 | G12: 46082 | H12: 46203 | I12: =IFERROR(NETWORKDAYS($A$1,Table1[[#This Row],[FOB/PLC VALIDITY EXPIRY DATE ]]),"-") -> 4 | J12: =IFERROR(NETWORKDAYS($A$1,Table1[[#This Row],[OFR VALIDITY EXPIRY DATE ]]),"-") -> 4 | K12: OFR & Service Update Request | L12: CENTRIC - https://centric.wwalliance.com | M12: Jens Pottschul | N12: IRTAsia/Maria Girlie | O12: Yearly | P12: Yearly | Q12: Yearly | R12: Yearly | S12: Bi-Weekly | T12: Bi-Weekly | U12: Bi-Weekly | V12: Quarterly | W12: Quarterly | X12: Na | Y12: Incl. In OFR | Z12: Incl. In OFR | AA12: Incl. In OFR | AB12: Excl. As Per Advisory | AC12: Excl. As Per Advisory | AD12: Quote Separately For Class 3,6,8,9 | AE12: Quote Separately | AF12: Excluded | AG12: Quote Separately | AH12: Quote Separately | AI12: Excluded | AJ12: General Cargo FAK, (Non HAZ & HAZ Class 3,6,8,9) | AK12: 1:1 | AL12: Local Currency | AM12: Usd | AN12: Not Allowed | AO12: Yes | AP12: Yes | AQ12: 5 | AR12: Yes | AS12: Yes | AT12: -
A13: DACHSER INTRA ASIA | B13: Yearly | C13: Yearly | D13: - | E13: 45809 | F13: 46203 | G13: 45809 | H13: 46203 | I13: =IFERROR(NETWORKDAYS($A$1,Table1[[#This Row],[FOB/PLC VALIDITY EXPIRY DATE ]]),"-") -> 4 | J13: =IFERROR(NETWORKDAYS($A$1,Table1[[#This Row],[OFR VALIDITY EXPIRY DATE ]]),"-") -> 4 | K13: OFR & Service Update Request | L13: RFQ TOOL - https://rfqtool.wwalliance.com | M13: Jens Pottschul | N13: IRTAsia/Maria Girlie | O13: Yearly | P13: Yearly | Q13: Yearly | R13: Yearly | S13: Bi-Weekly | T13: Bi-Weekly | U13: Bi-Weekly | V13: Yearly | W13: Yearly | X13: Na | Y13: Incl. In OFR | Z13: Incl. In OFR | AA13: Incl. In OFR | AB13: Bi-Weekly | AC13: Excl. As Per Advisory | AD13: Quote Separately For Class 3,6,8,9 | AE13: Quote Separately | AF13: Excluded | AG13: Quote Separately | AH13: Quote Separately | AI13: Excluded | AJ13: General Cargo FAK, (Non HAZ & HAZ Class 3,6,8,9) | AK13: 1:1 | AL13: Local Currency | AM13: Usd | AN13: Not Allowed | AO13: Yes | AP13: Yes | AQ13: 5 | AR13: Yes | AS13: Yes | AT13: Pre-Defined Fob/Plc
A14: DHL | B14: Yearly | C14: Yearly | D14: Quarterly | E14: 46023 | F14: 46387 | G14: 46113 | H14: 46387 | I14: =IFERROR(NETWORKDAYS($A$1,Table1[[#This Row],[FOB/PLC VALIDITY EXPIRY DATE ]]),"-") -> 136 | J14: =IFERROR(NETWORKDAYS($A$1,Table1[[#This Row],[OFR VALIDITY EXPIRY DATE ]]),"-") -> 136 | K14: OFR & Service Update Request | L14: CENTRIC - https://centric.wwalliance.com | M14: Jakob Bluhme | N14: Santiago | O14: Yearly | P14: Yearly | Q14: Yearly | R14: Yearly | S14: Bi-Weekly | T14: Bi-Weekly | U14: Bi-Weekly | V14: Yearly | W14: Yearly | X14: Yearly | Y14: Quarterly | Z14: Quarterly | AA14: Quarterly | AB14: All US Origins To All Destinations Worldwide USD 6.00 W/M, Intra Asia USD 3.00 W/M, All Other Trade Lanes WW USD 7.00 W/M. | AC14: Excl. As Per Advisory | AD14: Quote Separately For Class 3,6,8,9 | AE14: Excluded | AF14: Excluded | AG14: Excluded | AH14: Excluded | AI14: Excluded | AJ14: General Cargo FAK, (Non HAZ & HAZ Class 3,6,8,9) | AK14: 1:1 | AL14: Local Currency | AM14: USD/EUR | AN14: Not Allowed | AO14: Yes (Except ECRS) | AP14: Yes | AQ14: 5 | AR14: Yes | AS14: Yes | AT14: Pre-Defined Fob/Plc / Ofr Rates Valid For 3 Months. No Updates Locally Nor Updates In Global Tariff Allowed. Only Ems/Ecrs To Change Every Month E-Inf - Updated By Sm For Us Location Only, For Rest Nap
A15: DP WORLD | B15: Yearly | C15: Monthly | D15: Bi-Weekly | E15: 46023 | F15: 46387 | G15: 46174 | H15: 46203 | I15: =IFERROR(NETWORKDAYS($A$1,Table1[[#This Row],[FOB/PLC VALIDITY EXPIRY DATE ]]),"-") -> 136 | J15: =IFERROR(NETWORKDAYS($A$1,Table1[[#This Row],[OFR VALIDITY EXPIRY DATE ]]),"-") -> 4 | K15: OFR & Service Update Request | L15: RFQ TOOL - https://rfqtool.wwalliance.com | M15: Martin Schulz | N15: Nadine/Santiago | O15: Yearly | P15: Yearly | Q15: Yearly | R15: Yearly | S15: Bi-Weekly | T15: Bi-Weekly | U15: Bi-Weekly | V15: Monthly | W15: Monthly | X15: Monthly | Y15: Bi-Weekly | Z15: Bi-Weekly | AA15: Bi-Weekly | AB15: Bi-Weekly | AC15: Bi-Weekly | AD15: Excluded | AE15: Quote Separately | AF15: Excluded | AG15: Quote Separately | AH15: Quote Separately | AI15: Excluded | AJ15: General Cargo FAK, (Non HAZ) | AK15: 1:1 | AL15: Local Currency | AM15: Usd | AN15: Not Allowed | AO15: Yes | AP15: Yes | AQ15: 5 | AR15: Yes | AS15: Yes | AT15: Pre-Defined Fob/Plc
A16: DSV GLOBAL (RFQ & NON-RFQ LANES) | B16: Yearly | C16: Yearly | D16: Monthly | E16: 46113 | F16: 46477 | G16: 46113 | H16: 46477 | I16: =IFERROR(NETWORKDAYS($A$1,Table1[[#This Row],[FOB/PLC VALIDITY EXPIRY DATE ]]),"-") -> 200 | J16: =IFERROR(NETWORKDAYS($A$1,Table1[[#This Row],[OFR VALIDITY EXPIRY DATE ]]),"-") -> 200 | K16: OFR & Service Update Request | L16: CENTRIC - https://centric.wwalliance.com | M16: Jakob Bluhme | N16: Santiago | O16: Yearly | P16: Yearly | Q16: Yearly | R16: Yearly | S16: Bi-Weekly | T16: Bi-Weekly | U16: Bi-Weekly | V16: Monthly | W16: Monthly | X16: Monthly | Y16: Monthly | Z16: Monthly | AA16: Monthly | AB16: Monthly | AC16: Monthly | AD16: Quote Separately For Class 3,6,8,9 | AE16: Quote Separately | AF16: Quote Separately | AG16: Quote Separately | AH16: Quote Separately | AI16: Excluded | AJ16: General Cargo FAK, (Non HAZ & HAZ Class 3,6,8,9) | AO16: No (Except Rate Adjustment On Monthly) | AP16: Yes | AQ16: 20th of Month | AR16: Yes | AS16: Yes
A17: EFL | B17: Yearly | C17: Monthly | D17: Bi-Weekly | E17: 46189 | F17: 46387 | G17: 46189 | H17: 46203 | I17: =IFERROR(NETWORKDAYS($A$1,Table1[[#This Row],[FOB/PLC VALIDITY EXPIRY DATE ]]),"-") -> 136 | J17: =IFERROR(NETWORKDAYS($A$1,Table1[[#This Row],[OFR VALIDITY EXPIRY DATE ]]),"-") -> 4 | K17: OFR & Service Update Request | L17: RFQ TOOL - https://rfqtool.wwalliance.com | M17: Helen Li | N17: - | O17: Yearly | P17: Yearly | Q17: Yearly | R17: Yearly | S17: Bi-Weekly | T17: Bi-Weekly | U17: Bi-Weekly | V17: Monthly | W17: Monthly | X17: Monthly | Y17: Bi-Weekly | Z17: Bi-Weekly | AA17: Bi-Weekly | AB17: Bi-Weekly | AC17: Bi-Weekly | AD17: Excluded | AE17: Excluded | AF17: Excluded | AG17: Excluded | AH17: Excluded | AI17: Excluded | AJ17: General Cargo FAK, (Non HAZ) | AK17: 1:1 | AL17: Usd | AM17: Usd | AN17: Allowed | AO17: No | AP17: No | AQ17: 3 | AR17: Yes | AS17: Yes | AT17: New Rate Card Effective 16Th June
A18: EV CARGO (RA) | B18: Yearly | C18: Quarterly | D18: Bi-Weekly | E18: 46023 | F18: 46387 | G18: 46204 | H18: 46295 | I18: =IFERROR(NETWORKDAYS($A$1,Table1[[#This Row],[FOB/PLC VALIDITY EXPIRY DATE ]]),"-") -> 136 | J18: =IFERROR(NETWORKDAYS($A$1,Table1[[#This Row],[OFR VALIDITY EXPIRY DATE ]]),"-") -> 70 | K18: OFR & Service Update Request | L18: CENTRIC - https://centric.wwalliance.com | M18: Mary-Anne Chua | N18: IRTAsia | O18: Yearly | P18: Yearly | Q18: Yearly | R18: Yearly | S18: Bi-Weekly | T18: Bi-Weekly | U18: Bi-Weekly | V18: Quarterly | W18: Quarterly | X18: Quarterly | Y18: Bi-Weekly | Z18: Bi-Weekly | AA18: Bi-Weekly | AB18: Bi-Weekly | AC18: Bi-Weekly | AD18: Excluded | AE18: Excluded | AF18: Excluded | AG18: Excluded | AH18: Excluded | AI18: Excluded | AJ18: General Cargo FAK, (Non HAZ) | AK18: 1:1 | AL18: Local Currency | AM18: Usd | AN18: Allowed | AO18: Yes | AP18: No | AQ18: 3 | AR18: No | AS18: Yes | AT18: Regional Account
A19: EXPEDITORS | B19: 6 Months | C19: Monthly | D19: Bi-Weekly | E19: 46204 | F19: 46387 | G19: 46174 | H19: 46203 | I19: =IFERROR(NETWORKDAYS($A$1,Table1[[#This Row],[FOB/PLC VALIDITY EXPIRY DATE ]]),"-") -> 136 | J19: =IFERROR(NETWORKDAYS($A$1,Table1[[#This Row],[OFR VALIDITY EXPIRY DATE ]]),"-") -> 4 | K19: OFR & Service Update Request | L19: RFQ TOOL - https://rfqtool.wwalliance.com | M19: Mette Karapetian/Sylvia Lathouwers | N19: - | O19: 6 Months | P19: 6 Months | Q19: 6 Months | R19: 6 Months | S19: Bi-Weekly | T19: Bi-Weekly | U19: Pre-Defined (Agreement) | V19: Monthly | W19: Monthly | X19: Monthly | Y19: Bi-Weekly | Z19: Bi-Weekly | AA19: Bi-Weekly | AB19: Bi-Weekly | AC19: Bi-Weekly | AD19: Quote Separately For Class 3,6,8,9 | AE19: Quote Separately | AF19: Excluded | AG19: Excluded | AH19: Excluded | AI19: Quote Separately | AJ19: General Cargo FAK, (Non HAZ & HAZ Class 3,6,8,9) | AK19: 1 cbm = 1000 kgs except for USA IPI rates | AL19: Local Currency | AM19: USD/EUR | AN19: Not Allowed | AO19: No | AP19: No | AQ19: 3 | AR19: Yes | AS19: Yes | AT19: -
A20: FEDEXTRADE | B20: Yearly | C20: Monthly | D20: Bi-Weekly | E20: 46023 | F20: 46387 | G20: 46174 | H20: 46203 | I20: =IFERROR(NETWORKDAYS($A$1,Table1[[#This Row],[FOB/PLC VALIDITY EXPIRY DATE ]]),"-") -> 136 | J20: =IFERROR(NETWORKDAYS($A$1,Table1[[#This Row],[OFR VALIDITY EXPIRY DATE ]]),"-") -> 4 | K20: OFR & Service Update Request | L20: CENTRIC - https://centric.wwalliance.com | M20: Mette Karapetian/Santiago Milian | N20: Helen | O20: Yearly | P20: Yearly | Q20: Yearly | R20: Yearly | S20: Bi-Weekly | T20: Bi-Weekly | U20: Bi-Weekly | V20: Monthly | W20: Monthly | X20: Monthly | Y20: Bi-Weekly | Z20: Bi-Weekly | AA20: Monthly | AB20: Monthly | AC20: Bi-Weekly | AD20: Excluded | AE20: Excluded | AF20: Excluded | AG20: Excluded | AH20: Excluded | AI20: Excluded | AJ20: General Cargo FAK, (Non HAZ) | AK20: 1 cbm = 1000 kgs | AL20: Local Currency | AM20: USD/EUR | AN20: Not Allowed | AO20: No | AP20: No | AQ20: 3 | AR20: Yes | AS20: Yes | AT20: -
A21: FIBS (RA) | B21: Yearly | C21: Quarterly | D21: Bi-Weekly | E21: 46023 | F21: 46387 | G21: 46204 | H21: 46295 | I21: =IFERROR(NETWORKDAYS($A$1,Table1[[#This Row],[FOB/PLC VALIDITY EXPIRY DATE ]]),"-") -> 136 | J21: =IFERROR(NETWORKDAYS($A$1,Table1[[#This Row],[OFR VALIDITY EXPIRY DATE ]]),"-") -> 70 | K21: OFR & Service Update Request | L21: RFQ TOOL - https://rfqtool.wwalliance.com | M21: Mary-Anne Chua | N21: IRTAsia | O21: Yearly | P21: Yearly | Q21: Yearly | R21: Yearly | S21: Bi-Weekly | T21: Bi-Weekly | U21: Bi-Weekly | V21: Quarterly | W21: Quarterly | X21: Quarterly | Y21: Bi-Weekly | Z21: Bi-Weekly | AA21: Bi-Weekly | AB21: Bi-Weekly | AC21: Bi-Weekly | AD21: Excluded | AE21: Excluded | AF21: Excluded | AG21: Excluded | AH21: Excluded | AI21: Excluded | AJ21: General Cargo FAK, (Non HAZ) | AK21: 1:1 | AL21: Local Currency | AM21: Usd | AN21: Allowed | AO21: No | AP21: No | AQ21: 3 | AR21: Yes | AS21: Yes | AT21: Regional Account
A22: FIVE STAR (RA) | B22: Yearly | C22: Monthly | D22: Bi-Weekly | E22: 46023 | F22: 46387 | G22: 46174 | H22: 46203 | I22: =IFERROR(NETWORKDAYS($A$1,Table1[[#This Row],[FOB/PLC VALIDITY EXPIRY DATE ]]),"-") -> 136 | J22: =IFERROR(NETWORKDAYS($A$1,Table1[[#This Row],[OFR VALIDITY EXPIRY DATE ]]),"-") -> 4 | K22: OFR & Service Update Request | L22: CENTRIC - https://centric.wwalliance.com | M22: Martin Schulz | N22: Dennis Frankowski | O22: Yearly | P22: Yearly | Q22: Yearly | R22: Yearly | S22: Bi-Weekly | T22: Bi-Weekly | U22: Pre-Defined (Agreement) | V22: Monthly | W22: Monthly | X22: Quarterly | Y22: Bi-Weekly | Z22: Bi-Weekly | AA22: Bi-Weekly | AB22: Bi-Weekly | AC22: Bi-Weekly | AD22: Excluded | AE22: Excluded | AF22: Excluded | AG22: Excluded | AH22: Excluded | AI22: Excluded | AJ22: General Cargo FAK, (Non HAZ) | AK22: 1:1 | AL22: Local Currency | AM22: USD/EUR | AN22: Not Allowed | AO22: No | AP22: No | AQ22: 3 | AR22: Yes | AS22: Yes | AT22: Regional Account
A23: FLEXPORT | B23: Yearly | C23: Monthly | D23: Bi-Weekly | E23: 46023 | F23: 46387 | G23: 46174 | H23: 46203 | I23: =IFERROR(NETWORKDAYS($A$1,Table1[[#This Row],[FOB/PLC VALIDITY EXPIRY DATE ]]),"-") -> 136 | J23: =IFERROR(NETWORKDAYS($A$1,Table1[[#This Row],[OFR VALIDITY EXPIRY DATE ]]),"-") -> 4 | K23: OFR & Service Update Request | L23: RFQ TOOL - https://rfqtool.wwalliance.com | M23: Jens Pottschul | N23: Michelle Yu Cc. Maria Girlie & Irt Asia | O23: Yearly | P23: Yearly | Q23: Yearly | R23: Yearly | S23: Bi-Weekly | T23: Bi-Weekly | U23: Bi-Weekly | V23: Monthly | W23: Monthly | X23: Quarterly | Y23: Bi-Weekly | Z23: Bi-Weekly | AA23: Bi-Weekly | AB23: Bi-Weekly | AC23: Bi-Weekly | AD23: Excluded | AE23: Quote Separately | AF23: Excluded | AG23: Excluded | AH23: Excluded | AI23: Excluded | AJ23: General Cargo FAK, (Non HAZ) | AK23: 1:1000 | AL23: Local Currency | AM23: Usd | AN23: Not Allowed | AO23: No | AP23: No | AQ23: 3 | AR23: Yes | AS23: Yes | AT23: As Flexport Pull Our Rates Via Api We Can Reduce Only Locally As Long As Grdb Is Maintained So When Flexport Pull Api It Will Reflect Here As Well.
A24: GEBR. WEISS | B24: Yearly | C24: Monthly | D24: Bi-Weekly | E24: 46023 | F24: 46387 | G24: 46174 | H24: 46203 | I24: =IFERROR(NETWORKDAYS($A$1,Table1[[#This Row],[FOB/PLC VALIDITY EXPIRY DATE ]]),"-") -> 136 | J24: =IFERROR(NETWORKDAYS($A$1,Table1[[#This Row],[OFR VALIDITY EXPIRY DATE ]]),"-") -> 4 | K24: OFR & Service Update Request | L24: CENTRIC - https://centric.wwalliance.com | M24: Jakob Bluhme | N24: Santiago | O24: Yearly | P24: Yearly | Q24: Yearly | R24: Yearly | S24: Bi-Weekly | T24: Bi-Weekly | U24: Bi-Weekly | V24: Monthly | W24: Monthly | X24: Monthly | Y24: Bi-Weekly | Z24: Bi-Weekly | AA24: Bi-Weekly | AB24: Bi-Weekly | AC24: Bi-Weekly | AD24: Quote Separately For Class 3,6,8,9 | AE24: Quote Separately | AF24: Excluded | AG24: Quote Separately | AH24: Quote Separately | AI24: Excluded | AJ24: General Cargo FAK, (Non HAZ & HAZ Class 3,6,8,9) | AK24: 0.04375 | AL24: Local Currency | AM24: Usd | AN24: Not Allowed | AO24: Yes | AP24: No | AQ24: 3 | AR24: Yes | AS24: Yes | AT24: -
A25: GEODIS | B25: Yearly | C25: Bi-Weekly | D25: Bi-Weekly | E25: 46023 | F25: 46387 | G25: 46174 | H25: 46203 | I25: =IFERROR(NETWORKDAYS($A$1,Table1[[#This Row],[FOB/PLC VALIDITY EXPIRY DATE ]]),"-") -> 136 | J25: =IFERROR(NETWORKDAYS($A$1,Table1[[#This Row],[OFR VALIDITY EXPIRY DATE ]]),"-") -> 4 | K25: OFR & Service Update Request | L25: RFQ TOOL - https://rfqtool.wwalliance.com | M25: Martin Schulz/Susanne Elsborg-Jensen | N25: Susanne | O25: Yearly | P25: Yearly | Q25: Yearly | R25: Yearly | S25: Bi-Weekly | T25: Bi-Weekly | U25: Bi-Weekly | V25: Bi-Weekly | W25: Bi-Weekly | X25: Bi-Weekly | Y25: Bi-Weekly | Z25: Bi-Weekly | AA25: Bi-Weekly | AB25: Bi-Weekly | AC25: Bi-Weekly | AD25: Excluded | AE25: Quote Separately | AF25: Excluded | AG25: Excluded | AH25: Excluded | AI25: Excluded | AJ25: General Cargo FAK, (Non HAZ) | AK25: 1:1 | AL25: Local Currency | AM25: USD/EUR | AN25: Not Allowed | AO25: Yes | AP25: Yes | AQ25: 3 | AR25: Yes | AS25: Yes | AT25: Monthly Ofr Rates - Can Be Reduced But Needs To Be Displayed In The Grdb.
A26: HELLMANN | B26: Yearly | C26: Quarterly | D26: Bi-Weekly | E26: 46054 | F26: 46387 | G26: 46143 | H26: 46265 | I26: =IFERROR(NETWORKDAYS($A$1,Table1[[#This Row],[FOB/PLC VALIDITY EXPIRY DATE ]]),"-") -> 136 | J26: =IFERROR(NETWORKDAYS($A$1,Table1[[#This Row],[OFR VALIDITY EXPIRY DATE ]]),"-") -> 48 | K26: OFR & Service Update Request | L26: CENTRIC - https://centric.wwalliance.com | M26: Martin Schulz/Nadine Beer | N26: Nadine | O26: Yearly | P26: Yearly | Q26: Yearly | R26: Yearly | S26: Bi-Weekly | T26: Bi-Weekly | U26: Bi-Weekly | V26: Quarterly | W26: Quarterly | X26: Quarterly | Y26: Bi-Weekly | Z26: Bi-Weekly | AA26: Bi-Weekly | AB26: Pre-Defined (Agreement) | AC26: Pre-Defined (Agreement) | AD26: Quote Separately For Class 2,4,5,6 And 3,8,9 | AE26: Quote Separately | AF26: Quote Separately | AG26: Excluded | AH26: Excluded | AI26: Excluded | AJ26: General Cargo FAK, (Non HAZ & HAZ Class 2,4,5,6 & 3,8,9) | AK26: 1:3 | AL26: Local Currency | AM26: USD/EUR | AN26: Not Allowed | AO26: No | AP26: Yes | AQ26: 22nd of Month | AR26: Yes | AS26: Yes | AT26: Hellmann Does Not Accept Any Interim Updates.
A27: HELLMANN INTRA ASIA | B27: Yearly | C27: Quarterly | D27: Bi-Weekly | E27: 46023 | F27: 46387 | G27: 46204 | H27: 46295 | I27: =IFERROR(NETWORKDAYS($A$1,Table1[[#This Row],[FOB/PLC VALIDITY EXPIRY DATE ]]),"-") -> 136 | J27: =IFERROR(NETWORKDAYS($A$1,Table1[[#This Row],[OFR VALIDITY EXPIRY DATE ]]),"-") -> 70 | K27: OFR & Service Update Request | L27: RFQ TOOL - https://rfqtool.wwalliance.com | M27: Jens Pottschul | N27: IRTAsia | O27: Yearly | P27: Yearly | Q27: Yearly | R27: Yearly | S27: Bi-Weekly | T27: Bi-Weekly | U27: Bi-Weekly | V27: Quarterly | W27: Quarterly | X27: Na | Y27: Bi-Weekly | Z27: Bi-Weekly | AA27: Bi-Weekly | AB27: Bi-Weekly | AC27: Excl. As Per Advisory | AD27: Quote Separately For Class 2,4,5,6 And 3,8,9 | AE27: Quote Separately | AF27: Quote Separately | AG27: Excluded | AH27: Excluded | AI27: Excluded | AJ27: General Cargo FAK, (Non HAZ & HAZ Class 2,4,5,6 & 3,8,9) | AK27: 1:1 | AL27: Local Currency | AM27: Usd | AN27: Not Allowed | AO27: No | AP27: Yes | AQ27: 5 | AR27: Yes | AS27: Yes | AT27: Pre-Defined Fob/Plc
A28: JAS OCEAN | B28: Yearly | C28: Monthly | D28: Bi-Weekly | E28: 46023 | F28: 46387 | G28: 46174 | H28: 46203 | I28: =IFERROR(NETWORKDAYS($A$1,Table1[[#This Row],[FOB/PLC VALIDITY EXPIRY DATE ]]),"-") -> 136 | J28: =IFERROR(NETWORKDAYS($A$1,Table1[[#This Row],[OFR VALIDITY EXPIRY DATE ]]),"-") -> 4 | K28: OFR & Service Update Request | L28: CENTRIC - https://centric.wwalliance.com | M28: Chris Crowder | N28: Helen | O28: Yearly | P28: Yearly | Q28: Yearly | R28: Yearly | S28: Bi-Weekly | T28: Bi-Weekly | U28: Bi-Weekly | V28: Monthly | W28: Monthly | X28: Monthly | Y28: Bi-Weekly | Z28: Bi-Weekly | AA28: Bi-Weekly | AB28: Bi-Weekly | AC28: Bi-Weekly | AD28: Excluded | AE28: Excluded | AF28: Excluded | AG28: Excluded | AH28: Excluded | AI28: Quote Separately | AJ28: General Cargo FAK, (Non HAZ) | AK28: 1 cbm = 1000 kgs | AL28: Local Currency | AM28: USD/EUR | AN28: Not Allowed | AO28: Yes | AP28: No | AQ28: 2 | AR28: Yes | AS28: Yes | AT28: Any Reductions Must Be Shared, Filed, And Ensure Grdb Updated
A29: KLN | B29: Quarterly | C29: Monthly | D29: Bi-Weekly | E29: 46204 | F29: 46295 | G29: 46174 | H29: 46203 | I29: =IFERROR(NETWORKDAYS($A$1,Table1[[#This Row],[FOB/PLC VALIDITY EXPIRY DATE ]]),"-") -> 70 | J29: =IFERROR(NETWORKDAYS($A$1,Table1[[#This Row],[OFR VALIDITY EXPIRY DATE ]]),"-") -> 4 | K29: OFR & Service Update Request | L29: RFQ TOOL - https://rfqtool.wwalliance.com | M29: Jens Pottschul | N29: IRTAsia | O29: Quarterly | P29: Quarterly | Q29: Quarterly | R29: Quarterly | S29: Bi-Weekly | T29: Bi-Weekly | U29: Bi-Weekly | V29: Monthly | W29: Monthly | X29: Quarterly | Y29: Bi-Weekly | Z29: Bi-Weekly | AA29: Bi-Weekly | AB29: Bi-Weekly | AC29: Bi-Weekly | AD29: Excluded | AE29: Excluded | AF29: Excluded | AG29: Excluded | AH29: Excluded | AI29: Excluded | AJ29: General Cargo FAK, (Non HAZ) | AK29: 1:1000 | AL29: Local Currency | AM29: Usd | AN29: Not Allowed | AO29: No | AP29: No | AQ29: 3 | AR29: Yes | AS29: Yes | AT29: As Per March 1St 2026, Ofr Validity Will Become Monthly.
A30: KINTETSU | B30: 6 Months | C30: Monthly | D30: Bi-Weekly | E30: 46204 | F30: 46387 | G30: 46174 | H30: 46203 | I30: =IFERROR(NETWORKDAYS($A$1,Table1[[#This Row],[FOB/PLC VALIDITY EXPIRY DATE ]]),"-") -> 136 | J30: =IFERROR(NETWORKDAYS($A$1,Table1[[#This Row],[OFR VALIDITY EXPIRY DATE ]]),"-") -> 4 | K30: OFR & Service Update Request | L30: CENTRIC - https://centric.wwalliance.com | M30: Jens Pottschul/Michelle Yu | N30: IRTAsia | O30: 6 Months | P30: 6 Months | Q30: 6 Months | R30: 6 Months | S30: Bi-Weekly | T30: Bi-Weekly | U30: Bi-Weekly | W30: Monthly | X30: Monthly | Y30: Bi-Weekly | Z30: Bi-Weekly | AA30: Bi-Weekly | AB30: Bi-Weekly | AC30: Bi-Weekly | AD30: Excluded | AE30: Excluded | AF30: Excluded | AG30: Excluded | AH30: Excluded | AI30: Excluded | AJ30: General Cargo FAK, (Non HAZ) | AK30: 1:1 | AL30: Local Currency | AM30: Usd | AN30: Not Allowed | AO30: Yes | AP30: No | AQ30: 3 | AR30: No | AS30: No | AT30: Kwe Are Happy For Local Negotiaitons As Long As This Is Updated In The Next Viable Update. I.E In The Bi-Weekly Tariff Update. Would Also Like An Overview Of The Changes Made To Any Fob/Ofr/Plc Charges Which Are Reductions So They Are Able To Inform And Align With Local Offices.
A31: KUEHNE & NAGEL | B31: Yearly | C31: Monthly | D31: Monthly | E31: 46023 | F31: 46387 | G31: 46174 | H31: 46203 | I31: =IFERROR(NETWORKDAYS($A$1,Table1[[#This Row],[FOB/PLC VALIDITY EXPIRY DATE ]]),"-") -> 136 | J31: =IFERROR(NETWORKDAYS($A$1,Table1[[#This Row],[OFR VALIDITY EXPIRY DATE ]]),"-") -> 4 | K31: OFR & Service Update Request | L31: RFQ TOOL - https://rfqtool.wwalliance.com | M31: Martin Schulz/Nadine Beer | N31: Nadine | O31: Yearly | P31: Yearly | Q31: Yearly | R31: Yearly | S31: Bi-Weekly | T31: Bi-Weekly | U31: Bi-Weekly | V31: Monthly | W31: Monthly | X31: Incl. In OFR | Y31: Monthly | Z31: Monthly | AA31: Monthly | AB31: Monthly | AC31: Monthly | AD31: Excluded | AE31: Quote Separately | AF31: Excluded | AG31: Excluded | AH31: Excluded | AI31: Excluded | AJ31: General Cargo FAK, (Non HAZ) | AK31: 0.04375 | AL31: Local Currency | AM31: Usd | AN31: Not Allowed | AO31: Yes (Except EDS/ESF) | AP31: Yes | AQ31: 13th of Month | AR31: Yes | AS31: Yes | AT31: Pre-Defined Fob/Plc (Partial) / K&N Does Not Accept Any Interim Updates.
A32: LESCHACO | B32: Yearly | C32: Monthly | D32: Bi-Weekly | E32: 46023 | F32: 46387 | G32: 46174 | H32: 46203 | I32: =IFERROR(NETWORKDAYS($A$1,Table1[[#This Row],[FOB/PLC VALIDITY EXPIRY DATE ]]),"-") -> 136 | J32: =IFERROR(NETWORKDAYS($A$1,Table1[[#This Row],[OFR VALIDITY EXPIRY DATE ]]),"-") -> 4 | K32: OFR & Service Update Request | L32: CENTRIC - https://centric.wwalliance.com | M32: Martin Schulz/Nadine Beer | N32: Nadine | O32: Yearly | P32: Yearly | Q32: Yearly | R32: Yearly | S32: Bi-Weekly | T32: Bi-Weekly | U32: Bi-Weekly | V32: Monthly | W32: Monthly | X32: Monthly | Y32: Bi-Weekly | Z32: Bi-Weekly | AA32: Bi-Weekly | AB32: Excl. As Per Advisory | AC32: Excl. As Per Advisory | AD32: Quote Separately For Class 3,8,9 | AE32: Excluded | AF32: Excluded | AG32: Quote Separately | AH32: Quote Separately | AI32: Excluded | AJ32: General Cargo FAK, (Non HAZ & HAZ Class 3, 8, 9) | AK32: 1:1000 | AL32: Local Currency | AM32: Usd | AN32: Not Allowed | AO32: Yes | AP32: No | AQ32: 3 | AR32: Yes | AS32: Yes | AT32: -
A33: LIGENTIA (RA) | B33: Yearly | C33: Monthly | D33: Bi-Weekly | E33: 46023 | F33: 46387 | G33: 46174 | H33: 46203 | I33: =IFERROR(NETWORKDAYS($A$1,Table1[[#This Row],[FOB/PLC VALIDITY EXPIRY DATE ]]),"-") -> 136 | J33: =IFERROR(NETWORKDAYS($A$1,Table1[[#This Row],[OFR VALIDITY EXPIRY DATE ]]),"-") -> 4 | K33: OFR & Service Update Request | L33: RFQ TOOL - https://rfqtool.wwalliance.com | M33: Mary-Anne Chua/Christine Zheng | N33: IRTAsia | O33: Yearly | P33: Yearly | Q33: Yearly | R33: Yearly | S33: Bi-Weekly | T33: Bi-Weekly | U33: Bi-Weekly | V33: Monthly | W33: Monthly | X33: Monthly | Y33: Bi-Weekly | Z33: Bi-Weekly | AA33: Bi-Weekly | AB33: Bi-Weekly | AC33: Excl. As Per Advisory | AD33: Excluded | AE33: Excluded | AF33: Excluded | AG33: Excluded | AH33: Excluded | AI33: Excluded | AJ33: General Cargo FAK, (Non HAZ) | AK33: 1:1 | AL33: Local Currency | AM33: Usd | AN33: Not Allowed | AO33: Yes | AP33: No | AQ33: 5 | AR33: Yes | AS33: Yes | AT33: Regional Account
A34: LOGISTEED (RA) | B34: Yearly | C34: Monthly | D34: Bi-Weekly | E34: 46023 | F34: 46387 | G34: 46174 | H34: 46203 | I34: =IFERROR(NETWORKDAYS($A$1,Table1[[#This Row],[FOB/PLC VALIDITY EXPIRY DATE ]]),"-") -> 136 | J34: =IFERROR(NETWORKDAYS($A$1,Table1[[#This Row],[OFR VALIDITY EXPIRY DATE ]]),"-") -> 4 | K34: OFR & Service Update Request | L34: CENTRIC - https://centric.wwalliance.com | M34: Mary-Anne Chua | N34: IRTAsia | O34: Yearly | P34: Yearly | Q34: Yearly | R34: Yearly | S34: Bi-Weekly | T34: Bi-Weekly | U34: Bi-Weekly | V34: Monthly | W34: Monthly | X34: Monthly | Y34: Bi-Weekly | Z34: Bi-Weekly | AA34: Bi-Weekly | AB34: Bi-Weekly | AC34: Bi-Weekly | AD34: Excluded | AE34: Excluded | AF34: Excluded | AG34: Excluded | AH34: Excluded | AI34: Excluded | AJ34: General Cargo FAK, (Non HAZ) | AK34: 1:1 | AL34: Local Currency | AM34: Usd | AN34: Allowed | AO34: Yes (E2E Rate Positive) | AP34: No | AQ34: 3 | AR34: Yes | AS34: Yes | AT34: Regional Account
A35: MAERSK LOGISTICS GLOBAL | B35: 6 Months | C35: Monthly | D35: Bi-Weekly | E35: 46204 | F35: 46387 | G35: 46174 | H35: 46203 | I35: =IFERROR(NETWORKDAYS($A$1,Table1[[#This Row],[FOB/PLC VALIDITY EXPIRY DATE ]]),"-") -> 136 | J35: =IFERROR(NETWORKDAYS($A$1,Table1[[#This Row],[OFR VALIDITY EXPIRY DATE ]]),"-") -> 4 | K35: OFR & Service Update Request | L35: RFQ TOOL - https://rfqtool.wwalliance.com | M35: Susanne Elsborg-Jensen | N35: Santiago | O35: 6 Months | P35: 6 Months | Q35: 6 Months | R35: 6 Months | S35: Bi-Weekly | T35: Bi-Weekly | U35: Bi-Weekly | V35: Monthly | W35: Monthly | X35: Monthly | Y35: Bi-Weekly | Z35: Bi-Weekly | AA35: Bi-Weekly | AB35: Bi-Weekly | AC35: Bi-Weekly | AD35: Quote Separately For Class 3,6,8,9 | AE35: Quote Separately | AF35: Excluded | AG35: Excluded | AH35: Excluded | AI35: Excluded | AJ35: General Cargo FAK, (Non HAZ & HAZ Class 3,6,8,9) | AK35: 4 cbm per 1000 kgs | AL35: Local Currency | AM35: Usd | AN35: Not Allowed | AO35: No | AP35: Yes-Increase; No-Decrease | AQ35: 3 | AR35: Yes | AS35: Yes | AT35: Accept Updates On Monthly Sweep
A36: MONDIALE VGL (RA) | B36: Quarterly | C36: Quarterly | D36: Bi-Weekly | E36: 46204 | F36: 46295 | G36: 46204 | H36: 46295 | I36: =IFERROR(NETWORKDAYS($A$1,Table1[[#This Row],[FOB/PLC VALIDITY EXPIRY DATE ]]),"-") -> 70 | J36: =IFERROR(NETWORKDAYS($A$1,Table1[[#This Row],[OFR VALIDITY EXPIRY DATE ]]),"-") -> 70 | K36: OFR & Service Update Request | L36: CENTRIC - https://centric.wwalliance.com | M36: John Forster | N36: Kerry Hirst | O36: Quarterly | P36: Quarterly | Q36: Quarterly | R36: Quarterly | S36: Bi-Weekly | T36: Bi-Weekly | U36: Bi-Weekly | V36: Monthly | W36: Monthly | X36: Incl. In OFR | Y36: Bi-Weekly | Z36: Bi-Weekly | AA36: Bi-Weekly | AB36: Bi-Weekly | AC36: Excl. As Per Advisory | AD36: Excluded | AE36: Quote Separately | AF36: Excluded | AG36: Excluded | AH36: Excluded | AI36: Quote Separately | AJ36: General Cargo FAK, (Non HAZ) | AK36: 1:1 | AL36: Local Currency | AM36: Usd | AN36: Allowed | AO36: Yes | AP36: Yes | AQ36: 5 | AR36: Yes | AS36: Yes | AT36: Regional Account
A37: MORRISON EXPRESS (RA) | B37: Yearly | C37: Monthly | D37: Bi-Weekly | E37: 46023 | F37: 46387 | G37: 46174 | H37: 46203 | I37: =IFERROR(NETWORKDAYS($A$1,Table1[[#This Row],[FOB/PLC VALIDITY EXPIRY DATE ]]),"-") -> 136 | J37: =IFERROR(NETWORKDAYS($A$1,Table1[[#This Row],[OFR VALIDITY EXPIRY DATE ]]),"-") -> 4 | K37: OFR & Service Update Request | L37: RFQ TOOL - https://rfqtool.wwalliance.com | M37: Kevin Taylor | N37: Ronan Teoh | O37: Yearly | P37: Yearly | Q37: Yearly | R37: Yearly | S37: Bi-Weekly | T37: Bi-Weekly | U37: Bi-Weekly | V37: Monthly | W37: Monthly | X37: Monthly | Y37: Bi-Weekly | Z37: Bi-Weekly | AA37: Bi-Weekly | AB37: Bi-Weekly | AC37: Excl. As Per Advisory | AD37: Excluded | AE37: Quote Separately | AF37: Excluded | AG37: Excluded | AH37: Excluded | AI37: Excluded | AJ37: General Cargo FAK, (Non HAZ) | AK37: 1:1 | AL37: Local Currency | AM37: Usd | AN37: Allowed | AO37: Yes (E2E Rate Positive) | AP37: Yes | AQ37: 26th of Month | AR37: Yes | AS37: Yes | AT37: Regional Account / Outbound Isc/Asia Fak Rate Card
A38: NIPPON NX | B38: Yearly | C38: Quarterly | D38: Bi-Weekly | E38: 46023 | F38: 46387 | G38: 46204 | H38: 46295 | I38: =IFERROR(NETWORKDAYS($A$1,Table1[[#This Row],[FOB/PLC VALIDITY EXPIRY DATE ]]),"-") -> 136 | J38: =IFERROR(NETWORKDAYS($A$1,Table1[[#This Row],[OFR VALIDITY EXPIRY DATE ]]),"-") -> 70 | K38: OFR & Service Update Request | L38: CENTRIC - https://centric.wwalliance.com | M38: Jens Pottschul | N38: IRTAsia | O38: Yearly | P38: Yearly | Q38: Yearly | R38: Yearly | S38: Bi-Weekly | T38: Bi-Weekly | U38: Bi-Weekly | V38: Quarterly | W38: Quarterly | X38: Quarterly | Y38: Bi-Weekly | Z38: Bi-Weekly | AA38: Bi-Weekly | AB38: Bi-Weekly | AC38: Bi-Weekly | AD38: Excluded | AE38: Quote Separately | AF38: Excluded | AG38: Excluded | AH38: Excluded | AI38: Excluded | AJ38: General Cargo FAK, (Non HAZ) | AK38: 1 cbm per 1000 kgs. | AL38: Local Currency | AM38: USD/EUR | AN38: Not Allowed | AO38: No | AP38: No | AQ38: 3 | AR38: Yes | AS38: Yes | AT38: -
A39: NNR | B39: Bi-Weekly | C39: Bi-Weekly | D39: Bi-Weekly | E39: 46189 | F39: 46203 | G39: 46189 | H39: 46203 | I39: =IFERROR(NETWORKDAYS($A$1,Table1[[#This Row],[FOB/PLC VALIDITY EXPIRY DATE ]]),"-") -> 4 | J39: =IFERROR(NETWORKDAYS($A$1,Table1[[#This Row],[OFR VALIDITY EXPIRY DATE ]]),"-") -> 4 | K39: OFR & Service Update Request | L39: RFQ TOOL - https://rfqtool.wwalliance.com | M39: Jens Pottschul | N39: - | O39: Bi-Weekly | P39: Bi-Weekly | Q39: Bi-Weekly | R39: Bi-Weekly | S39: Bi-Weekly | T39: Bi-Weekly | U39: Bi-Weekly | V39: GRDB | W39: GRDB | X39: GRDB | Y39: Bi-Weekly | Z39: Bi-Weekly | AA39: Bi-Weekly | AD39: Excluded | AE39: Excluded | AF39: Excluded | AG39: Excluded | AH39: Excluded | AI39: Excluded | AJ39: General Cargo FAK, (Non HAZ) | AK39: 0.042361111 | AL39: Local Currency | AM39: Usd | AN39: Not Allowed | AO39: Yes | AP39: No | AQ39: 1 | AR39: No | AS39: NA | AT39: Member Update Through Grdb / Existing Monthly Rate Card (Grdb Data Download)
A40: NTG AIR & OCEAN | B40: Yearly | C40: Monthly | D40: Bi-Weekly | E40: 46174 | F40: 46387 | G40: 46174 | H40: 46203 | I40: =IFERROR(NETWORKDAYS($A$1,Table1[[#This Row],[FOB/PLC VALIDITY EXPIRY DATE ]]),"-") -> 136 | J40: =IFERROR(NETWORKDAYS($A$1,Table1[[#This Row],[OFR VALIDITY EXPIRY DATE ]]),"-") -> 4 | K40: OFR & Service Update Request | L40: CENTRIC - https://centric.wwalliance.com | M40: Susanne Elsborg-Jensen | N40: Santiago | O40: Yearly | P40: Yearly | Q40: Yearly | R40: Yearly | S40: Bi-Weekly | T40: Bi-Weekly | U40: Bi-Weekly | V40: Monthly | W40: Monthly | X40: Monthly | Y40: Bi-Weekly | Z40: Bi-Weekly | AA40: Bi-Weekly | AB40: Bi-Weekly | AC40: Bi-Weekly | AD40: Excluded | AE40: Excluded | AF40: Excluded | AG40: Excluded | AH40: Excluded | AI40: Excluded | AJ40: General Cargo FAK, (Non HAZ) | AK40: 0.042361111 | AL40: Local Currency | AM40: Usd | AN40: Not Allowed | AO40: Yes | AP40: No | AQ40: 3 | AR40: Yes | AS40: Yes | AT40: New Rate Card Effective 1St June
A41: OIA | B41: Quarterly | C41: Quarterly | D41: Bi-Weekly | E41: 46204 | F41: 46295 | G41: 46204 | H41: 46295 | I41: =IFERROR(NETWORKDAYS($A$1,Table1[[#This Row],[FOB/PLC VALIDITY EXPIRY DATE ]]),"-") -> 70 | J41: =IFERROR(NETWORKDAYS($A$1,Table1[[#This Row],[OFR VALIDITY EXPIRY DATE ]]),"-") -> 70 | K41: OFR & Service Update Request | L41: RFQ TOOL - https://rfqtool.wwalliance.com | M41: Kevin Taylor | N41: Helen | O41: Quarterly | P41: Quarterly | Q41: Quarterly | R41: Quarterly | S41: Bi-Weekly | T41: Bi-Weekly | U41: Bi-Weekly | V41: Monthly | W41: Monthly | X41: Quarterly | Y41: Bi-Weekly | Z41: Bi-Weekly | AA41: Bi-Weekly | AB41: Bi-Weekly | AC41: Bi-Weekly | AD41: Quote Separately For Class 3,8,9 | AE41: Quote Separately | AF41: Excluded | AG41: Excluded | AH41: Excluded | AI41: Quote Separately | AJ41: General Cargo FAK, (Non HAZ & HAZ Class 3, 8, 9) | AK41: 0.042361111 | AL41: Local Currency | AM41: Usd | AN41: Allowed | AO41: No | AP41: Yes | AQ41: 3 | AR41: Yes | AS41: Yes | AT41: -
A42: PSA BDP | B42: Yearly | C42: Monthly | D42: Bi-Weekly | E42: 46023 | F42: 46387 | G42: 46174 | H42: 46203 | I42: =IFERROR(NETWORKDAYS($A$1,Table1[[#This Row],[FOB/PLC VALIDITY EXPIRY DATE ]]),"-") -> 136 | J42: =IFERROR(NETWORKDAYS($A$1,Table1[[#This Row],[OFR VALIDITY EXPIRY DATE ]]),"-") -> 4 | K42: OFR & Service Update Request | L42: CENTRIC - https://centric.wwalliance.com | M42: Jakob Bluhme | N42: Santiago | O42: Yearly | P42: Yearly | Q42: Yearly | R42: Yearly | S42: Bi-Weekly | T42: Bi-Weekly | U42: Bi-Weekly | V42: Monthly | W42: Monthly | X42: Monthly | Y42: Bi-Weekly | Z42: Bi-Weekly | AA42: Bi-Weekly | AB42: Bi-Weekly | AC42: Bi-Weekly | AD42: Excluded | AE42: Excluded | AF42: Excluded | AG42: Excluded | AH42: Excluded | AI42: Excluded | AJ42: General Cargo FAK, (Non HAZ) | AK42: 1:3 | AL42: Local Currency | AM42: Usd | AN42: Not Allowed | AO42: Yes | AP42: No | AQ42: 3 | AR42: Yes | AS42: Yes | AT42: -
A43: RHENUS | B43: Yearly | C43: Monthly | D43: Bi-Weekly | E43: 45748 | F43: 46477 | G43: 46174 | H43: 46203 | I43: =IFERROR(NETWORKDAYS($A$1,Table1[[#This Row],[FOB/PLC VALIDITY EXPIRY DATE ]]),"-") -> 200 | J43: =IFERROR(NETWORKDAYS($A$1,Table1[[#This Row],[OFR VALIDITY EXPIRY DATE ]]),"-") -> 4 | K43: OFR & Service Update Request | L43: RFQ TOOL - https://rfqtool.wwalliance.com | M43: Jens Pottschul | N43: IRTAsia | O43: Yearly | P43: Yearly | Q43: Yearly | R43: Yearly | S43: Bi-Weekly | T43: Bi-Weekly | U43: Bi-Weekly | V43: Monthly | W43: Monthly | X43: Quarterly | Y43: Bi-Weekly | Z43: Bi-Weekly | AA43: Bi-Weekly | AB43: Bi-Weekly | AC43: Excl. As Per Advisory | AD43: Excluded | AE43: Quote Separately | AF43: Excluded | AG43: Excluded | AH43: Excluded | AI43: Excluded | AJ43: General Cargo FAK, (Non HAZ) | AK43: 1:1000 | AL43: Local Currency | AM43: Usd | AN43: Not Allowed | AO43: No | AP43: Yes | AQ43: 5 | AR43: Yes | AS43: Yes | AT43: **2 Working Days Prior New Effective Date. / In Principle Yes, But The Client Woudl Still Like To Clarify Some Technical Aspects Which Needs To Be Considered
A44: RIM LOGISTICS | B44: Yearly | C44: Monthly | D44: Bi-Weekly | E44: 46023 | F44: 46387 | G44: 46174 | H44: 46203 | I44: =IFERROR(NETWORKDAYS($A$1,Table1[[#This Row],[FOB/PLC VALIDITY EXPIRY DATE ]]),"-") -> 136 | J44: =IFERROR(NETWORKDAYS($A$1,Table1[[#This Row],[OFR VALIDITY EXPIRY DATE ]]),"-") -> 4 | K44: OFR & Service Update Request | L44: CENTRIC - https://centric.wwalliance.com | M44: Ryan Robert Howell | N44: Santiago | O44: Yearly | P44: Yearly | Q44: Yearly | R44: Yearly | S44: Bi-Weekly | T44: Bi-Weekly | U44: Bi-Weekly | V44: Monthly | W44: Monthly | X44: Monthly | Y44: Bi-Weekly | Z44: Bi-Weekly | AA44: Bi-Weekly | AB44: Bi-Weekly | AC44: Bi-Weekly | AD44: Excluded | AE44: Excluded | AF44: Excluded | AG44: Excluded | AH44: Excluded | AI44: Excluded | AJ44: General Cargo FAK, (Non HAZ) | AK44: 1:1000 | AL44: Local Currency | AM44: Usd | AN44: Not Allowed | AO44: Yes | AP44: Yes | AQ44: 3 | AR44: Yes | AS44: Yes | AT44: Will Receive Reductions When Applicable, Grdb And Customer Tariff Need To Be Updated/Matching And Shared With Rim
A45: ROHLIG | B45: Yearly | C45: Monthly | D45: Bi-Weekly | E45: 46023 | F45: 46387 | G45: 46174 | H45: 46203 | I45: =IFERROR(NETWORKDAYS($A$1,Table1[[#This Row],[FOB/PLC VALIDITY EXPIRY DATE ]]),"-") -> 136 | J45: =IFERROR(NETWORKDAYS($A$1,Table1[[#This Row],[OFR VALIDITY EXPIRY DATE ]]),"-") -> 4 | K45: OFR & Service Update Request | L45: RFQ TOOL - https://rfqtool.wwalliance.com | M45: Martin Schulz/Nadine Beer | N45: Nadine | O45: Yearly | P45: Yearly | Q45: Yearly | R45: Yearly | S45: Bi-Weekly | T45: Bi-Weekly | U45: Bi-Weekly | V45: Monthly | W45: Monthly | X45: Quarterly | Y45: Bi-Weekly | Z45: Bi-Weekly | AA45: Bi-Weekly | AB45: Bi-Weekly | AC45: Excl. As Per Advisory | AD45: Excluded | AE45: Excluded | AF45: Excluded | AG45: Excluded | AH45: Excluded | AI45: Excluded | AJ45: General Cargo FAK, (Non HAZ) | AK45: 1:1 | AL45: Local Currency | AM45: Usd | AN45: Not Allowed | AO45: Yes | AP45: No | AQ45: 3 | AR45: Yes | AS45: Yes | AT45: -
A46: SCAN GLOBAL LOGISTICS | B46: Yearly | C46: Bi-Weekly | D46: Bi-Weekly | E46: 46023 | F46: 46387 | G46: 46189 | H46: 46203 | I46: =IFERROR(NETWORKDAYS($A$1,Table1[[#This Row],[FOB/PLC VALIDITY EXPIRY DATE ]]),"-") -> 136 | J46: =IFERROR(NETWORKDAYS($A$1,Table1[[#This Row],[OFR VALIDITY EXPIRY DATE ]]),"-") -> 4 | K46: OFR & Service Update Request | L46: CENTRIC - https://centric.wwalliance.com | M46: Susanne Elsborg-Jensen | N46: Santiago | O46: Yearly | P46: Yearly | Q46: Yearly | R46: Yearly | S46: Bi-Weekly | T46: Bi-Weekly | U46: Bi-Weekly | V46: Bi-Weekly | W46: Bi-Weekly | X46: Bi-Weekly | Y46: Bi-Weekly | Z46: Bi-Weekly | AA46: Bi-Weekly | AB46: Bi-Weekly | AC46: Bi-Weekly | AD46: Excluded | AE46: Excluded | AF46: Excluded | AG46: Excluded | AH46: Excluded | AI46: Excluded | AJ46: General Cargo FAK, (Non HAZ) | AK46: 1:1000 | AL46: Local Currency | AM46: USD/EUR | AN46: Allowed | AO46: No | AP46: No | AQ46: 3 | AR46: Yes | AS46: Yes | AT46: -
A47: SCAN-SHIPPING (RA) | B47: Yearly | C47: Monthly | D47: Bi-Weekly | E47: 46023 | F47: 46387 | G47: 46174 | H47: 46203 | I47: =IFERROR(NETWORKDAYS($A$1,Table1[[#This Row],[FOB/PLC VALIDITY EXPIRY DATE ]]),"-") -> 136 | J47: =IFERROR(NETWORKDAYS($A$1,Table1[[#This Row],[OFR VALIDITY EXPIRY DATE ]]),"-") -> 4 | K47: OFR & Service Update Request | L47: RFQ TOOL - https://rfqtool.wwalliance.com | M47: Mette Karapetian / Susanne Elsborg-Jensen | N47: Susanne / Santiago | O47: Yearly | P47: Yearly | Q47: Yearly | R47: Yearly | S47: Bi-Weekly | T47: Bi-Weekly | U47: Bi-Weekly | V47: Monthly | W47: Monthly | X47: Monthly | Y47: Bi-Weekly | Z47: Bi-Weekly | AA47: Bi-Weekly | AB47: Bi-Weekly | AC47: Bi-Weekly | AD47: Quote Separately For Class 3,6,8,9 | AE47: Excluded | AF47: Excluded | AG47: Excluded | AH47: Excluded | AI47: Quote Separately | AJ47: General Cargo FAK, (Non HAZ & HAZ Class 3,6,8,9) | AK47: 1:1 | AL47: Local Currency | AM47: USD/EUR | AN47: Allowed | AO47: Yes | AP47: Yes-Increase; No-Decrease | AQ47: 2 | AR47: Yes | AS47: Yes | AT47: Regional Account / Client Requires Full Visibility Into Grdb. Scan Shipping Utilizing Wwa Online Portal For Spot Quote Processing Incl.Door-Door Where Possible.
A48: SEKO | B48: 9 Months | C48: Monthly | D48: Bi-Weekly | E48: 46113 | F48: 46387 | G48: 46174 | H48: 46203 | I48: =IFERROR(NETWORKDAYS($A$1,Table1[[#This Row],[FOB/PLC VALIDITY EXPIRY DATE ]]),"-") -> 136 | J48: =IFERROR(NETWORKDAYS($A$1,Table1[[#This Row],[OFR VALIDITY EXPIRY DATE ]]),"-") -> 4 | K48: OFR & Service Update Request | L48: CENTRIC - https://centric.wwalliance.com | M48: Jens Pottschul | N48: IRTAsia | O48: 9 Months | P48: 9 Months | Q48: 9 Months | R48: 9 Months | S48: Bi-Weekly | T48: Bi-Weekly | U48: Bi-Weekly | V48: Monthly | W48: Monthly | X48: Monthly | Y48: Bi-Weekly | Z48: Bi-Weekly | AA48: Bi-Weekly | AB48: Bi-Weekly | AC48: Bi-Weekly | AD48: Quote Separately For Class 3,6,8,9 | AE48: Quote Separately | AF48: Excluded | AG48: Excluded | AH48: Excluded | AI48: Excluded | AJ48: General Cargo FAK, (Non HAZ & HAZ Class 3,6,8,9) | AK48: 0.042361111 | AL48: Local Currency | AM48: Usd | AN48: Allowed | AO48: Yes | AP48: NA | AQ48: 3 | AR48: Yes | AS48: Yes | AT48: Any In- Or Decrease To Be Handled On A Local Level And To Be Updated Only Per The Next Update Cycle.
A49: TOLL GLOBAL FORWARDING | B49: Yearly | C49: Monthly | D49: Bi-Weekly | E49: 46023 | F49: 46387 | G49: 46174 | H49: 46203 | I49: =IFERROR(NETWORKDAYS($A$1,Table1[[#This Row],[FOB/PLC VALIDITY EXPIRY DATE ]]),"-") -> 136 | J49: =IFERROR(NETWORKDAYS($A$1,Table1[[#This Row],[OFR VALIDITY EXPIRY DATE ]]),"-") -> 4 | K49: OFR & Service Update Request | L49: RFQ TOOL - https://rfqtool.wwalliance.com | M49: Jens Pottschul | N49: IRTAsia | O49: Yearly | P49: Yearly | Q49: Yearly | R49: Yearly | S49: Bi-Weekly | T49: Bi-Weekly | U49: Bi-Weekly | V49: Monthly | W49: Monthly | X49: Quarterly | Y49: Bi-Weekly | Z49: Bi-Weekly | AA49: Bi-Weekly | AB49: Bi-Weekly | AC49: Excl. As Per Advisory | AD49: Quote Separately For Class 3,6,8,9 | AE49: Quote Separately | AF49: Excluded | AG49: Excluded | AH49: Excluded | AI49: Excluded | AJ49: General Cargo FAK, (Non HAZ & HAZ Class 3,6,8,9) | AK49: 1:1000 | AL49: Local Currency | AM49: Usd | AN49: Not Allowed | AO49: Yes (E2E Rate Positive) | AP49: Yes | AQ49: 3 | AR49: Yes | AS49: Yes | AT49: Pre-Defined Fob/Plc E-Inf - Added In Compensation Overview
A50: UPS GLOBAL | B50: Yearly | C50: Monthly | D50: Bi-Weekly | E50: 46082 | F50: 46387 | G50: 46174 | H50: 46203 | I50: =IFERROR(NETWORKDAYS($A$1,Table1[[#This Row],[FOB/PLC VALIDITY EXPIRY DATE ]]),"-") -> 136 | J50: =IFERROR(NETWORKDAYS($A$1,Table1[[#This Row],[OFR VALIDITY EXPIRY DATE ]]),"-") -> 4 | K50: OFR & Service Update Request | L50: CENTRIC - https://centric.wwalliance.com | M50: Diane Kaiser | N50: Diane Kaiser | O50: Yearly | P50: Yearly | Q50: Yearly | R50: Yearly | S50: Bi-Weekly | T50: Bi-Weekly | U50: Bi-Weekly | V50: Monthly | W50: Monthly | X50: Monthly | Y50: Bi-Weekly | Z50: Bi-Weekly | AA50: Bi-Weekly | AB50: Bi-Weekly | AC50: Excl. As Per Advisory | AD50: Quote Separately For Class 3,8,9 | AE50: Excluded | AF50: Excluded | AG50: Quote Separately | AH50: Quote Separately | AI50: Quote Separately | AJ50: General Cargo FAK, (Non HAZ & HAZ Class 3, 8, 9) | AK50: 1:1 | AL50: Local Currency | AM50: USD/EUR | AN50: Not Allowed | AO50: No | AP50: Yes | AQ50: 2 | AR50: Yes | AS50: Yes | AT50: Ups Does Not Accept Any Interim Updates.
A51: YUSEN INTRA ASIA | B51: 6 Months | C51: 6 Months | D51: Bi-Weekly | E51: 46113 | F51: 46295 | G51: 46113 | H51: 46295 | I51: =IFERROR(NETWORKDAYS($A$1,Table1[[#This Row],[FOB/PLC VALIDITY EXPIRY DATE ]]),"-") -> 70 | J51: =IFERROR(NETWORKDAYS($A$1,Table1[[#This Row],[OFR VALIDITY EXPIRY DATE ]]),"-") -> 70 | K51: OFR & Service Update Request | L51: RFQ TOOL - https://rfqtool.wwalliance.com | M51: Jens Pottschul | N51: IRTAsia | O51: 6 Months | P51: 6 Months | Q51: 6 Months | R51: 6 Months | S51: Bi-Weekly | T51: Bi-Weekly | U51: Bi-Weekly | V51: Monthly | W51: Monthly | X51: Na | Y51: Bi-Weekly | Z51: Bi-Weekly | AA51: Bi-Weekly | AB51: Bi-Weekly | AC51: Bi-Weekly | AD51: Excluded | AE51: Excluded | AF51: Excluded | AG51: Excluded | AH51: Excluded | AI51: Excluded | AJ51: General Cargo FAK, (Non HAZ) | AK51: 1:1000 | AL51: Local Currency | AM51: Usd | AN51: Allowed | AO51: No | AP51: No | AQ51: 5 | AR51: Yes | AS51: Yes | AT51: -
A52: YUSEN (USA) IMP/EXP | B52: Quarterly | C52: Quarterly | D52: Bi-Weekly | E52: 46204 | F52: 46295 | G52: 46204 | H52: 46295 | I52: =IFERROR(NETWORKDAYS($A$1,Table1[[#This Row],[FOB/PLC VALIDITY EXPIRY DATE ]]),"-") -> 70 | J52: =IFERROR(NETWORKDAYS($A$1,Table1[[#This Row],[OFR VALIDITY EXPIRY DATE ]]),"-") -> 70 | K52: OFR & Service Update Request | L52: CENTRIC - https://centric.wwalliance.com | M52: Bruce Ericson | N52: Helen | O52: Quarterly | P52: Quarterly | Q52: Quarterly | R52: Quarterly | S52: Bi-Weekly | T52: Bi-Weekly | U52: Bi-Weekly | V52: Monthly | W52: Monthly | X52: Quarterly | Y52: Bi-Weekly | Z52: Bi-Weekly | AA52: Bi-Weekly | AB52: Bi-Weekly | AC52: Bi-Weekly | AD52: Excluded | AE52: Excluded | AF52: Excluded | AG52: Excluded | AH52: Excluded | AI52: Quote Separately | AJ52: General Cargo FAK, (Non HAZ) | AK52: 1 CBM: 1000 kgs. | AL52: Local Currency | AM52: Usd | AN52: Not Allowed | AO52: No | AP52: Yes | AQ52: 3 | AR52: Yes | AS52: Yes | AT52: Rates Valid For 3 Month. Rates Can Re Reduced Locally, But Yusen Needs To Be Informed What Is Changed Via Owner. Yusen Requested Advance Notification If/When Any Increases Are Pending.
A53: YUSEN EUROPE | B53: Quarterly | C53: Quarterly | D53: Bi-Weekly | E53: 46204 | F53: 46295 | G53: 46204 | H53: 46295 | I53: =IFERROR(NETWORKDAYS($A$1,Table1[[#This Row],[FOB/PLC VALIDITY EXPIRY DATE ]]),"-") -> 70 | J53: =IFERROR(NETWORKDAYS($A$1,Table1[[#This Row],[OFR VALIDITY EXPIRY DATE ]]),"-") -> 70 | K53: OFR & Service Update Request | L53: RFQ TOOL - https://rfqtool.wwalliance.com | M53: Sylvia Lathouwers | N53: Nadine Beer | O53: Quarterly | P53: Quarterly | Q53: Quarterly | R53: Quarterly | S53: Bi-Weekly | T53: Bi-Weekly | U53: Bi-Weekly | V53: Monthly | W53: Monthly | X53: Quarterly | Y53: Bi-Weekly | Z53: Bi-Weekly | AA53: Bi-Weekly | AB53: Bi-Weekly | AC53: Excl. As Per Advisory | AD53: Excluded | AE53: Excluded | AF53: Excluded | AG53: Excluded | AH53: Excluded | AI53: Excluded | AJ53: General Cargo FAK, (Non HAZ) | AK53: 1:1 | AL53: Local Currency | AM53: Usd | AN53: Allowed | AO53: Yes | AP53: Yes | AQ53: 3 | AR53: Yes | AS53: Yes | AT53: Yusen Europe Does Not Accept Any Interim Updates.
A54: YUSEN LATAM (IMPORT) | B54: 6 Months | C54: 6 Months | D54: Bi-Weekly | E54: 46113 | F54: 46295 | G54: 46113 | H54: 46295 | I54: =IFERROR(NETWORKDAYS($A$1,Table1[[#This Row],[FOB/PLC VALIDITY EXPIRY DATE ]]),"-") -> 70 | J54: =IFERROR(NETWORKDAYS($A$1,Table1[[#This Row],[OFR VALIDITY EXPIRY DATE ]]),"-") -> 70 | K54: OFR & Service Update Request | L54: CENTRIC - https://centric.wwalliance.com | M54: Jens Pottschul | N54: IRTAsia | O54: Weekly | P54: 6 Months | Q54: 6 Months | R54: 6 Months | S54: Bi-Weekly | T54: Bi-Weekly | U54: Bi-Weekly | V54: Monthly | W54: Monthly | X54: Quarterly | Y54: Bi-Weekly | Z54: Bi-Weekly | AA54: Bi-Weekly | AB54: Bi-Weekly | AC54: Bi-Weekly | AD54: Excluded | AE54: Excluded | AF54: Excluded | AG54: Excluded | AH54: Excluded | AI54: Excluded | AJ54: General Cargo FAK, (Non HAZ) | AK54: 1:1000 | AL54: Local Currency | AM54: Usd | AN54: Allowed | AO54: No | AP54: Yes | AQ54: 5 | AR54: Yes | AS54: Yes | AT54: -

Sheet Customer_Exception
A1: Customer | B1: Exceptions
A2: UPS | B2: Link

Sheet NAC
F1: ACCOUNT | H1: OWNER | J1: VALIDITIES | N1: SURCHARGES | X1: CONDITIONAL CHARGES | AC1: GENERAL | AK1: UPDATES | AM1: 46092
A2: YEAR | B2: MONTH | C2: REQUEST RECEIVED DATE | D2: SUBMISSION DATE | E2: RELEASED DATE | F2: WWA CUSTOMER | G2: NAMED ACCOUNT | H2: GLOBAL/REGIONAL ACCOUNT OWNER | I2: RFQ OWNER | J2: FOB VALIDITY EFFECTIVE DATE | K2: PLC VALIDITY EXPIRY DATE | L2: OFR VALIDITY EFFECTIVE DATE | M2: OFR VALIDITY EXPIRY DATE | N2: SOLAS | O2: FILING | P2: MANDATORY ICS2 ADMIN FEE | Q2: CONDITIONAL ICS2 FILING FEE | R2: IMO2020 | S2: GRI | T2: ESF | U2: E-PSS | V2: LWS/PCS | W2: ETSS/FEMS | X2: HAZ | Y2: 3RD PARTY | Z2: NON-STACKABLE | AA2: STORAGE CHARGES | AB2: BMSB SURCHARGES | AC2: NEGATIVE RATES ACCEPTED (Y/N) | AD2: R1 HANDLED UNDER SWIFT (Y/N) | AE2: SWIFT NOT HANDLED REASON | AF2: MADE INTO ROUND 2 | AG2: DELAYED HANDLING (Y/N) | AH2: DELAYED REASON | AI2: CANCELLED (Y/N) | AJ2: CANCELLED REASON | AK2: FOB/PLC FOLLOW-UP IN DAYS | AL2: OFR FOLLOW-UP IN DAYS | AM2: TOTAL UPDATES
A3: 2025 | B3: =UPPER(TEXT(C3,"MMM")) -> FEB | C3: 46069 | E3: 46069 | F3: KLN | G3: DYSON | H3: =UPPER(VLOOKUP(F3,Droplist!A:C,3,0)) -> JENS POTTSCHUL | I3: MARIA GIRLIE/ MICHELLE YU | J3: 46143 | K3: 46387 | L3: 46143 | M3: 46387 | N3: SEPARATE | O3: SEPARATE | P3: SEPARATELY | Q3: INCL. IN FILING FEE | R3: SEPARATELY | S3: EXCL. AS PER ADVISORY | T3: EXCL. AS PER ADVISORY | U3: EXCL. AS PER ADVISORY | V3: EXCL. AS PER ADVISORY | W3: EXCL. AS PER ADVISORY | X3: N | Y3: N | Z3: N | AA3: N | AB3: N | AC3: Y | AD3: N | AE3: Maintenance / update rates | AF3: =IF(AD3="Y",IF(AM3>1,"Y","N"),"") | AG3: =IFERROR(IF(NETWORKDAYS(C3+1,E3)>=2,"Y","N"),"N") -> N | AI3: N | AK3: =IFERROR(NETWORKDAYS(K3,$AM$1),"-") -> -212 | AL3: =IFERROR(NETWORKDAYS(M3,$AM$1),"-") -> -212 | AM3: =IFERROR(COUNTIFS($F$3:$F$1048576,F3,$G$3:$G$1048576,G3),"") -> 1
A4: 2025 | B4: =UPPER(TEXT(C4,"MMM")) -> FEB | C4: 46073 | E4: NA | F4: LOGWIN | G4: KONECRANES | H4: =UPPER(VLOOKUP(F4,Droplist!A:C,3,0)) -> MARTIN SCHULZ | I4: NADINE BEER | J4: 46073 | K4: 46387 | L4: 46073 | M4: 46203 | N4: SEPARATE | O4: SEPARATE | P4: SEPARATELY | Q4: EXCL. (AS PER AGREEMENT) | R4: SEPARATE | S4: SEPARATE | T4: SEPARATE | U4: SEPARATE | V4: SEPARATE | W4: SEPARATE | X4: N | Y4: N | Z4: N | AA4: N | AB4: N | AC4: N | AD4: Y | AE4: NA | AF4: =IF(AD4="Y",IF(AM4>1,"Y","N"),"") -> N | AG4: =IFERROR(IF(NETWORKDAYS(C4+1,E4)>=2,"Y","N"),"N") -> N | AI4: N | AK4: =IFERROR(NETWORKDAYS(K4,$AM$1),"-") -> -212 | AL4: =IFERROR(NETWORKDAYS(M4,$AM$1),"-") -> -80 | AM4: =IFERROR(COUNTIFS($F$3:$F$1048576,F4,$G$3:$G$1048576,G4),"") -> 1
A5: 2025 | B5: =UPPER(TEXT(C5,"MMM")) -> FEB | C5: 46072 | E5: NA | F5: NOATUM | G5: REGAL REXNORD | H5: =UPPER(VLOOKUP(F5,Droplist!A:C,3,0)) -> JAKOB BLUHME / TOM HINE | I5: HELEN LI | J5: 46076 | K5: 46387 | L5: 46076 | M5: 46387 | N5: SEPARATE | O5: SEPARATE | P5: INCL. IN FILING FEE | Q5: EXCL. (AS PER AGREEMENT) | R5: SEPARATE | S5: SEPARATE | T5: SEPARATE | U5: SEPARATE | V5: SEPARATE | W5: SEPARATE | X5: N | Y5: N | Z5: N | AA5: N | AB5: N | AC5: Y | AD5: Y | AE5: NA | AF5: =IF(AD5="Y",IF(AM5>1,"Y","N"),"") -> N | AG5: =IFERROR(IF(NETWORKDAYS(C5+1,E5)>=2,"Y","N"),"N") -> N | AI5: N | AK5: =IFERROR(NETWORKDAYS(K5,$AM$1),"-") -> -212 | AL5: =IFERROR(NETWORKDAYS(M5,$AM$1),"-") -> -212 | AM5: =IFERROR(COUNTIFS($F$3:$F$1048576,F5,$G$3:$G$1048576,G5),"") -> 1
A6: 2025 | B6: =UPPER(TEXT(C6,"MMM")) -> FEB | C6: 46073 | E6: 46076 | F6: KLN | G6: HIGHLY MARELLI | H6: =UPPER(VLOOKUP(F6,Droplist!A:C,3,0)) -> JENS POTTSCHUL | I6: DOREEN LAM | J6: 46077 | K6: 46387 | L6: 46077 | M6: 46387 | N6: SEPARATE | O6: SEPARATE | P6: SEPARATELY | Q6: EXCL. (AS PER AGREEMENT) | R6: SEPARATE | S6: SEPARATE | T6: SEPARATE | U6: SEPARATE | V6: SEPARATE | W6: SEPARATE | X6: N | Y6: Y | Z6: N | AA6: N | AB6: N | AC6: N | AD6: N | AE6: Criteria as per POC SOP not met | AF6: =IF(AD6="Y",IF(AM6>1,"Y","N"),"") | AG6: =IFERROR(IF(NETWORKDAYS(C6+1,E6)>=2,"Y","N"),"N") -> N | AI6: N | AK6: =IFERROR(NETWORKDAYS(K6,$AM$1),"-") -> -212 | AL6: =IFERROR(NETWORKDAYS(M6,$AM$1),"-") -> -212 | AM6: =IFERROR(COUNTIFS($F$3:$F$1048576,F6,$G$3:$G$1048576,G6),"") -> 1
A7: 2025 | B7: =UPPER(TEXT(C7,"MMM")) -> FEB | C7: 46073 | E7: NA | F7: CRANE WORLDWIDE | G7: HARMAN | H7: =UPPER(VLOOKUP(F7,Droplist!A:C,3,0)) -> METTE B. KARAPETIAN | I7: HELEN LI | J7: 46077 | K7: 46203 | L7: 46077 | M7: 46203 | N7: SEPARATE | O7: SEPARATE | P7: INCL. IN DOC FEE | Q7: EXCL. (AS PER AGREEMENT) | R7: SEPARATE | S7: SEPARATE | T7: SEPARATE | U7: SEPARATE | V7: SEPARATE | W7: SEPARATE | X7: N | Y7: Y | Z7: N | AA7: N | AB7: N | AC7: N | AD7: Y | AE7: NA | AF7: =IF(AD7="Y",IF(AM7>1,"Y","N"),"") -> N | AG7: =IFERROR(IF(NETWORKDAYS(C7+1,E7)>=2,"Y","N"),"N") -> N | AI7: N | AK7: =IFERROR(NETWORKDAYS(K7,$AM$1),"-") -> -80 | AL7: =IFERROR(NETWORKDAYS(M7,$AM$1),"-") -> -80 | AM7: =IFERROR(COUNTIFS($F$3:$F$1048576,F7,$G$3:$G$1048576,G7),"") -> 1
A8: 2025 | B8: =UPPER(TEXT(C8,"MMM")) -> FEB | C8: 46073 | E8: 46076 | F8: YUSEN | G8: FAST RETAILING | H8: =UPPER(VLOOKUP(F8,Droplist!A:C,3,0)) -> JENS POTTSCHUL | I8: MARIA GIRLIE | J8: 46143 | K8: 46507 | L8: 46143 | M8: 46507 | N8: SEPARATE | O8: SEPARATE | P8: INCL. IN DOC FEE | Q8: EXCL. (AS PER AGREEMENT) | R8: SEPARATE | S8: SEPARATE | T8: EXCL. AS PER ADVISORY | U8: EXCL. AS PER ADVISORY | V8: EXCL. AS PER ADVISORY | W8: EXCL. AS PER ADVISORY | X8: N | Y8: Y | Z8: N | AA8: N | AB8: N | AC8: N | AD8: N | AE8: Criteria as per POC SOP not met | AF8: =IF(AD8="Y",IF(AM8>1,"Y","N"),"") | AG8: =IFERROR(IF(NETWORKDAYS(C8+1,E8)>=2,"Y","N"),"N") -> N | AI8: N | AK8: =IFERROR(NETWORKDAYS(K8,$AM$1),"-") -> -298 | AL8: =IFERROR(NETWORKDAYS(M8,$AM$1),"-") -> -298 | AM8: =IFERROR(COUNTIFS($F$3:$F$1048576,F8,$G$3:$G$1048576,G8),"") -> 1
A9: 2025 | B9: =UPPER(TEXT(C9,"MMM")) -> FEB | C9: 46078 | E9: NA | F9: KLN | G9: STELLANTIS | H9: =UPPER(VLOOKUP(F9,Droplist!A:C,3,0)) -> JENS POTTSCHUL | I9: MARIA GIRLIE/YI WEI PAK | J9: 46174 | K9: 46387 | L9: 46174 | M9: 46387 | N9: SEPARATE | O9: SEPARATE | P9: SEPARATELY | Q9: EXCL. (AS PER AGREEMENT) | R9: INCL IN OFR | S9: EXCL. AS PER ADVISORY | T9: EXCL. AS PER ADVISORY | U9: EXCL. AS PER ADVISORY | V9: EXCL. AS PER ADVISORY | W9: EXCL. AS PER ADVISORY | X9: N | Y9: N | Z9: N | AA9: N | AB9: N | AC9: Y | AD9: Y | AE9: NA | AF9: =IF(AD9="Y",IF(AM9>1,"Y","N"),"") -> N | AG9: =IFERROR(IF(NETWORKDAYS(C9+1,E9)>=2,"Y","N"),"N") -> N | AI9: N | AK9: =IFERROR(NETWORKDAYS(K9,$AM$1),"-") -> -212 | AL9: =IFERROR(NETWORKDAYS(M9,$AM$1),"-") -> -212 | AM9: =IFERROR(COUNTIFS($F$3:$F$1048576,F9,$G$3:$G$1048576,G9),"") -> 1
A10: 2025 | B10: =UPPER(TEXT(C10,"MMM")) -> FEB | C10: 46076 | E10: 46077 | F10: MORRISON EXPRESS | G10: ANSELL | H10: =UPPER(VLOOKUP(F10,Droplist!A:C,3,0)) -> KEVIN TAYLOR | I10: RONAN TEOH | J10: 46082 | K10: 46387 | L10: 46082 | M10: 46112 | N10: INCL. IN DOC FEE | O10: EXCL. (AS PER AGREEMENT) | P10: INCL. IN DOC FEE | Q10: EXCL. (AS PER AGREEMENT) | R10: SEPARATE | S10: SEPARATE | T10: SEPARATE | U10: SEPARATE | V10: SEPARATE | W10: SEPARATE | X10: N | Y10: N | Z10: N | AA10: N | AB10: N | AC10: N | AD10: N | AE10: Maintenance / update rates | AF10: =IF(AD10="Y",IF(AM10>1,"Y","N"),"") | AG10: =IFERROR(IF(NETWORKDAYS(C10+1,E10)>=2,"Y","N"),"N") -> N | AI10: N | AK10: =IFERROR(NETWORKDAYS(K10,$AM$1),"-") -> -212 | AL10: =IFERROR(NETWORKDAYS(M10,$AM$1),"-") -> -15 | AM10: =IFERROR(COUNTIFS($F$3:$F$1048576,F10,$G$3:$G$1048576,G10),"") -> 2
A11: 2025 | B11: =UPPER(TEXT(C11,"MMM")) -> FEB | C11: 46072 | E11: 46073 | F11: CARGO PARTNER | G11: EATON | H11: =UPPER(VLOOKUP(F11,Droplist!A:C,3,0)) -> DENNIS FRANKOWSKI | I11: RONAN TEOH | J11: 46082 | K11: 46387 | L11: 46082 | M11: 46203 | N11: SEPARATE | O11: SEPARATE | P11: SEPARATELY | Q11: EXCL. (AS PER AGREEMENT) | R11: SEPARATE | S11: SEPARATE | T11: SEPARATE | U11: SEPARATE | V11: SEPARATE | W11: SEPARATE | X11: N | Y11: Y | Z11: N | AA11: N | AB11: N | AC11: Y | AD11: N | AE11: Criteria as per POC SOP not met | AF11: =IF(AD11="Y",IF(AM11>1,"Y","N"),"") | AG11: =IFERROR(IF(NETWORKDAYS(C11+1,E11)>=2,"Y","N"),"N") -> N | AI11: N | AK11: =IFERROR(NETWORKDAYS(K11,$AM$1),"-") -> -212 | AL11: =IFERROR(NETWORKDAYS(M11,$AM$1),"-") -> -80 | AM11: =IFERROR(COUNTIFS($F$3:$F$1048576,F11,$G$3:$G$1048576,G11),"") -> 1
A12: 2025 | B12: =UPPER(TEXT(C12,"MMM")) -> FEB | C12: 46076 | E12: 46077 | F12: RHENUS | G12: KOHLER | H12: =UPPER(VLOOKUP(F12,Droplist!A:C,3,0)) -> JENS POTTSCHUL | I12: MARIA GIRLIE/ DOREEN LAM | J12: 46143 | K12: 46507 | L12: 46143 | M12: 46507 | N12: SEPARATE | O12: EXCL. (AS PER AGREEMENT) | P12: SEPARATELY | Q12: EXCL. (AS PER AGREEMENT) | R12: SEPARATE | S12: SEPARATE | T12: SEPARATE | U12: SEPARATE | V12: SEPARATE | W12: SEPARATE | X12: N | Y12: Y | Z12: N | AA12: N | AB12: N | AC12: N | AD12: N | AE12: Criteria as per POC SOP not met | AF12: =IF(AD12="Y",IF(AM12>1,"Y","N"),"") | AG12: =IFERROR(IF(NETWORKDAYS(C12+1,E12)>=2,"Y","N"),"N") -> N | AI12: N | AK12: =IFERROR(NETWORKDAYS(K12,$AM$1),"-") -> -298 | AL12: =IFERROR(NETWORKDAYS(M12,$AM$1),"-") -> -298 | AM12: =IFERROR(COUNTIFS($F$3:$F$1048576,F12,$G$3:$G$1048576,G12),"") -> 1
A13: 2025 | B13: =UPPER(TEXT(C13,"MMM")) -> FEB | C13: 46074 | E13: 46078 | F13: OIA | G13: GIVAUDAN | H13: =UPPER(VLOOKUP(F13,Droplist!A:C,3,0)) -> KEVIN TAYLOR | I13: HELEN LI | J13: 46082 | K13: 46446 | L13: 46082 | M13: 46446 | N13: SEPARATE | O13: SEPARATE | P13: INCL. IN DOC FEE | Q13: EXCL. (AS PER AGREEMENT) | R13: SEPARATE | S13: SEPARATE | T13: SEPARATE | U13: SEPARATE | V13: SEPARATE | W13: SEPARATE | X13: Y | Y13: Y | Z13: N | AA13: N | AB13: N | AC13: Y | AD13: N | AE13: Criteria as per POC SOP not met | AF13: =IF(AD13="Y",IF(AM13>1,"Y","N"),"") | AG13: =IFERROR(IF(NETWORKDAYS(C13+1,E13)>=2,"Y","N"),"N") -> Y | AH13: Queries were raised by the team, but the response from the owner was received late | AI13: N | AK13: =IFERROR(NETWORKDAYS(K13,$AM$1),"-") -> -253 | AL13: =IFERROR(NETWORKDAYS(M13,$AM$1),"-") -> -253 | AM13: =IFERROR(COUNTIFS($F$3:$F$1048576,F13,$G$3:$G$1048576,G13),"") -> 1
A14: 2025 | B14: =UPPER(TEXT(C14,"MMM")) -> FEB | C14: 46077 | E14: 46078 | F14: LESCHACO | G14: CHEMICAL ACCOUNT | H14: =UPPER(VLOOKUP(F14,Droplist!A:C,3,0)) -> MARTIN SCHULZ | I14: NADINE BEER | J14: 46083 | K14: 46387 | L14: 46083 | M14: 46112 | N14: SEPARATE | O14: SEPARATE | P14: SEPARATELY | Q14: EXCL. (AS PER AGREEMENT) | R14: SEPARATE | S14: SEPARATE | T14: SEPARATE | U14: SEPARATE | V14: SEPARATE | W14: SEPARATE | X14: Y | Y14: N | Z14: N | AA14: N | AB14: N | AC14: N | AD14: N | AE14: Criteria as per POC SOP not met | AF14: =IF(AD14="Y",IF(AM14>1,"Y","N"),"") | AG14: =IFERROR(IF(NETWORKDAYS(C14+1,E14)>=2,"Y","N"),"N") -> N | AI14: N | AK14: =IFERROR(NETWORKDAYS(K14,$AM$1),"-") -> -212 | AL14: =IFERROR(NETWORKDAYS(M14,$AM$1),"-") -> -15 | AM14: =IFERROR(COUNTIFS($F$3:$F$1048576,F14,$G$3:$G$1048576,G14),"") -> 3
A15: 2025 | B15: =UPPER(TEXT(C15,"MMM")) -> FEB | C15: 46077 | E15: 46078 | F15: A.HARTRODT | G15: GROHE | H15: =UPPER(VLOOKUP(F15,Droplist!A:C,3,0)) -> PETER ANDERSEN | I15: DOREEN LAM/MARIA GIRLIE | J15: 46084 | K15: 46387 | L15: 46084 | M15: 46387 | N15: SEPARATE | O15: EXCL. (AS PER AGREEMENT) | P15: SEPARATELY | Q15: EXCL. (AS PER AGREEMENT) | R15: SEPARATE | S15: SEPARATE | T15: SEPARATE | U15: SEPARATE | V15: SEPARATE | W15: SEPARATE | X15: N | Y15: N | Z15: N | AA15: N | AB15: N | AC15: Y | AD15: N | AE15: Maintenance / update rates | AF15: =IF(AD15="Y",IF(AM15>1,"Y","N"),"") | AG15: =IFERROR(IF(NETWORKDAYS(C15+1,E15)>=2,"Y","N"),"N") -> N | AI15: N | AK15: =IFERROR(NETWORKDAYS(K15,$AM$1),"-") -> -212 | AL15: =IFERROR(NETWORKDAYS(M15,$AM$1),"-") -> -212 | AM15: =IFERROR(COUNTIFS($F$3:$F$1048576,F15,$G$3:$G$1048576,G15),"") -> 1
A16: 2025 | B16: =UPPER(TEXT(C16,"MMM")) -> FEB | C16: 46078 | E16: 46079 | F16: KLN | G16: HONEYWELL | H16: =UPPER(VLOOKUP(F16,Droplist!A:C,3,0)) -> JENS POTTSCHUL | I16: MARIA GIRLIE/ YI WEI | J16: 46174 | K16: 46387 | L16: 46174 | M16: 46387 | N16: SEPARATE | O16: SEPARATE | P16: SEPARATELY | Q16: EXCL. (AS PER AGREEMENT) | R16: SEPARATE | S16: SEPARATE | T16: EXCL. AS PER ADVISORY | U16: EXCL. AS PER ADVISORY | V16: EXCL. AS PER ADVISORY | W16: EXCL. AS PER ADVISORY | X16: Y | Y16: N | Z16: N | AA16: N | AB16: N | AC16: Y | AD16: N | AE16: Criteria as per POC SOP not met | AF16: =IF(AD16="Y",IF(AM16>1,"Y","N"),"") | AG16: =IFERROR(IF(NETWORKDAYS(C16+1,E16)>=2,"Y","N"),"N") -> N | AI16: N | AK16: =IFERROR(NETWORKDAYS(K16,$AM$1),"-") -> -212 | AL16: =IFERROR(NETWORKDAYS(M16,$AM$1),"-") -> -212 | AM16: =IFERROR(COUNTIFS($F$3:$F$1048576,F16,$G$3:$G$1048576,G16),"") -> 1
A17: 2025 | B17: =UPPER(TEXT(C17,"MMM")) -> FEB | C17: 46078 | E17: 46079 | F17: LOGWIN | G17: PIP SAFETY | H17: =UPPER(VLOOKUP(F17,Droplist!A:C,3,0)) -> MARTIN SCHULZ | I17: SEEK ZOU GAN | J17: 46113 | K17: 46387 | L17: 46113 | M17: 46387 | N17: INCL. IN DOC FEE | O17: INCL. IN DOC FEE | P17: EXCL. (AS PER AGREEMENT) | Q17: EXCL. (AS PER AGREEMENT) | R17: SEPARATE | S17: EXCL. AS PER ADVISORY | T17: EXCL. AS PER ADVISORY | U17: EXCL. AS PER ADVISORY | V17: EXCL. AS PER ADVISORY | W17: EXCL. AS PER ADVISORY | X17: N | Y17: N | Z17: N | AA17: N | AB17: N | AC17: Y | AD17: N | AE17: All AU/NZ port pairs | AF17: =IF(AD17="Y",IF(AM17>1,"Y","N"),"") | AG17: =IFERROR(IF(NETWORKDAYS(C17+1,E17)>=2,"Y","N"),"N") -> N | AI17: N | AK17: =IFERROR(NETWORKDAYS(K17,$AM$1),"-") -> -212 | AL17: =IFERROR(NETWORKDAYS(M17,$AM$1),"-") -> -212 | AM17: =IFERROR(COUNTIFS($F$3:$F$1048576,F17,$G$3:$G$1048576,G17),"") -> 1
A18: 2025 | B18: =UPPER(TEXT(C18,"MMM")) -> FEB | C18: 46078 | E18: 46079 | F18: NIPPON | G18: MUJI | H18: =UPPER(VLOOKUP(F18,Droplist!A:C,3,0)) -> JENS POTTSCHUL | I18: MARIA GIRLIE | J18: 46113 | K18: 46387 | L18: 46113 | M18: 46387 | N18: SEPARATE | O18: SEPARATE | P18: INCL. IN DOC FEE | Q18: EXCL. (AS PER AGREEMENT) | R18: INCL IN OFR | S18: SEPARATE | T18: SEPARATE | U18: SEPARATE | V18: SEPARATE | W18: SEPARATE | X18: N | Y18: Y | Z18: N | AA18: N | AB18: N | AC18: Y | AD18: N | AE18: Criteria as per POC SOP not met | AF18: =IF(AD18="Y",IF(AM18>1,"Y","N"),"") | AG18: =IFERROR(IF(NETWORKDAYS(C18+1,E18)>=2,"Y","N"),"N") -> N | AI18: N | AK18: =IFERROR(NETWORKDAYS(K18,$AM$1),"-") -> -212 | AL18: =IFERROR(NETWORKDAYS(M18,$AM$1),"-") -> -212 | AM18: =IFERROR(COUNTIFS($F$3:$F$1048576,F18,$G$3:$G$1048576,G18),"") -> 1
A19: 2025 | B19: =UPPER(TEXT(C19,"MMM")) -> FEB | C19: 46078 | E19: 46079 | F19: CARGO PARTNER | G19: MINTH | H19: =UPPER(VLOOKUP(F19,Droplist!A:C,3,0)) -> DENNIS FRANKOWSKI | I19: MARIA GIRLIE/ SEEK ZOU GAN | J19: 46113 | K19: 46387 | L19: 46113 | M19: 46387 | N19: SEPARATE | O19: SEPARATE | P19: SEPARATELY | Q19: EXCL. (AS PER AGREEMENT) | R19: SEPARATE | S19: EXCL. AS PER ADVISORY | T19: EXCL. AS PER ADVISORY | U19: EXCL. AS PER ADVISORY | V19: EXCL. AS PER ADVISORY | W19: EXCL. AS PER ADVISORY | X19: N | Y19: Y | Z19: N | AA19: N | AB19: N | AC19: Y | AD19: N | AE19: Criteria as per POC SOP not met | AF19: =IF(AD19="Y",IF(AM19>1,"Y","N"),"") | AG19: =IFERROR(IF(NETWORKDAYS(C19+1,E19)>=2,"Y","N"),"N") -> N | AI19: N | AK19: =IFERROR(NETWORKDAYS(K19,$AM$1),"-") -> -212 | AL19: =IFERROR(NETWORKDAYS(M19,$AM$1),"-") -> -212 | AM19: =IFERROR(COUNTIFS($F$3:$F$1048576,F19,$G$3:$G$1048576,G19),"") -> 1
A20: 2025 | B20: =UPPER(TEXT(C20,"MMM")) -> FEB | C20: 46078 | E20: 46079 | F20: GEODIS | G20: TETRA PACK GROUP | H20: =UPPER(VLOOKUP(F20,Droplist!A:C,3,0)) -> MARTIN SCHULZ | I20: SUSANNE ELSBORG-JENSEN | J20: 46082 | K20: 46387 | L20: 46082 | M20: 46203 | N20: INCL. IN DOC FEE | O20: SEPARATE | P20: SEPARATELY | Q20: EXCL. (AS PER AGREEMENT) | R20: INCL IN OFR | S20: INCL. IN OFR | T20: INCL. IN OFR | U20: INCL. IN OFR | V20: INCL. IN OFR | W20: INCL. IN OFR | X20: N | Y20: Y | Z20: N | AA20: N | AB20: N | AC20: Y | AD20: N | AE20: Criteria as per POC SOP not met | AF20: =IF(AD20="Y",IF(AM20>1,"Y","N"),"") | AG20: =IFERROR(IF(NETWORKDAYS(C20+1,E20)>=2,"Y","N"),"N") -> N | AI20: N | AK20: =IFERROR(NETWORKDAYS(K20,$AM$1),"-") -> -212 | AL20: =IFERROR(NETWORKDAYS(M20,$AM$1),"-") -> -80 | AM20: =IFERROR(COUNTIFS($F$3:$F$1048576,F20,$G$3:$G$1048576,G20),"") -> 1
A21: 2025 | B21: =UPPER(TEXT(C21,"MMM")) -> FEB | C21: 46078 | E21: 46079 | F21: LOGWIN | G21: BEELINE | H21: =UPPER(VLOOKUP(F21,Droplist!A:C,3,0)) -> MARTIN SCHULZ | I21: DENNIS FRANKOWSKI | J21: 46113 | K21: 46387 | L21: 46113 | M21: 46295 | N21: SEPARATE | O21: SEPARATE | P21: INCL. IN DOC FEE | Q21: EXCL. (AS PER AGREEMENT) | R21: INCL IN OFR | S21: INCL. IN OFR | T21: SEPARATE | U21: SEPARATE | V21: SEPARATE | W21: SEPARATE | X21: N | Y21: N | Z21: N | AA21: N | AB21: N | AC21: N | AD21: N | AE21: Maintenance / update rates | AF21: =IF(AD21="Y",IF(AM21>1,"Y","N"),"") | AG21: =IFERROR(IF(NETWORKDAYS(C21+1,E21)>=2,"Y","N"),"N") -> N | AI21: N | AK21: =IFERROR(NETWORKDAYS(K21,$AM$1),"-") -> -212 | AL21: =IFERROR(NETWORKDAYS(M21,$AM$1),"-") -> -146 | AM21: =IFERROR(COUNTIFS($F$3:$F$1048576,F21,$G$3:$G$1048576,G21),"") -> 1
A22: 2025 | B22: =UPPER(TEXT(C22,"MMM")) -> FEB | C22: 46079 | E22: 46080 | F22: CEVA | G22: F&F | H22: =UPPER(VLOOKUP(F22,Droplist!A:C,3,0)) -> JAKOB BLUHME | I22: SANTIAGO MILIAN | J22: 46085 | K22: 46418 | L22: 46085 | M22: 46173 | N22: SEPARATE | O22: SEPARATE | P22: INCL. IN DOC FEE | Q22: EXCL. (AS PER AGREEMENT) | R22: INCL IN OFR | S22: INCL. IN OFR | T22: SEPARATE | U22: SEPARATE | V22: SEPARATE | W22: SEPARATE | X22: Y | Y22: Y | Z22: N | AA22: N | AB22: N | AC22: Y | AD22: N | AE22: Criteria as per POC SOP not met | AF22: =IF(AD22="Y",IF(AM22>1,"Y","N"),"") | AG22: =IFERROR(IF(NETWORKDAYS(C22+1,E22)>=2,"Y","N"),"N") -> N | AI22: N | AK22: =IFERROR(NETWORKDAYS(K22,$AM$1),"-") -> -233 | AL22: =IFERROR(NETWORKDAYS(M22,$AM$1),"-") -> -58 | AM22: =IFERROR(COUNTIFS($F$3:$F$1048576,F22,$G$3:$G$1048576,G22),"") -> 1
A23: 2025 | B23: =UPPER(TEXT(C23,"MMM")) -> MAR | C23: 46084 | E23: 46084 | F23: KLN | G23: AALBERTS BUILDING | H23: =UPPER(VLOOKUP(F23,Droplist!A:C,3,0)) -> JENS POTTSCHUL | I23: YI WEI / MARIA GIRLIE | J23: 46086 | K23: 46326 | L23: 46086 | M23: 46326 | N23: SEPARATE | O23: SEPARATE | P23: INCL. IN DOC FEE | Q23: INCL. IN DOC FEE | R23: INCL IN OFR | S23: EXCL. AS PER ADVISORY | T23: EXCL. AS PER ADVISORY | U23: EXCL. AS PER ADVISORY | V23: EXCL. AS PER ADVISORY | W23: EXCL. AS PER ADVISORY | X23: N | Y23: Y | Z23: N | AA23: N | AB23: N | AC23: Y | AD23: N | AE23: Criteria as per POC SOP not met | AF23: =IF(AD23="Y",IF(AM23>1,"Y","N"),"") | AG23: =IFERROR(IF(NETWORKDAYS(C23+1,E23)>=2,"Y","N"),"N") -> N | AI23: N | AK23: =IFERROR(NETWORKDAYS(K23,$AM$1),"-") -> -168 | AL23: =IFERROR(NETWORKDAYS(M23,$AM$1),"-") -> -168 | AM23: =IFERROR(COUNTIFS($F$3:$F$1048576,F23,$G$3:$G$1048576,G23),"") -> 1
A24: 2025 | B24: =UPPER(TEXT(C24,"MMM")) -> FEB | C24: 46076 | E24: 46077 | F24: CRANE WORLDWIDE | G24: IFF | H24: =UPPER(VLOOKUP(F24,Droplist!A:C,3,0)) -> METTE B. KARAPETIAN | I24: HELEN LI | J24: 46087 | K24: 46295 | L24: 46087 | M24: 46295 | N24: SEPARATE | O24: SEPARATE | P24: SEPARATELY | Q24: EXCL. (AS PER AGREEMENT) | R24: SEPARATE | S24: SEPARATE | T24: SEPARATE | U24: SEPARATE | V24: SEPARATE | W24: SEPARATE | X24: Y | Y24: Y | Z24: N | AA24: N | AB24: N | AC24: Y | AD24: N | AE24: Criteria as per POC SOP not met | AF24: =IF(AD24="Y",IF(AM24>1,"Y","N"),"") | AG24: =IFERROR(IF(NETWORKDAYS(C24+1,E24)>=2,"Y","N"),"N") -> N | AI24: N | AK24: =IFERROR(NETWORKDAYS(K24,$AM$1),"-") -> -146 | AL24: =IFERROR(NETWORKDAYS(M24,$AM$1),"-") -> -146 | AM24: =IFERROR(COUNTIFS($F$3:$F$1048576,F24,$G$3:$G$1048576,G24),"") -> 1
A25: 2025 | B25: =UPPER(TEXT(C25,"MMM")) -> MAR | C25: 46083 | E25: 46084 | F25: CEVA | G25: GENERAL ELECTRIC - GSA | H25: =UPPER(VLOOKUP(F25,Droplist!A:C,3,0)) -> JAKOB BLUHME | I25: SANTIAGO MILIAN | J25: 46096 | K25: 46387 | L25: 46096 | M25: 46203 | N25: SEPARATE | O25: SEPARATE | P25: SEPARATELY | Q25: EXCL. (AS PER AGREEMENT) | R25: INCL IN OFR | S25: INCL. IN OFR | T25: SEPARATE | U25: SEPARATE | V25: SEPARATE | W25: SEPARATE | X25: N | Y25: Y | Z25: N | AA25: N | AB25: N | AC25: Y | AD25: N | AE25: Criteria as per POC SOP not met | AF25: =IF(AD25="Y",IF(AM25>1,"Y","N"),"") | AG25: =IFERROR(IF(NETWORKDAYS(C25+1,E25)>=2,"Y","N"),"N") -> N | AI25: N | AK25: =IFERROR(NETWORKDAYS(K25,$AM$1),"-") -> -212 | AL25: =IFERROR(NETWORKDAYS(M25,$AM$1),"-") -> -80 | AM25: =IFERROR(COUNTIFS($F$3:$F$1048576,F25,$G$3:$G$1048576,G25),"") -> 1
... A31: 2025 | B31: =UPPER(TEXT(C31,"MMM")) -> MAR | C31: 46090 | E31: 46091 | F31: DSV | G31: DOW | H31: =UPPER(VLOOKUP(F31,Droplist!A:C,3,0)) -> #N/A | I31: SANTIAGO MILIAN | J31: 46113 | K31: 46203 | L31: 46113 | M31: 46203 | N31: INCL. IN DOC FEE | O31: INCL. IN DOC FEE | P31: SEPARATELY | Q31: INCL. IN DOC FEE | R31: SEPARATE | S31: SEPARATE | T31: SEPARATE | U31: SEPARATE | V31: SEPARATE | W31: SEPARATE | X31: Y | Y31: N | Z31: N | AA31: N | AB31: N | AC31: N | AD31: N | AE31: Criteria as per POC SOP not met | AF31: =IF(AD31="Y",IF(AM31>1,"Y","N"),"") | AG31: =IFERROR(IF(NETWORKDAYS(C31+1,E31)>=2,"Y","N"),"N") -> N | AI31: N | AK31: =IFERROR(NETWORKDAYS(K31,$AM$1),"-") -> -80 | AL31: =IFERROR(NETWORKDAYS(M31,$AM$1),"-") -> -80 | AM31: =IFERROR(COUNTIFS($F$3:$F$1048576,F31,$G$3:$G$1048576,G31),"") -> 1
A32: 2025 | B32: =UPPER(TEXT(C32,"MMM")) -> MAR | C32: 46084 | E32: 46087 | F32: DACHSER | G32: BOHLER | H32: =UPPER(VLOOKUP(F32,Droplist!A:C,3,0)) -> MARTIN SCHULZ | I32: NADINE BEER | J32: 46113 | K32: 46203 | L32: 46113 | M32: 46203 | N32: INCL. IN DOC FEE | O32: SEPARATE | P32: EXCL. (AS PER AGREEMENT) | Q32: EXCL. (AS PER AGREEMENT) | R32: SEPARATE | S32: INCL. IN OFR | T32: SEPARATE | U32: SEPARATE | V32: SEPARATE | W32: SEPARATE | X32: N | Y32: Y | Z32: N | AA32: N | AB32: N | AC32: N | AD32: N | AE32: Maintenance / update rates | AF32: =IF(AD32="Y",IF(AM32>1,"Y","N"),"") | AG32: =IFERROR(IF(NETWORKDAYS(C32+1,E32)>=2,"Y","N"),"N") -> Y | AH32: Released as per schedule | AI32: N | AK32: =IFERROR(NETWORKDAYS(K32,$AM$1),"-") -> -80 | AL32: =IFERROR(NETWORKDAYS(M32,$AM$1),"-") -> -80 | AM32: =IFERROR(COUNTIFS($F$3:$F$1048576,F32,$G$3:$G$1048576,G32),"") -> 1
A33: 2025 | B33: =UPPER(TEXT(C33,"MMM")) -> MAR | C33: 46084 | E33: 46085 | F33: DACHSER | G33: MAHLE | H33: =UPPER(VLOOKUP(F33,Droplist!A:C,3,0)) -> MARTIN SCHULZ | I33: NADINE BEER | J33: 46023 | K33: 46387 | L33: 46113 | M33: 46203 | N33: INCL. IN DOC FEE | O33: SEPARATE | P33: INCL. IN DOC FEE | Q33: EXCL. (AS PER AGREEMENT) | R33: INCL IN OFR | S33: INCL. IN OFR | T33: SEPARATE | U33: SEPARATE | V33: SEPARATE | W33: SEPARATE | X33: Y | Y33: Y | Z33: N | AA33: N | AB33: N | AC33: N | AD33: N | AE33: Criteria as per POC SOP not met | AF33: =IF(AD33="Y",IF(AM33>1,"Y","N"),"") | AG33: =IFERROR(IF(NETWORKDAYS(C33+1,E33)>=2,"Y","N"),"N") -> N | AI33: N | AK33: =IFERROR(NETWORKDAYS(K33,$AM$1),"-") -> -212 | AL33: =IFERROR(NETWORKDAYS(M33,$AM$1),"-") -> -80 | AM33: =IFERROR(COUNTIFS($F$3:$F$1048576,F33,$G$3:$G$1048576,G33),"") -> 1
A34: 2025 | B34: =UPPER(TEXT(C34,"MMM")) -> MAR | C34: 46084 | E34: 46090 | F34: JAS | G34: HEUBACH | H34: =UPPER(VLOOKUP(F34,Droplist!A:C,3,0)) -> CHRIS CROWDER | I34: NADINE BEER | J34: 46113 | K34: 46203 | L34: 46113 | M34: 46203 | N34: SEPARATE | O34: INCL. IN DOC FEE | P34: INCL. IN DOC FEE | Q34: EXCL. (AS PER AGREEMENT) | R34: INCL IN OFR | S34: INCL. IN OFR | T34: SEPARATE | U34: SEPARATE | V34: SEPARATE | W34: SEPARATE | X34: Y | Y34: N | Z34: N | AA34: N | AB34: N | AC34: N | AD34: N | AE34: Maintenance / update rates | AF34: =IF(AD34="Y",IF(AM34>1,"Y","N"),"") | AG34: =IFERROR(IF(NETWORKDAYS(C34+1,E34)>=2,"Y","N"),"N") -> Y | AH34: Released as per schedule | AI34: N | AK34: =IFERROR(NETWORKDAYS(K34,$AM$1),"-") -> -80 | AL34: =IFERROR(NETWORKDAYS(M34,$AM$1),"-") -> -80 | AM34: =IFERROR(COUNTIFS($F$3:$F$1048576,F34,$G$3:$G$1048576,G34),"") -> 1
A35: 2025 | B35: =UPPER(TEXT(C35,"MMM")) -> MAR | C35: 46084 | E35: 46090 | F35: LESCHACO | G35: CHEMICAL ACCOUNT | H35: =UPPER(VLOOKUP(F35,Droplist!A:C,3,0)) -> MARTIN SCHULZ | I35: NADINE BEER | J35: 46083 | K35: 46387 | L35: 46113 | M35: 46203 | N35: SEPARATE | O35: SEPARATE | P35: SEPARATELY | Q35: EXCL. (AS PER AGREEMENT) | R35: SEPARATE | S35: SEPARATE | T35: SEPARATE | U35: SEPARATE | V35: SEPARATE | W35: SEPARATE | X35: Y | Y35: N | Z35: N | AA35: N | AB35: N | AC35: N | AD35: N | AE35: Maintenance / update rates | AF35: =IF(AD35="Y",IF(AM35>1,"Y","N"),"") | AG35: =IFERROR(IF(NETWORKDAYS(C35+1,E35)>=2,"Y","N"),"N") -> Y | AH35: Released as per schedule | AI35: N | AK35: =IFERROR(NETWORKDAYS(K35,$AM$1),"-") -> -212 | AL35: =IFERROR(NETWORKDAYS(M35,$AM$1),"-") -> -80 | AM35: =IFERROR(COUNTIFS($F$3:$F$1048576,F35,$G$3:$G$1048576,G35),"") -> 3
A36: 2025 | B36: =UPPER(TEXT(C36,"MMM")) -> MAR | C36: 46085 | E36: 46087 | F36: GEODIS | G36: DIEBOLD NIXDORF | H36: =UPPER(VLOOKUP(F36,Droplist!A:C,3,0)) -> MARTIN SCHULZ | I36: SUSANNE ELSBORG-JENSEN | J36: 46027 | K36: 46387 | L36: 46113 | M36: 46203 | N36: SEPARATE | O36: SEPARATE | P36: SEPARATELY | Q36: EXCL. (AS PER AGREEMENT) | R36: SEPARATE | S36: SEPARATE | T36: SEPARATE | U36: SEPARATE | V36: SEPARATE | W36: SEPARATE | X36: N | Y36: N | Z36: N | AA36: N | AB36: N | AC36: Y | AD36: N | AE36: Maintenance / update rates | AF36: =IF(AD36="Y",IF(AM36>1,"Y","N"),"") | AG36: =IFERROR(IF(NETWORKDAYS(C36+1,E36)>=2,"Y","N"),"N") -> Y | AH36: Released as per schedule | AI36: N | AK36: =IFERROR(NETWORKDAYS(K36,$AM$1),"-") -> -212 | AL36: =IFERROR(NETWORKDAYS(M36,$AM$1),"-") -> -80 | AM36: =IFERROR(COUNTIFS($F$3:$F$1048576,F36,$G$3:$G$1048576,G36),"") -> 1
A37: 2025 | B37: =UPPER(TEXT(C37,"MMM")) -> MAR | C37: 46085 | E37: 46087 | F37: NOATUM | G37: BLUE OWL | H37: =UPPER(VLOOKUP(F37,Droplist!A:C,3,0)) -> JAKOB BLUHME / TOM HINE | I37: HELEN LI | J37: 46094 | K37: 46387 | L37: 46094 | M37: 46203 | N37: SEPARATE | O37: SEPARATE | P37: INCL. IN DOC FEE | Q37: EXCL. (AS PER AGREEMENT) | R37: SEPARATE | S37: SEPARATE | T37: SEPARATE | U37: SEPARATE | V37: SEPARATE | W37: SEPARATE | X37: Y | Y37: Y | Z37: N | AA37: N | AB37: N | AC37: Y | AD37: N | AE37: Criteria as per POC SOP not met | AF37: =IF(AD37="Y",IF(AM37>1,"Y","N"),"") | AG37: =IFERROR(IF(NETWORKDAYS(C37+1,E37)>=2,"Y","N"),"N") -> Y | AH37: Queries were raised by the team, but the response from the owner was received late | AI37: N | AK37: =IFERROR(NETWORKDAYS(K37,$AM$1),"-") -> -212 | AL37: =IFERROR(NETWORKDAYS(M37,$AM$1),"-") -> -80 | AM37: =IFERROR(COUNTIFS($F$3:$F$1048576,F37,$G$3:$G$1048576,G37),"") -> 1
A38: 2025 | B38: =UPPER(TEXT(C38,"MMM")) -> MAR | C38: 46084 | E38: 46090 | F38: LESCHACO | G38: BAYER COVESTRO LANXESS | H38: =UPPER(VLOOKUP(F38,Droplist!A:C,3,0)) -> MARTIN SCHULZ | I38: NADINE BEER | J38: 46023 | K38: 46387 | L38: 46113 | M38: 46203 | N38: SEPARATE | O38: SEPARATE | P38: SEPARATELY | Q38: EXCL. (AS PER AGREEMENT) | R38: SEPARATE | S38: SEPARATE | T38: SEPARATE | U38: SEPARATE | V38: SEPARATE | W38: SEPARATE | X38: Y | Y38: N | Z38: N | AA38: N | AB38: N | AC38: N | AD38: N | AE38: Maintenance / update rates | AF38: =IF(AD38="Y",IF(AM38>1,"Y","N"),"") | AG38: =IFERROR(IF(NETWORKDAYS(C38+1,E38)>=2,"Y","N"),"N") -> Y | AH38: Released as per schedule | AI38: N | AK38: =IFERROR(NETWORKDAYS(K38,$AM$1),"-") -> -212 | AL38: =IFERROR(NETWORKDAYS(M38,$AM$1),"-") -> -80 | AM38: =IFERROR(COUNTIFS($F$3:$F$1048576,F38,$G$3:$G$1048576,G38),"") -> 1
A39: 2025 | B39: =UPPER(TEXT(C39,"MMM")) -> MAR | C39: 46087 | E39: NA | F39: CARGO PARTNER | G39: KNORR BREMSE | H39: =UPPER(VLOOKUP(F39,Droplist!A:C,3,0)) -> DENNIS FRANKOWSKI | I39: SEEK ZOU GAN | J39: 46113 | K39: 46387 | L39: 46113 | M39: 46387 | N39: INCL. IN DOC FEE | O39: EXCL. (AS PER AGREEMENT) | P39: EXCL. (AS PER AGREEMENT) | Q39: EXCL. (AS PER AGREEMENT) | R39: SEPARATE | S39: EXCL. AS PER ADVISORY | T39: EXCL. AS PER ADVISORY | U39: EXCL. AS PER ADVISORY | V39: EXCL. AS PER ADVISORY | W39: EXCL. (AS PER AGREEMENT) | X39: N | Y39: N | Z39: N | AA39: N | AB39: N | AC39: N | AD39: Y | AE39: NA | AF39: =IF(AD39="Y",IF(AM39>1,"Y","N"),"") -> N | AG39: =IFERROR(IF(NETWORKDAYS(C39+1,E39)>=2,"Y","N"),"N") -> N | AI39: N | AK39: =IFERROR(NETWORKDAYS(K39,$AM$1),"-") -> -212 | AL39: =IFERROR(NETWORKDAYS(M39,$AM$1),"-") -> -212 | AM39: =IFERROR(COUNTIFS($F$3:$F$1048576,F39,$G$3:$G$1048576,G39),"") -> 1
A40: 2025 | B40: =UPPER(TEXT(C40,"MMM")) -> MAR | C40: 46091 | E40: 46092 | F40: FLEXPORT | G40: BOSCH | H40: =UPPER(VLOOKUP(F40,Droplist!A:C,3,0)) -> JENS POTTSCHUL | I40: MARIA GIRLIEL | J40: 46023 | K40: 46387 | L40: 46113 | M40: 46203 | N40: SEPARATE | O40: SEPARATE | P40: EXCL. (AS PER AGREEMENT) | Q40: EXCL. (AS PER AGREEMENT) | R40: SEPARATE | S40: SEPARATE | T40: EXCL. AS PER ADVISORY | U40: EXCL. AS PER ADVISORY | V40: EXCL. AS PER ADVISORY | W40: SEPARATE | X40: N | Y40: N | Z40: N | AA40: N | AB40: N | AC40: N | AD40: N | AE40: Maintenance / update rates | AF40: =IF(AD40="Y",IF(AM40>1,"Y","N"),"") | AG40: =IFERROR(IF(NETWORKDAYS(C40+1,E40)>=2,"Y","N"),"N") -> N | AI40: N | AK40: =IFERROR(NETWORKDAYS(K40,$AM$1),"-") -> -212 | AL40: =IFERROR(NETWORKDAYS(M40,$AM$1),"-") -> -80 | AM40: =IFERROR(COUNTIFS($F$3:$F$1048576,F40,$G$3:$G$1048576,G40),"") -> 1
A41: 2025 | B41: =UPPER(TEXT(C41,"MMM")) -> MAR | C41: 46091 | E41: 46092 | F41: JAS | G41: VALMET | H41: =UPPER(VLOOKUP(F41,Droplist!A:C,3,0)) -> CHRIS CROWDER | I41: SANTIAGO MILIAN | J41: 46023 | K41: 46203 | L41: 46113 | M41: 46203 | N41: EXCL. (AS PER AGREEMENT) | O41: EXCL. (AS PER AGREEMENT) | P41: INCL. IN DOC FEE | Q41: EXCL. (AS PER AGREEMENT) | R41: INCL IN OFR | S41: INCL. IN OFR | T41: EXCL. AS PER ADVISORY | U41: EXCL. AS PER ADVISORY | V41: EXCL. AS PER ADVISORY | W41: SEPARATE | X41: N | Y41: N | Z41: N | AA41: N | AB41: N | AC41: Y | AD41: N | AE41: Maintenance / update rates | AF41: =IF(AD41="Y",IF(AM41>1,"Y","N"),"") | AG41: =IFERROR(IF(NETWORKDAYS(C41+1,E41)>=2,"Y","N"),"N") -> N | AI41: N | AK41: =IFERROR(NETWORKDAYS(K41,$AM$1),"-") -> -80 | AL41: =IFERROR(NETWORKDAYS(M41,$AM$1),"-") -> -80 | AM41: =IFERROR(COUNTIFS($F$3:$F$1048576,F41,$G$3:$G$1048576,G41),"") -> 1
A42: 2025 | B42: =UPPER(TEXT(C42,"MMM")) -> MAR | C42: 46091 | E42: 46092 | F42: KLN | G42: ON RUNNING | H42: =UPPER(VLOOKUP(F42,Droplist!A:C,3,0)) -> JENS POTTSCHUL | I42: MARIA GIRLIEL | J42: 46023 | K42: 46387 | L42: 46113 | M42: 46203 | N42: SEPARATE | O42: SEPARATE | P42: SEPARATELY | Q42: INCL. IN FILING FEE | R42: INCL IN OFR | S42: INCL. IN OFR | T42: SEPARATE | U42: SEPARATE | V42: SEPARATE | W42: SEPARATE | X42: N | Y42: N | Z42: N | AA42: N | AB42: N | AC42: N | AD42: N | AE42: Maintenance / update rates | AF42: =IF(AD42="Y",IF(AM42>1,"Y","N"),"") | AG42: =IFERROR(IF(NETWORKDAYS(C42+1,E42)>=2,"Y","N"),"N") -> N | AI42: N | AK42: =IFERROR(NETWORKDAYS(K42,$AM$1),"-") -> -212 | AL42: =IFERROR(NETWORKDAYS(M42,$AM$1),"-") -> -80 | AM42: =IFERROR(COUNTIFS($F$3:$F$1048576,F42,$G$3:$G$1048576,G42),"") -> 1
A43: 2025 | B43: =UPPER(TEXT(C43,"MMM")) -> MAR | C43: 46091 | E43: NA | F43: CARGO PARTNER | G43: DELTA GROUP | H43: =UPPER(VLOOKUP(F43,Droplist!A:C,3,0)) -> DENNIS FRANKOWSKI | I43: SEEK ZOU GAN | J43: 46023 | K43: 46387 | L43: 46023 | M43: 46387 | N43: SEPARATE | O43: SEPARATE | P43: SEPARATELY | Q43: EXCL. (AS PER AGREEMENT) | R43: SEPARATE | S43: EXCL. AS PER ADVISORY | T43: EXCL. AS PER ADVISORY | U43: EXCL. AS PER ADVISORY | V43: EXCL. AS PER ADVISORY | W43: EXCL. AS PER ADVISORY | X43: N | Y43: N | Z43: N | AA43: N | AB43: N | AC43: Y | AD43: Y | AE43: NA | AF43: =IF(AD43="Y",IF(AM43>1,"Y","N"),"") -> N | AG43: =IFERROR(IF(NETWORKDAYS(C43+1,E43)>=2,"Y","N"),"N") -> N | AI43: N | AK43: =IFERROR(NETWORKDAYS(K43,$AM$1),"-") -> -212 | AL43: =IFERROR(NETWORKDAYS(M43,$AM$1),"-") -> -212 | AM43: =IFERROR(COUNTIFS($F$3:$F$1048576,F43,$G$3:$G$1048576,G43),"") -> 1
A44: 2025 | B44: =UPPER(TEXT(C44,"MMM")) -> MAR | C44: 46092 | E44: NA | F44: LOGISTEED | G44: MUJI | H44: =UPPER(VLOOKUP(F44,Droplist!A:C,3,0)) -> ROATHA LY | I44: MARY-ANNE CHUA | J44: 46113 | K44: 46387 | L44: 46113 | M44: 46203 | N44: SEPARATE | O44: SEPARATE | P44: SEPARATELY | Q44: EXCL. (AS PER AGREEMENT) | R44: SEPARATE | S44: SEPARATE | T44: SEPARATE | U44: SEPARATE | V44: SEPARATE | W44: SEPARATE | X44: N | Y44: N | Z44: N | AA44: N | AB44: N | AC44: N | AD44: Y | AE44: NA | AF44: N | AG44: =IFERROR(IF(NETWORKDAYS(C44+1,E44)>=2,"Y","N"),"N") -> N | AI44: N | AK44: =IFERROR(NETWORKDAYS(K44,$AM$1),"-") -> -212 | AL44: =IFERROR(NETWORKDAYS(M44,$AM$1),"-") -> -80 | AM44: =IFERROR(COUNTIFS($F$3:$F$1048576,F44,$G$3:$G$1048576,G44),"") -> 1
A45: 2025 | B45: =UPPER(TEXT(C45,"MMM")) -> MAR | C45: 46092 | E45: 46093 | F45: NTG AIR AND OCEAN | G45: REGAL REXNORD | H45: =UPPER(VLOOKUP(F45,Droplist!A:C,3,0)) -> SUSANNE ELSBORG-JENSEN | I45: SANTIAGO MILIAN | J45: 46113 | K45: 46203 | L45: 46113 | M45: 46203 | N45: SEPARATE | O45: SEPARATE | P45: SEPARATELY | Q45: EXCL. (AS PER AGREEMENT) | R45: SEPARATE | S45: SEPARATE | T45: SEPARATE | U45: SEPARATE | V45: SEPARATE | W45: SEPARATE | X45: N | Y45: Y | Z45: N | AA45: N | AB45: N | AC45: N | AD45: N | AE45: Criteria as per POC SOP not met | AF45: N | AG45: =IFERROR(IF(NETWORKDAYS(C45+1,E45)>=2,"Y","N"),"N") -> N | AI45: N | AK45: =IFERROR(NETWORKDAYS(K45,$AM$1),"-") -> -80 | AL45: =IFERROR(NETWORKDAYS(M45,$AM$1),"-") -> -80 | AM45: =IFERROR(COUNTIFS($F$3:$F$1048576,F45,$G$3:$G$1048576,G45),"") -> 1
A46: 2025 | B46: =UPPER(TEXT(C46,"MMM")) -> MAR | C46: 46093 | E46: 46093 | F46: A.HARTRODT | G46: VIBRACOUSTIC | H46: =UPPER(VLOOKUP(F46,Droplist!A:C,3,0)) -> PETER ANDERSEN | I46: JUSTIN DE BRUIJN | J46: 46113 | K46: 46387 | L46: 46113 | M46: 46203 | N46: SEPARATE | O46: SEPARATE | P46: INCL. IN DOC FEE | Q46: EXCL. (AS PER AGREEMENT) | R46: SEPARATE | S46: SEPARATE | T46: SEPARATE | U46: SEPARATE | V46: SEPARATE | W46: SEPARATE | X46: N | Y46: Y | Z46: N | AA46: N | AB46: N | AC46: N | AD46: N | AE46: Criteria as per POC SOP not met | AF46: N | AG46: =IFERROR(IF(NETWORKDAYS(C46+1,E46)>=2,"Y","N"),"N") -> N | AI46: N | AK46: =IFERROR(NETWORKDAYS(K46,$AM$1),"-") -> -212 | AL46: =IFERROR(NETWORKDAYS(M46,$AM$1),"-") -> -80 | AM46: =IFERROR(COUNTIFS($F$3:$F$1048576,F46,$G$3:$G$1048576,G46),"") -> 1
A47: 2025 | B47: =UPPER(TEXT(C47,"MMM")) -> MAR | C47: 46093 | E47: 46093 | F47: GEODIS | G47: ABB | H47: =UPPER(VLOOKUP(F47,Droplist!A:C,3,0)) -> MARTIN SCHULZ | I47: SUSANNE ELSBORG-JENSEN | J47: 46055 | K47: 46387 | L47: 46113 | M47: 46203 | N47: INCL. IN DOC FEE | O47: INCL. IN DOC FEE | P47: INCL. IN DOC FEE | Q47: EXCL. (AS PER AGREEMENT) | R47: INCL IN OFR | S47: INCL. IN OFR | T47: INCL. IN OFR | U47: INCL. IN OFR | V47: INCL. IN OFR | W47: INCL. IN OFR | X47: N | Y47: Y | Z47: N | AA47: N | AB47: N | AC47: Y | AD47: N | AE47: Criteria as per POC SOP not met | AF47: N | AG47: N | AI47: N | AK47: =IFERROR(NETWORKDAYS(K47,$AM$1),"-") -> -212 | AL47: =IFERROR(NETWORKDAYS(M47,$AM$1),"-") -> -80 | AM47: =IFERROR(COUNTIFS($F$3:$F$1048576,F47,$G$3:$G$1048576,G47),"") -> 1
A48: 2025 | B48: =UPPER(TEXT(C48,"MMM")) -> MAR | C48: 46094 | E48: 46097 | F48: CEVA | G48: SCHNEIDER | H48: =UPPER(VLOOKUP(F48,Droplist!A:C,3,0)) -> JAKOB BLUHME | I48: SANTIAGO MILIAN | J48: 46113 | K48: 46477 | L48: 46113 | M48: 46203 | N48: SEPARATE | O48: SEPARATE | P48: INCL. IN DOC FEE | Q48: EXCL. (AS PER AGREEMENT) | R48: INCL IN OFR | S48: INCL. IN OFR | T48: SEPARATE | U48: SEPARATE | V48: SEPARATE | W48: SEPARATE | X48: N | Y48: Y | Z48: N | AA48: N | AB48: N | AC48: Y | AD48: N | AE48: Criteria as per POC SOP not met | AF48: N | AG48: =IFERROR(IF(NETWORKDAYS(C48+1,E48)>=2,"Y","N"),"N") -> N | AI48: N | AK48: =IFERROR(NETWORKDAYS(K48,$AM$1),"-") -> -276 | AL48: =IFERROR(NETWORKDAYS(M48,$AM$1),"-") -> -80 | AM48: =IFERROR(COUNTIFS($F$3:$F$1048576,F48,$G$3:$G$1048576,G48),"") -> 2
A49: 2025 | B49: =UPPER(TEXT(C49,"MMM")) -> MAR | C49: 46097 | E49: 46097 | F49: MORRISON EXPRESS | G49: ANSELL | H49: =UPPER(VLOOKUP(F49,Droplist!A:C,3,0)) -> KEVIN TAYLOR | I49: RONAN TEOH | J49: 46082 | K49: 46387 | L49: 46113 | M49: 46203 | N49: INCL. IN DOC FEE | O49: EXCL. (AS PER AGREEMENT) | P49: INCL. IN DOC FEE | Q49: EXCL. (AS PER AGREEMENT) | R49: SEPARATE | S49: SEPARATE | T49: SEPARATE | U49: SEPARATE | V49: SEPARATE | W49: SEPARATE | X49: N | Y49: N | Z49: N | AA49: N | AB49: N | AC49: N | AD49: N | AE49: Maintenance / update rates | AF49: =IF(AD49="Y",IF(AM49>1,"Y","N"),"") | AG49: =IFERROR(IF(NETWORKDAYS(C49+1,E49)>=2,"Y","N"),"N") -> N | AI49: N | AK49: =IFERROR(NETWORKDAYS(K49,$AM$1),"-") -> -212 | AL49: =IFERROR(NETWORKDAYS(M49,$AM$1),"-") -> -80 | AM49: =IFERROR(COUNTIFS($F$3:$F$1048576,F49,$G$3:$G$1048576,G49),"") -> 2
A50: 2025 | B50: =UPPER(TEXT(C50,"MMM")) -> MAR | C50: 46098 | E50: 46098 | F50: RHENUS | G50: TDK | H50: =UPPER(VLOOKUP(F50,Droplist!A:C,3,0)) -> JENS POTTSCHUL | I50: MARIA GIRLIEL | J50: 46113 | K50: 46203 | L50: 46113 | M50: 46203 | N50: SEPARATE | O50: SEPARATE | P50: INCL. IN DOC FEE | Q50: EXCL. (AS PER AGREEMENT) | R50: SEPARATE | S50: SEPARATE | T50: SEPARATE | U50: SEPARATE | V50: SEPARATE | W50: SEPARATE | X50: N | Y50: N | Z50: N | AA50: N | AB50: N | AC50: N | AD50: Y | AE50: Criteria as per POC SOP not met | AF50: =IF(AD50="Y",IF(AM50>1,"Y","N"),"") -> N | AG50: =IFERROR(IF(NETWORKDAYS(C50+1,E50)>=2,"Y","N"),"N") -> N | AI50: N | AK50: =IFERROR(NETWORKDAYS(K50,$AM$1),"-") -> -80 | AL50: =IFERROR(NETWORKDAYS(M50,$AM$1),"-") -> -80 | AM50: =IFERROR(COUNTIFS($F$3:$F$1048576,F50,$G$3:$G$1048576,G50),"") -> 1
A51: 2025 | B51: =UPPER(TEXT(C51,"MMM")) -> MAR | C51: 46097 | E51: 46097 | F51: KLN | G51: STANLEY BLACK & DECKER | H51: =UPPER(VLOOKUP(F51,Droplist!A:C,3,0)) -> JENS POTTSCHUL | I51: YI WEI | J51: 46023 | K51: 46387 | L51: 46113 | M51: 46203 | N51: SEPARATE | O51: SEPARATE | P51: INCL. IN DOC FEE | Q51: INCL. IN FILING FEE | R51: INCL IN OFR | S51: EXCL. AS PER ADVISORY | T51: EXCL. AS PER ADVISORY | U51: EXCL. AS PER ADVISORY | V51: EXCL. AS PER ADVISORY | W51: EXCL. AS PER ADVISORY | X51: N | Y51: N | Z51: N | AA51: N | AB51: N | AC51: N | AD51: N | AE51: Maintenance / update rates | AF51: =IF(AD51="Y",IF(AM51>1,"Y","N"),"") | AG51: =IFERROR(IF(NETWORKDAYS(C51+1,E51)>=2,"Y","N"),"N") -> N | AI51: N | AK51: =IFERROR(NETWORKDAYS(K51,$AM$1),"-") -> -212 | AL51: =IFERROR(NETWORKDAYS(M51,$AM$1),"-") -> -80 | AM51: =IFERROR(COUNTIFS($F$3:$F$1048576,F51,$G$3:$G$1048576,G51),"") -> 1
A52: 2025 | B52: =UPPER(TEXT(C52,"MMM")) -> MAR | C52: 46084 | E52: 46084 | F52: LESCHACO | G52: CHEMICAL ACCOUNT | H52: =UPPER(VLOOKUP(F52,Droplist!A:C,3,0)) -> MARTIN SCHULZ | I52: NADINE BEER | J52: 46083 | K52: 46387 | L52: 46113 | M52: 46112 | N52: SEPARATE | O52: SEPARATE | P52: SEPARATELY | Q52: EXCL. (AS PER AGREEMENT) | R52: SEPARATE | S52: SEPARATE | T52: SEPARATE | U52: SEPARATE | V52: SEPARATE | W52: SEPARATE | X52: Y | Y52: N | Z52: N | AA52: N | AB52: N | AC52: N | AD52: N | AE52: Criteria as per POC SOP not met | AF52: N | AG52: =IFERROR(IF(NETWORKDAYS(C52+1,E52)>=2,"Y","N"),"N") -> N | AI52: N | AK52: =IFERROR(NETWORKDAYS(K52,$AM$1),"-") -> -212 | AL52: =IFERROR(NETWORKDAYS(M52,$AM$1),"-") -> -15 | AM52: =IFERROR(COUNTIFS($F$3:$F$1048576,F52,$G$3:$G$1048576,G52),"") -> 3
A53: 2025 | B53: =UPPER(TEXT(C53,"MMM")) -> MAR | C53: 46093 | E53: 46097 | F53: GEODIS | G53: HUSQVARNA | H53: =UPPER(VLOOKUP(F53,Droplist!A:C,3,0)) -> MARTIN SCHULZ | I53: SUSANNE ELSBORG-JENSEN | J53: 46113 | K53: 46387 | L53: 46113 | M53: 46203 | N53: SEPARATE | O53: INCL. IN DOC FEE | P53: SEPARATELY | Q53: EXCL. (AS PER AGREEMENT) | R53: SEPARATE | S53: SEPARATE | T53: SEPARATE | U53: SEPARATE | V53: SEPARATE | W53: SEPARATE | X53: N | Y53: Y | Z53: N | AA53: N | AB53: N | AC53: Y | AD53: N | AE53: Criteria as per POC SOP not met | AF53: N | AG53: N | AI53: N | AK53: =IFERROR(NETWORKDAYS(K53,$AM$1),"-") -> -212 | AL53: =IFERROR(NETWORKDAYS(M53,$AM$1),"-") -> -80 | AM53: =IFERROR(COUNTIFS($F$3:$F$1048576,F53,$G$3:$G$1048576,G53),"") -> 1
A54: 2025 | B54: =UPPER(TEXT(C54,"MMM")) -> MAR | C54: 46099 | E54: 46100 | F54: CARGO PARTNER | G54: GKN | H54: =UPPER(VLOOKUP(F54,Droplist!A:C,3,0)) -> DENNIS FRANKOWSKI | I54: SEEK ZOU GAN | J54: 46113 | K54: 46203 | L54: 46113 | M54: 46203 | N54: SEPARATE | O54: SEPARATE | P54: SEPARATELY | Q54: EXCL. (AS PER AGREEMENT) | R54: SEPARATE | S54: SEPARATE | T54: SEPARATE | U54: SEPARATE | V54: SEPARATE | W54: SEPARATE | X54: N | Y54: N | Z54: N | AA54: N | AB54: N | AC54: N | AD54: N | AE54: Maintenance / update rates | AF54: =IF(AD54="Y",IF(AM54>1,"Y","N"),"") | AG54: N | AI54: N | AK54: =IFERROR(NETWORKDAYS(K54,$AM$1),"-") -> -80 | AL54: =IFERROR(NETWORKDAYS(M54,$AM$1),"-") -> -80 | AM54: =IFERROR(COUNTIFS($F$3:$F$1048576,F54,$G$3:$G$1048576,G54),"") -> 1
A55: 2025 | B55: =UPPER(TEXT(C55,"MMM")) -> MAR | C55: 46104 | E55: NA | F55: KLN | G55: NEW BALANCE | H55: =UPPER(VLOOKUP(F55,Droplist!A:C,3,0)) -> JENS POTTSCHUL | I55: MARIA GIRLIEL | J55: 46113 | K55: 46203 | L55: 46113 | M55: 46203 | N55: SEPARATE | O55: SEPARATE | P55: SEPARATELY | Q55: INCL. IN FILING FEE | R55: SEPARATE | S55: SEPARATE | T55: SEPARATE | U55: SEPARATE | V55: SEPARATE | W55: EXCL. AS PER ADVISORY | X55: N | Y55: Y | Z55: N | AA55: N | AB55: N | AC55: Y | AD55: N | AE55: Surcharge update as per WWA Advisory | AF55: N | AG55: =IFERROR(IF(NETWORKDAYS(C55+1,E55)>=2,"Y","N"),"N") -> N | AI55: N | AK55: =IFERROR(NETWORKDAYS(K55,$AM$1),"-") -> -80 | AL55: =IFERROR(NETWORKDAYS(M55,$AM$1),"-") -> -80 | AM55: =IFERROR(COUNTIFS($F$3:$F$1048576,F55,$G$3:$G$1048576,G55),"") -> 2
A56: 2025 | B56: =UPPER(TEXT(C56,"MMM")) -> MAR | C56: 46104 | E56: 46106 | F56: KINTETSU | G56: DELL | H56: =UPPER(VLOOKUP(F56,Droplist!A:C,3,0)) -> JENS POTTSCHUL | I56: SEEK ZOU GAN | J56: 46235 | K56: 46599 | L56: 46235 | M56: 46599 | N56: SEPARATE | O56: SEPARATE | P56: EXCL. (AS PER AGREEMENT) | Q56: EXCL. (AS PER AGREEMENT) | R56: SEPARATE | S56: EXCL. AS PER ADVISORY | T56: EXCL. AS PER ADVISORY | U56: EXCL. AS PER ADVISORY | V56: EXCL. AS PER ADVISORY | W56: EXCL. AS PER ADVISORY | X56: N | Y56: Y | Z56: N | AA56: N | AB56: N | AC56: Y | AD56: N | AE56: Criteria as per POC SOP not met | AF56: N | AG56: N | AI56: N | AK56: =IFERROR(NETWORKDAYS(K56,$AM$1),"-") -> -363 | AL56: =IFERROR(NETWORKDAYS(M56,$AM$1),"-") -> -363 | AM56: =IFERROR(COUNTIFS($F$3:$F$1048576,F56,$G$3:$G$1048576,G56),"") -> 1
A57: 2025 | B57: MAR | C57: 46104 | E57: 46105 | F57: GEODIS | G57: VOLVO | H57: =UPPER(VLOOKUP(F57,Droplist!A:C,3,0)) -> MARTIN SCHULZ | I57: SUSANNE ELSBORG-JENSEN | J57: 46070 | K57: 46387 | L57: 46113 | M57: 46203 | N57: INCL. IN DOC FEE | O57: INCL. IN DOC FEE | P57: INCL. IN DOC FEE | Q57: EXCL. (AS PER AGREEMENT) | R57: SEPARATE | S57: SEPARATE | T57: SEPARATE | U57: SEPARATE | V57: SEPARATE | W57: SEPARATE | X57: Y | Y57: Y | Z57: N | AA57: N | AB57: N | AC57: Y | AD57: N | AE57: Criteria as per POC SOP not met | AF57: N | AG57: N | AI57: N | AK57: =IFERROR(NETWORKDAYS(K57,$AM$1),"-") -> -212 | AL57: =IFERROR(NETWORKDAYS(M57,$AM$1),"-") -> -80 | AM57: =IFERROR(COUNTIFS($F$3:$F$1048576,F57,$G$3:$G$1048576,G57),"") -> 1
A58: 2025 | B58: =UPPER(TEXT(C58,"MMM")) -> MAR | C58: 46101 | E58: 46105 | F58: NIPPON | G58: MAHLE | H58: =UPPER(VLOOKUP(F58,Droplist!A:C,3,0)) -> JENS POTTSCHUL | I58: MARIA GIRLIEL | J58: 46113 | K58: 46203 | L58: 46113 | M58: 46203 | N58: SEPARATE | O58: SEPARATE | P58: EXCL. (AS PER AGREEMENT) | Q58: EXCL. (AS PER AGREEMENT) | R58: SEPARATE | S58: INCL. IN OFR | T58: SEPARATE | U58: SEPARATE | V58: SEPARATE | W58: SEPARATE | X58: N | Y58: Y | Z58: N | AA58: N | AB58: N | AC58: Y | AD58: N | AE58: Criteria as per POC SOP not met | AF58: N | AG58: N | AH58: =IF(AF58="Y",IF(AO58>1,"Y","N"),"") | AI58: N | AJ58: =IF(AH58="Y",IF(AQ58>1,"Y","N"),"") | AK58: =IFERROR(NETWORKDAYS(K58,$AM$1),"-") -> -80 | AL58: =IFERROR(NETWORKDAYS(M58,$AM$1),"-") -> -80 | AM58: =IFERROR(COUNTIFS($F$3:$F$1048576,F58,$G$3:$G$1048576,G58),"") -> 1
A59: 2025 | B59: =UPPER(TEXT(C59,"MMM")) -> MAR | C59: 46104 | E59: 46106 | F59: APL LOGISTICS | G59: TJX | H59: =UPPER(VLOOKUP(F59,Droplist!A:C,3,0)) -> MICHELLE YU | I59: NADINE BEER | J59: 46113 | K59: 46203 | L59: 46113 | M59: 46203 | N59: EXCL. (AS PER AGREEMENT) | O59: EXCL. (AS PER AGREEMENT) | P59: INCL. IN DOC FEE | Q59: INCL. IN DOC FEE | R59: SEPARATE | S59: EXCL. AS PER ADVISORY | T59: EXCL. AS PER ADVISORY | U59: EXCL. AS PER ADVISORY | V59: EXCL. AS PER ADVISORY | W59: SEPARATE | X59: N | Y59: N | Z59: N | AA59: N | AB59: N | AC59: N | AD59: N | AE59: Maintenance / update rates | AF59: =IF(AD59="Y",IF(AM59>1,"Y","N"),"") | AG59: N | AH59: =IF(AF59="Y",IF(AO59>1,"Y","N"),"") | AI59: N | AJ59: =IF(AH59="Y",IF(AQ59>1,"Y","N"),"") | AK59: =IFERROR(NETWORKDAYS(K59,$AM$1),"-") -> -80 | AL59: =IFERROR(NETWORKDAYS(M59,$AM$1),"-") -> -80 | AM59: =IFERROR(COUNTIFS($F$3:$F$1048576,F59,$G$3:$G$1048576,G59),"") -> 1
A60: 2025 | B60: =UPPER(TEXT(C60,"MMM")) -> MAR | C60: 46107 | E60: NA | F60: RHENUS | G60: GROUPE | H60: =UPPER(VLOOKUP(F60,Droplist!A:C,3,0)) -> JENS POTTSCHUL | I60: DOREEN LAM | J60: 46113 | K60: 46203 | L60: 46113 | M60: 46203 | N60: SEPARATE | O60: SEPARATE | P60: SEPARATELY | Q60: EXCL. (AS PER AGREEMENT) | R60: SEPARATE | S60: SEPARATE | T60: SEPARATE | U60: SEPARATE | V60: SEPARATE | W60: SEPARATE | X60: N | Y60: N | Z60: N | AA60: N | AB60: N | AC60: N | AD60: Y | AE60: NA | AF60: N | AG60: N | AH60: =IF(AF60="Y",IF(AO60>1,"Y","N"),"") | AI60: N | AJ60: =IF(AH60="Y",IF(AQ60>1,"Y","N"),"") | AK60: =IFERROR(NETWORKDAYS(K60,$AM$1),"-") -> -80 | AL60: =IFERROR(NETWORKDAYS(M60,$AM$1),"-") -> -80 | AM60: =IFERROR(COUNTIFS($F$3:$F$1048576,F60,$G$3:$G$1048576,G60),"") -> 1
A61: 2025 | B61: =UPPER(TEXT(C61,"MMM")) -> MAR | C61: 46107 | E61: 46108 | F61: NNR | G61: PANASONIC | H61: =UPPER(VLOOKUP(F61,Droplist!A:C,3,0)) -> JENS POTTSCHUL | I61: HELEN LI | J61: 46113 | K61: 46477 | L61: 46113 | M61: 46477 | N61: SEPARATE | O61: SEPARATE | P61: INCL. IN DOC FEE | Q61: EXCL. (AS PER AGREEMENT) | R61: EXCL. AS PER ADVISORY | S61: EXCL. AS PER ADVISORY | T61: EXCL. AS PER ADVISORY | U61: EXCL. AS PER ADVISORY | V61: EXCL. AS PER ADVISORY | W61: EXCL. AS PER ADVISORY | X61: N | Y61: N | Z61: N | AA61: N | AB61: N | AC61: N | AD61: N | AE61: Criteria as per POC SOP not met | AF61: =IF(AD61="Y",IF(AM61>1,"Y","N"),"") | AG61: N | AH61: =IF(AF61="Y",IF(AO61>1,"Y","N"),"") | AI61: N | AJ61: =IF(AH61="Y",IF(AQ61>1,"Y","N"),"") | AK61: =IFERROR(NETWORKDAYS(K61,$AM$1),"-") -> -276 | AL61: =IFERROR(NETWORKDAYS(M61,$AM$1),"-") -> -276 | AM61: =IFERROR(COUNTIFS($F$3:$F$1048576,F61,$G$3:$G$1048576,G61),"") -> 1
A62: 2025 | B62: =UPPER(TEXT(C62,"MMM")) -> MAR | C62: 46107 | E62: 46108 | F62: JAS | G62: LEAR | H62: =UPPER(VLOOKUP(F62,Droplist!A:C,3,0)) -> CHRIS CROWDER | I62: HELEN LI | J62: 46113 | K62: 46173 | L62: 46113 | M62: 46173 | N62: SEPARATE | O62: INCL. IN DOC FEE | P62: INCL. IN DOC FEE | Q62: INCL. IN DOC FEE | R62: EXCL. AS PER ADVISORY | S62: SEPARATE | T62: EXCL. AS PER ADVISORY | U62: EXCL. AS PER ADVISORY | V62: EXCL. AS PER ADVISORY | W62: EXCL. AS PER ADVISORY | X62: N | Y62: N | Z62: N | AA62: N | AB62: N | AC62: N | AD62: N | AE62: Criteria as per POC SOP not met | AF62: =IF(AD62="Y",IF(AM62>1,"Y","N"),"") | AG62: N | AH62: =IF(AF62="Y",IF(AO62>1,"Y","N"),"") | AI62: N | AJ62: =IF(AH62="Y",IF(AQ62>1,"Y","N"),"") | AK62: =IFERROR(NETWORKDAYS(K62,$AM$1),"-") -> -58 | AL62: =IFERROR(NETWORKDAYS(M62,$AM$1),"-") -> -58 | AM62: =IFERROR(COUNTIFS($F$3:$F$1048576,F62,$G$3:$G$1048576,G62),"") -> 1
A63: 2025 | B63: =UPPER(TEXT(C63,"MMM")) -> MAR | C63: 46107 | E63: 46108 | F63: UPS | G63: PRESIDO | H63: =UPPER(VLOOKUP(F63,Droplist!A:C,3,0)) -> ROBERTA MACLEOD-STUART | I63: HELEN LI | J63: 46113 | K63: 46477 | L63: 46113 | M63: 46477 | N63: SEPARATE | O63: SEPARATE | P63: SEPARATELY | Q63: EXCL. (AS PER AGREEMENT) | R63: SEPARATE | S63: INCL. IN OFR | T63: SEPARATE | U63: SEPARATE | V63: SEPARATE | W63: SEPARATE | X63: N | Y63: N | Z63: N | AA63: N | AB63: N | AC63: N | AD63: N | AE63: Criteria as per POC SOP not met | AF63: =IF(AD63="Y",IF(AM63>1,"Y","N"),"") | AG63: N | AH63: =IF(AF63="Y",IF(AO63>1,"Y","N"),"") | AI63: N | AJ63: =IF(AH63="Y",IF(AQ63>1,"Y","N"),"") | AK63: =IFERROR(NETWORKDAYS(K63,$AM$1),"-") -> -276 | AL63: =IFERROR(NETWORKDAYS(M63,$AM$1),"-") -> -276 | AM63: =IFERROR(COUNTIFS($F$3:$F$1048576,F63,$G$3:$G$1048576,G63),"") -> 1
A64: 2025 | B64: =UPPER(TEXT(C64,"MMM")) -> MAR | C64: 46109 | E64: 46111 | F64: OIA | G64: DELL | H64: =UPPER(VLOOKUP(F64,Droplist!A:C,3,0)) -> KEVIN TAYLOR | I64: HELEN LI | J64: 46143 | K64: 46507 | L64: 46143 | M64: 46203 | N64: SEPARATE | O64: SEPARATE | P64: INCL. IN DOC FEE | Q64: EXCL. (AS PER AGREEMENT) | R64: SEPARATE | S64: SEPARATE | T64: SEPARATE | U64: SEPARATE | V64: SEPARATE | W64: SEPARATE | X64: N | Y64: Y | Z64: N | AA64: N | AB64: N | AC64: N | AD64: N | AE64: Criteria as per POC SOP not met | AF64: N | AG64: N | AH64: =IF(AF64="Y",IF(AO64>1,"Y","N"),"") | AI64: N | AJ64: =IF(AH64="Y",IF(AQ64>1,"Y","N"),"") | AK64: =IFERROR(NETWORKDAYS(K64,$AM$1),"-") -> -298 | AL64: =IFERROR(NETWORKDAYS(M64,$AM$1),"-") -> -80 | AM64: =IFERROR(COUNTIFS($F$3:$F$1048576,F64,$G$3:$G$1048576,G64),"") -> 1
A65: 2025 | B65: =UPPER(TEXT(C65,"MMM")) -> MAR | C65: 46112 | E65: 46112 | F65: TOLL GROUP | G65: EVONIK | H65: =UPPER(VLOOKUP(F65,Droplist!A:C,3,0)) -> JENS POTTSCHUL | I65: NADINE BEER | J65: 46121 | K65: 46387 | L65: 46121 | M65: 46142 | N65: SEPARATE | O65: SEPARATE | P65: SEPARATELY | Q65: EXCL. (AS PER AGREEMENT) | R65: SEPARATE | S65: SEPARATE | T65: SEPARATE | U65: SEPARATE | V65: SEPARATE | W65: SEPARATE | X65: N | Y65: N | Z65: N | AA65: N | AB65: N | AC65: N | AD65: N | AE65: Maintenance / update rates | AF65: =IF(AD65="Y",IF(AM65>1,"Y","N"),"") | AG65: N | AH65: =IF(AF65="Y",IF(AO65>1,"Y","N"),"") | AI65: N | AJ65: =IF(AH65="Y",IF(AQ65>1,"Y","N"),"") | AK65: =IFERROR(NETWORKDAYS(K65,$AM$1),"-") -> -212 | AL65: =IFERROR(NETWORKDAYS(M65,$AM$1),"-") -> -37 | AM65: =IFERROR(COUNTIFS($F$3:$F$1048576,F65,$G$3:$G$1048576,G65),"") -> 1
A66: 2025 | B66: =UPPER(TEXT(C66,"APRIL")) -> APRIL | C66: 46113 | E66: NA | F66: LOGISTEED | G66: OTIS | H66: =UPPER(VLOOKUP(F66,Droplist!A:C,3,0)) -> ROATHA LY | I66: ROATHA LY | J66: 46118 | K66: 46387 | L66: 46118 | M66: 46203 | N66: SEPARATE | O66: SEPARATE | P66: SEPARATELY | Q66: EXCL. (AS PER AGREEMENT) | R66: SEPARATE | S66: SEPARATE | T66: SEPARATE | U66: SEPARATE | V66: SEPARATE | W66: SEPARATE | X66: N | Y66: N | Z66: N | AA66: N | AB66: N | AC66: N | AD66: Y | AE66: NA | AF66: N | AG66: N | AH66: =IF(AF66="Y",IF(AO66>1,"Y","N"),"") | AI66: N | AJ66: =IF(AH66="Y",IF(AQ66>1,"Y","N"),"") | AK66: =IFERROR(NETWORKDAYS(K66,$AM$1),"-") -> -212 | AL66: =IFERROR(NETWORKDAYS(M66,$AM$1),"-") -> -80 | AM66: =IFERROR(COUNTIFS($F$3:$F$1048576,F66,$G$3:$G$1048576,G66),"") -> 1
A67: 2025 | B67: =UPPER(TEXT(C67,"APRIL")) -> APRIL | C67: 46113 | E67: 46113 | F67: NOATUM | G67: AY MCDONALD VAL-MATIC | H67: =UPPER(VLOOKUP(F67,Droplist!A:C,3,0)) -> JAKOB BLUHME / TOM HINE | I67: HELEN LI | J67: 46143 | K67: 46507 | L67: 46143 | M67: 46507 | N67: SEPARATE | O67: SEPARATE | P67: INCL. IN DOC FEE | Q67: EXCL. (AS PER AGREEMENT) | R67: SEPARATE | S67: SEPARATE | T67: SEPARATE | U67: SEPARATE | V67: SEPARATE | W67: SEPARATE | X67: N | Y67: N | Z67: N | AA67: N | AB67: N | AC67: N | AD67: N | AE67: Maintenance / update rates | AF67: =IF(AD67="Y",IF(AM67>1,"Y","N"),"") | AG67: N | AH67: =IF(AF67="Y",IF(AO67>1,"Y","N"),"") | AI67: N | AJ67: =IF(AH67="Y",IF(AQ67>1,"Y","N"),"") | AK67: =IFERROR(NETWORKDAYS(K67,$AM$1),"-") -> -298 | AL67: =IFERROR(NETWORKDAYS(M67,$AM$1),"-") -> -298 | AM67: =IFERROR(COUNTIFS($F$3:$F$1048576,F67,$G$3:$G$1048576,G67),"") -> 1

Sheet NAC Award overview
A1: ID | B1: YEAR | C1: HANDLED BY WRC / REGIONAL | D1: WWA CUSTOMER | E1: NAMED ACCOUNT | F1: HISTORICAL | G1: CSRFQ SUBMISSION DATE TO OWNER | H1: OFR VALIDITY EFFECTIVE DATE | I1: OFR VALIDITY EXPIRY DATE | J1: RFQ OWNER | K1: BOOKING REF. (WHEN AWARDED) | L1: AWARD STATUS | M1: PRIME / MAINTENANCE | N1: When NOT Awarded or NOT Met Target list reason why: | O1: VOLUME QUOTED IN CBM | P1: NR. OF LANES QUOTED | Q1: VOLUME QUOTED IN CBM PER LANE | R1: AWARDED VOLUME | S1: Volume Commitment p/Month | T1: Actual Volume received till 31st of December 2025 | U1: Actual Volume received till 28th of February 2026 | V1: ADDITIONAL COMMENTS
A2: 882 | B2: 2025 | C2: WRC | D2: CRANE WORLDWIDE | E2: ZF | F2: Updated/ renewed 2025 | G2: 45575 | H2: 45658 | I2: 46022 | J2: =VLOOKUP(D2,Droplist!A:C,3,0) -> Mette B. Karapetian | K2: ZF | L2: AWARDED | M2: =IF(L2<>"AWARDED",L2,IF(NOT(ISNUMBER(T2)),L2,IF(T2>=700,"PRIME",IF(T2>=250,"MAINTENANCE",L2)))) -> MAINTENANCE | O2: 6900 | P2: 396 | Q2: =O2/P2 -> 17.424242 | R2: Not provided | S2: Not provided | T2: 540.43 | V2: SM 17 JAN 2025: STILL PENDING NEXT ROUND (Submitted Round 2 Pricing for Crane WW Review 11/11/24)
A3: 883 | B3: 2025 | C3: WRC | D3: CRANE WORLDWIDE | E3: GENERAL ELECTRIC - GSA | F3: Updated/ renewed 2025 | G3: 45581 | H3: 45658 | I3: 46022 | J3: =VLOOKUP(D3,Droplist!A:C,3,0) -> Mette B. Karapetian | L3: NOT AWARDED | M3: =IF(L3<>"AWARDED",L3,IF(NOT(ISNUMBER(T3)),L3,IF(T3>=700,"PRIME",IF(T3>=250,"MAINTENANCE",L3)))) -> NOT AWARDED | N3: No Feedback provided by customer | O3: 9352 | P3: 283 | Q3: =O3/P3 -> 33.045936 | T3: 10.46
A4: 884 | B4: 2025 | C4: WRC | D4: DACHSER | E4: ZF | F4: NEW quote 2025 | G4: 45574 | H4: 45658 | I4: 46022 | J4: =VLOOKUP(D4,Droplist!A:C,3,0) -> Martin Schulz | L4: NOT AWARDED | M4: =IF(L4<>"AWARDED",L4,IF(NOT(ISNUMBER(T4)),L4,IF(T4>=700,"PRIME",IF(T4>=250,"MAINTENANCE",L4)))) -> NOT AWARDED | N4: No Feedback provided by customer | O4: 19342 | P4: 187 | Q4: =O4/P4 -> 103.43316 | T4: 32.685 | V4: 21 NOV. STILL PENDING AWARD YET NAC VOLUMES REPORTED? HL 6 Nov 2024: STILL PENDING
A5: 885 | B5: 2025 | C5: WRC | D5: LESCHACO | E5: SOLENIS | F5: NEW quote 2025 | G5: 45923 | H5: 45931 | I5: 46053 | J5: =VLOOKUP(D5,Droplist!A:C,3,0) -> Martin Schulz | K5: SOLENIS | L5: AWARDED | M5: =IF(L5<>"AWARDED",L5,IF(NOT(ISNUMBER(T5)),L5,IF(T5>=700,"PRIME",IF(T5>=250,"MAINTENANCE",L5)))) -> PRIME | O5: 1230.45 | P5: 72 | Q5: =O5/P5 -> 17.089583 | R5: 1230 | S5: 107 | T5: 918.251 | U5: 45.172 | V5: Nadine (17-Dec-2025): Extended rate from till 31-Dec-2025 to 31-Jan-2026 Replaced by NAC Chemical Account 2026 quoted 1230450 kgs
A6: 909 | B6: 2025 | C6: WRC | D6: KLN | E6: COTY | F6: NEW quote 2025 | G6: 45665 | H6: 45689 | I6: 45747 | J6: =VLOOKUP(D6,Droplist!A:C,3,0) -> Jens Pottschul | L6: NOT AWARDED | M6: =IF(L6<>"AWARDED",L6,IF(NOT(ISNUMBER(T6)),L6,IF(T6>=700,"PRIME",IF(T6>=250,"MAINTENANCE",L6)))) -> NOT AWARDED | N6: No Feedback provided by customer | O6: 4847 | P6: 202 | Q6: =O6/P6 -> 23.99505
A7: 933 | B7: 2025 | C7: WRC | D7: JAS | E7: MAGNA | F7: New quote 2025 | G7: 45622 | H7: 45658 | I7: 45838 | J7: =VLOOKUP(D7,Droplist!A:C,3,0) -> Chris Crowder | L7: NOT AWARDED | M7: =IF(L7<>"AWARDED",L7,IF(NOT(ISNUMBER(T7)),L7,IF(T7>=700,"PRIME",IF(T7>=250,"MAINTENANCE",L7)))) -> NOT AWARDED | N7: No Feedback provided by customer | O7: 975 | P7: 10 | Q7: =O7/P7 -> 97.5
A8: 934 | B8: 2025 | C8: WRC | D8: CEVA | E8: VALEO | F8: Updated/ renewed 2025 | G8: 45632 | H8: 45658 | I8: 46022 | J8: =VLOOKUP(D8,Droplist!A:C,3,0) -> Jakob Bluhme | K8: VALEO | L8: AWARDED/EXPIRED | M8: =IF(L8<>"AWARDED",L8,IF(NOT(ISNUMBER(T8)),L8,IF(T8>=700,"PRIME",IF(T8>=250,"MAINTENANCE",L8)))) -> AWARDED/EXPIRED | O8: 6800 | P8: 92 | Q8: =O8/P8 -> 73.913043 | R8: 417 | S8: 35 | T8: 130.462 | U8: 6.132 | V8: Awarded 13 lanes// Round 1 was released with FAK without member involvement
A9: 935 | B9: 2025 | C9: WRC | D9: DSV | E9: MAGNA | F9: NEW quote 2025 | G9: 45624 | H9: 45658 | I9: 45838 | J9: =VLOOKUP(D9,Droplist!A:C,3,0) -> #N/A | L9: NOT AWARDED | M9: =IF(L9<>"AWARDED",L9,IF(NOT(ISNUMBER(T9)),L9,IF(T9>=700,"PRIME",IF(T9>=250,"MAINTENANCE",L9)))) -> NOT AWARDED | N9: No Feedback provided by customer | O9: 2864 | P9: 20 | Q9: =O9/P9 -> 143.2 | V9: 22 Apr 2025: Updated to Not Awarded as effective date > 3 months
A10: 937 | B10: 2025 | C10: WRC | D10: KLN | E10: NEW BALANCE | F10: Updated/ renewed 2025 | G10: 45904 | H10: 45931 | I10: 46022 | J10: =VLOOKUP(D10,Droplist!A:C,3,0) -> Jens Pottschul | K10: NEW BALANCE | L10: AWARDED | M10: =IF(L10<>"AWARDED",L10,IF(NOT(ISNUMBER(T10)),L10,IF(T10>=700,"PRIME",IF(T10>=250,"MAINTENANCE",L10)))) -> PRIME | O10: 2000 | P10: 128 | Q10: =O10/P10 -> 15.625 | R10: Not Provided by Customer | S10: Not Provided by Customer | T10: 2469.947 | U10: 444.076 | V10: Requoted Q3-2025, Awarded 156 lanes
A11: 938 | B11: 2025 | C11: WRC | D11: RHENUS | E11: LIXIL | F11: Updated/ renewed 2025 | G11: 45630 | H11: 45658 | I11: 45747 | J11: =VLOOKUP(D11,Droplist!A:C,3,0) -> Jens Pottschul | K11: Lixil 2025 | L11: AWARDED/EXPIRED | M11: =IF(L11<>"AWARDED",L11,IF(NOT(ISNUMBER(T11)),L11,IF(T11>=700,"PRIME",IF(T11>=250,"MAINTENANCE",L11)))) -> AWARDED/EXPIRED | O11: 2156.73 | P11: 57 | Q11: =O11/P11 -> 37.837368 | R11: 1600 | S11: Not Provided by Customer | T11: 341.879 | V11: RENEWED eff 31st March 2025 to 31st December 2025
A12: 939 | B12: 2025 | C12: WRC | D12: EXPEDITORS | E12: LIXIL | F12: NEW quote 2025 | G12: 45630 | H12: 45658 | I12: 45747 | J12: =VLOOKUP(D12,Droplist!A:C,3,0) -> Mette B. Karapetian | L12: NOT AWARDED | M12: =IF(L12<>"AWARDED",L12,IF(NOT(ISNUMBER(T12)),L12,IF(T12>=700,"PRIME",IF(T12>=250,"MAINTENANCE",L12)))) -> NOT AWARDED | N12: Validity already passed | O12: 1084 | P12: 36 | Q12: =O12/P12 -> 30.111111
A13: 940 | B13: 2025 | C13: WRC | D13: CARGO PARTNER | E13: AT&S | F13: NEW quote 2025 | G13: 45632 | H13: 45658 | I13: 46022 | J13: =VLOOKUP(D13,Droplist!A:C,3,0) -> Dennis Frankowski | K13: AT&S | L13: AWARDED/EXPIRED | M13: =IF(L13<>"AWARDED",L13,IF(NOT(ISNUMBER(T13)),L13,IF(T13>=700,"PRIME",IF(T13>=250,"MAINTENANCE",L13)))) -> AWARDED/EXPIRED | O13: 634.82 | P13: 22 | Q13: =O13/P13 -> 28.855455 | R13: 23 | S13: 1 | T13: 29.98 | U13: 2.82 | V13: Extended till end Dec 2025, 2 Lanes Awarded ex KR/TW to SHA
A14: 941 | B14: 2025 | C14: WRC | D14: KLN | E14: STANLEY BLACK & DECKER | F14: Updated/ renewed 2025 | G14: 45915 | H14: 45931 | I14: 46022 | J14: =VLOOKUP(D14,Droplist!A:C,3,0) -> Jens Pottschul | K14: SBD | L14: AWARDED | M14: =IF(L14<>"AWARDED",L14,IF(NOT(ISNUMBER(T14)),L14,IF(T14>=700,"PRIME",IF(T14>=250,"MAINTENANCE",L14)))) -> MAINTENANCE | O14: 2314 | P14: 737 | Q14: =O14/P14 -> 3.1397558 | R14: Not Provided by Customer | S14: Not Provided by Customer | T14: 569.092 | U14: 93.384
A15: 942 | B15: 2025 | C15: WRC | D15: TOLL GROUP | E15: WILO | F15: Updated/ renewed 2025 | G15: 45701 | H15: 45701 | I15: 46022 | J15: =VLOOKUP(D15,Droplist!A:C,3,0) -> Jens Pottschul | K15: WILO | L15: AWARDED/EXPIRED | M15: =IF(L15<>"AWARDED",L15,IF(NOT(ISNUMBER(T15)),L15,IF(T15>=700,"PRIME",IF(T15>=250,"MAINTENANCE",L15)))) -> AWARDED/EXPIRED | O15: 1346.714 | P15: 100 | Q15: =O15/P15 -> 13.46714 | R15: 1300 | S15: 110 | T15: 1148.195 | U15: 220.009
A16: 943 | B16: 2025 | C16: WRC | D16: TOLL GROUP | E16: EVONIK | F16: Updated/ renewed 2025 | G16: 45636 | H16: 45658 | I16: 46022 | J16: =VLOOKUP(D16,Droplist!A:C,3,0) -> Jens Pottschul | K16: EVONIK | L16: AWARDED | M16: =IF(L16<>"AWARDED",L16,IF(NOT(ISNUMBER(T16)),L16,IF(T16>=700,"PRIME",IF(T16>=250,"MAINTENANCE",L16)))) -> PRIME | O16: 2903 | P16: 64 | Q16: =O16/P16 -> 45.359375 | R16: 3000 | S16: 250 | T16: 2656.988 | U16: 387.019
A17: 944 | B17: 2025 | C17: WRC | D17: GEODIS | E17: VOLVO | F17: Updated/ renewed 2025 | G17: 45952 | H17: 45962 | I17: 46022 | J17: =VLOOKUP(D17,Droplist!A:C,3,0) -> Martin Schulz | K17: VOLVO-WWA | L17: AWARDED | M17: =IF(L17<>"AWARDED",L17,IF(NOT(ISNUMBER(T17)),L17,IF(T17>=700,"PRIME",IF(T17>=250,"MAINTENANCE",L17)))) -> PRIME | O17: 9700 | P17: 304 | Q17: =O17/P17 -> 31.907895 | R17: 6200 | S17: 517 | T17: 2619.891 | U17: 354.453 | V17: 26 Nov 25 - Award sent out for remaining Q4 - awaiting Q1 2026 details for processing. 29 Oct 25 SEJ: Pending feedback from round 1 - reminder sent to Geodis to inquire if further extention may be required into 1st week of November - 29 Sept SEJ: Q3 rates extended to Oct 31st - awaiting Geodis feedback on portpairs/volume etc should be in hand first week October 07 July : SEJ - Volvo addl lanes presented awaiting award on these expected next week 22 APR: 265 lanes primary award (1550 cbm /qrtr) / 78 lanes secondary award (626 cbm/qrtr) SEJ 26.02.25 Geodis will advise soonest on new template and new T&C's from VOLVO. Geodis has been awarded biz for new term 1 april 25 to 31st March 2026 - now just needs WWA update based on new details SEJ FUP week 11. 03.27.25 review/negotiations on Q2 levels
A18: 945 | B18: 2025 | C18: REGIONAL | D18: CEVA | E18: GENERAL ELECTRIC - GSA | F18: Updated/ renewed 2025 | G18: 45645 | H18: 45658 | I18: 46022 | J18: =VLOOKUP(D18,Droplist!A:C,3,0) -> Jakob Bluhme | K18: GE GSA | L18: AWARDED | M18: =IF(L18<>"AWARDED",L18,IF(NOT(ISNUMBER(T18)),L18,IF(T18>=700,"PRIME",IF(T18>=250,"MAINTENANCE",L18)))) -> MAINTENANCE | O18: 15595 | P18: 766 | Q18: =O18/P18 -> 20.359008 | R18: 1813 | S18: 165 | T18: 494.627 | U18: 23.46
A19: 947 | B19: 2025 | C19: WRC | D19: APL LOGISTICS | E19: TJX | F19: Updated/ renewed 2025 | G19: 45919 | H19: 45931 | I19: 46022 | J19: =VLOOKUP(D19,Droplist!A:C,3,0) -> Michelle Yu | K19: WWA APL NAC TJX RFQ 2025 | L19: AWARDED | M19: =IF(L19<>"AWARDED",L19,IF(NOT(ISNUMBER(T19)),L19,IF(T19>=700,"PRIME",IF(T19>=250,"MAINTENANCE",L19)))) -> AWARDED | O19: 500 | P19: 155 | Q19: =O19/P19 -> 3.2258065 | R19: 500 | S19: Not Provided by Customer, no regular cargo flow. | T19: 52.457 | U19: 2.516 | V19: 14apr: Customer cannot give exact expected volume as this is the nature of their customer. All depends on how martket develops. Customer accepted new 2025 rates and clear instruction was given to APLL and members to make sure Booking ref is mentioned at time of booking to avoid stat issues.
A20: 948 | B20: 2025 | C20: WRC | D20: GEODIS | E20: HUSQVARNA | F20: Updated/ renewed 2025 | G20: 45932 | H20: 45932 | I20: 46022 | J20: =VLOOKUP(D20,Droplist!A:C,3,0) -> Martin Schulz | K20: HUSQVARNA | L20: AWARDED | M20: =IF(L20<>"AWARDED",L20,IF(NOT(ISNUMBER(T20)),L20,IF(T20>=700,"PRIME",IF(T20>=250,"MAINTENANCE",L20)))) -> MAINTENANCE | O20: 14294 | P20: 594 | Q20: =O20/P20 -> 24.063973 | R20: 1400 | S20: 116 | T20: 446.803 | U20: 95.589 | V20: 3 Dec, Q1-2026 now in process, 1 Dec 25 awaiting details for Q1-2026 processing, Oct 9th Q4 award - 29 sept SEJ - pending Q4 round 2 finalization - May require extention of rates until finalized 1st week of October 07 July SEJ: addl lane award BRSSZ-CRSJO Geodis Husqvarna is active. We only filed TPEB so far as pending input from Geodis on the rest.
A21: 949 | B21: 2025 | C21: WRC | D21: LOGWIN | E21: WURTH | F21: Updated/ renewed 2025 | G21: 45645 | H21: 45658 | I21: 45747 | J21: =VLOOKUP(D21,Droplist!A:C,3,0) -> Martin Schulz | L21: NOT AWARDED | M21: =IF(L21<>"AWARDED",L21,IF(NOT(ISNUMBER(T21)),L21,IF(T21>=700,"PRIME",IF(T21>=250,"MAINTENANCE",L21)))) -> NOT AWARDED | N21: LCL rates not competitive | O21: 3779.1 | P21: 125 | Q21: =O21/P21 -> 30.2328
A22: 950 | B22: 2025 | C22: WRC | D22: JAS | E22: VALMET | F22: Quoted in 2025 | G22: 45950 | H22: 45951 | I22: 46022 | J22: =VLOOKUP(D22,Droplist!A:C,3,0) -> Chris Crowder | K22: VALMET | L22: AWARDED | M22: =IF(L22<>"AWARDED",L22,IF(NOT(ISNUMBER(T22)),L22,IF(T22>=700,"PRIME",IF(T22>=250,"MAINTENANCE",L22)))) -> PRIME | O22: 14661 | P22: 107 | Q22: =O22/P22 -> 137.01869 | R22: 14660 | S22: 900 | T22: 2044.652 | U22: 245.945 | V22: Rate is eff: 1st of Jan 2025 and requoted for Q2-2025
A23: 951 | B23: 2025 | C23: WRC | D23: NIPPON | E23: ATLAS COPCO | F23: NEW quote 2025 | G23: 45643 | H23: 45658 | I23: 46022 | J23: =VLOOKUP(D23,Droplist!A:C,3,0) -> Jens Pottschul | L23: NOT AWARDED | M23: =IF(L23<>"AWARDED",L23,IF(NOT(ISNUMBER(T23)),L23,IF(T23>=700,"PRIME",IF(T23>=250,"MAINTENANCE",L23)))) -> NOT AWARDED | N23: No Feedback provided by customer | O23: 800 | P23: 10 | Q23: =O23/P23 -> 80 | T23: 364.044 | U23: 36.457 | V23: volume quoted was adjusted by Gil dd 28 Mar from 800000 to 800 cbm
A24: 952 | B24: 2025 | C24: WRC | D24: CEVA | E24: BOSCH | F24: Updated/ renewed 2025 | G24: 45215 | H24: 45658 | I24: 45747 | J24: =VLOOKUP(D24,Droplist!A:C,3,0) -> Jakob Bluhme | K24: BOSCH | L24: AWARDED/EXPIRED | M24: =IF(L24<>"AWARDED",L24,IF(NOT(ISNUMBER(T24)),L24,IF(T24>=700,"PRIME",IF(T24>=250,"MAINTENANCE",L24)))) -> AWARDED/EXPIRED | O24: 262 | P24: 31 | Q24: =O24/P24 -> 8.4516129 | R24: 5000 | S24: 416.66667 | T24: 89.024 | V24: Extended 2024 rate till 31st of Mar 2025
A25: 953 | B25: 2025 | C25: WRC | D25: CEVA | E25: HBI | F25: Updated/ renewed 2025 | G25: 45952 | H25: 45962 | I25: 46053 | J25: =VLOOKUP(D25,Droplist!A:C,3,0) -> Jakob Bluhme | K25: HBI2024 | L25: AWARDED | M25: =IF(L25<>"AWARDED",L25,IF(NOT(ISNUMBER(T25)),L25,IF(T25>=700,"PRIME",IF(T25>=250,"MAINTENANCE",L25)))) -> PRIME | O25: 1650 | P25: 13 | Q25: =O25/P25 -> 126.92308 | R25: 850 | S25: 85 | T25: 707.379 | U25: 119.091 | V25: Extended 2024 rate till 30th of Jun 2025
A26: 954 | B26: 2025 | C26: WRC | D26: CEVA | E26: HEAD | F26: Updated/ renewed 2025 | G26: 45331 | H26: 45658 | I26: 45747 | J26: =VLOOKUP(D26,Droplist!A:C,3,0) -> Jakob Bluhme | K26: HEAD2024 | L26: AWARDED/EXPIRED | M26: =IF(L26<>"AWARDED",L26,IF(NOT(ISNUMBER(T26)),L26,IF(T26>=700,"PRIME",IF(T26>=250,"MAINTENANCE",L26)))) -> AWARDED/EXPIRED | O26: 900 | P26: 82 | Q26: =O26/P26 -> 10.97561 | R26: Not provided | S26: Not provided | V26: Extended 2024 rate till 31st of Mar 2025
A27: 955 | B27: 2025 | C27: WRC | D27: CEVA | E27: METSO | F27: Updated/ renewed 2025 | G27: 45278 | H27: 45658 | I27: 45747 | J27: =VLOOKUP(D27,Droplist!A:C,3,0) -> Jakob Bluhme | K27: METSO | L27: AWARDED/EXPIRED | M27: =IF(L27<>"AWARDED",L27,IF(NOT(ISNUMBER(T27)),L27,IF(T27>=700,"PRIME",IF(T27>=250,"MAINTENANCE",L27)))) -> AWARDED/EXPIRED | O27: 1657 | P27: 16 | Q27: =O27/P27 -> 103.5625 | R27: 324 | S27: 29 | T27: 0.374 | V27: Extended 2024 rate till 31st of Mar 2025
A28: 956 | B28: 2025 | C28: WRC | D28: CEVA | E28: OMRON | F28: Updated/ renewed 2025 | G28: 45278 | H28: 45658 | I28: 45747 | J28: =VLOOKUP(D28,Droplist!A:C,3,0) -> Jakob Bluhme | K28: OMROM | L28: AWARDED/EXPIRED | M28: =IF(L28<>"AWARDED",L28,IF(NOT(ISNUMBER(T28)),L28,IF(T28>=700,"PRIME",IF(T28>=250,"MAINTENANCE",L28)))) -> AWARDED/EXPIRED | O28: 896 | P28: 23 | Q28: =O28/P28 -> 38.956522 | R28: 105 | S28: 10 | V28: Extended 2024 rate till 31st of Mar 2025
A29: 957 | B29: 2025 | C29: WRC | D29: CEVA | E29: OXFORD | F29: Updated/ renewed 2025 | G29: 45327 | H29: 45658 | I29: 45747 | J29: =VLOOKUP(D29,Droplist!A:C,3,0) -> Jakob Bluhme | K29: OXFORD | L29: AWARDED/EXPIRED | M29: =IF(L29<>"AWARDED",L29,IF(NOT(ISNUMBER(T29)),L29,IF(T29>=700,"PRIME",IF(T29>=250,"MAINTENANCE",L29)))) -> AWARDED/EXPIRED | O29: 720 | P29: 13 | Q29: =O29/P29 -> 55.384615 | R29: Not provided | S29: Not provided | V29: Extended 2024 rate till 31st of Mar 2025
A30: 958 | B30: 2025 | C30: REGIONAL | D30: CEVA | E30: SIGNIFY | F30: Updated/ renewed 2025 | G30: 45931 | H30: 45931 | I30: 46053 | J30: =VLOOKUP(D30,Droplist!A:C,3,0) -> Jakob Bluhme | K30: SIGNIFY | L30: AWARDED | M30: =IF(L30<>"AWARDED",L30,IF(NOT(ISNUMBER(T30)),L30,IF(T30>=700,"PRIME",IF(T30>=250,"MAINTENANCE",L30)))) -> MAINTENANCE | O30: 12471.03 | P30: 774 | Q30: =O30/P30 -> 16.112442 | R30: 5468.11 | S30: 100 | T30: 639.053 | U30: 143.806 | V30: Extended 2024 rate till 30th of Sep 2025 As per Q3 handled regionally
A31: 959 | B31: 2025 | C31: WRC | D31: CEVA | E31: TRIUMPH | F31: Updated/ renewed 2025 | G31: 45835 | H31: 45839 | I31: 46053 | J31: =VLOOKUP(D31,Droplist!A:C,3,0) -> Jakob Bluhme | K31: TRIUMPH | L31: AWARDED | M31: =IF(L31<>"AWARDED",L31,IF(NOT(ISNUMBER(T31)),L31,IF(T31>=700,"PRIME",IF(T31>=250,"MAINTENANCE",L31)))) -> MAINTENANCE | O31: 4458 | P31: 74 | Q31: =O31/P31 -> 60.243243 | R31: 848 | S31: 71 | T31: 377.575 | U31: 29.475 | V31: Extended 2024 rate till 30th of Jun 2025
A32: 960 | B32: 2025 | C32: WRC | D32: JAS | E32: HEUBACH | F32: Updated/ renewed 2025 | G32: 45924 | H32: 45931 | I32: 46022 | J32: =VLOOKUP(D32,Droplist!A:C,3,0) -> Chris Crowder | K32: JAS MANNHEIM | L32: AWARDED | M32: =IF(L32<>"AWARDED",L32,IF(NOT(ISNUMBER(T32)),L32,IF(T32>=700,"PRIME",IF(T32>=250,"MAINTENANCE",L32)))) -> PRIME | O32: 3450 | P32: 73 | Q32: =O32/P32 -> 47.260274 | R32: Not provided | S32: Not provided | T32: 2939.058 | U32: 318.986 | V32: Requoted Q2/Q3-2025, Extended rate till 31st of Mar 2025
A33: 961 | B33: 2025 | C33: WRC | D33: JAS | E33: TANATEX | F33: Quoted in 2024 | G33: 45924 | H33: 45931 | I33: 46022 | J33: =VLOOKUP(D33,Droplist!A:C,3,0) -> Chris Crowder | K33: TANATEX | L33: AWARDED/EXPIRED | M33: =IF(L33<>"AWARDED",L33,IF(NOT(ISNUMBER(T33)),L33,IF(T33>=700,"PRIME",IF(T33>=250,"MAINTENANCE",L33)))) -> AWARDED/EXPIRED | O33: 1164 | P33: 66 | Q33: =O33/P33 -> 17.636364 | R33: 1164 | S33: Not provided | T33: 155.288 | U33: 4.602 | V33: 15 Dec. NB: Rate for Tanatex will expire 31 Dec. 2025. Requoted Q2-2025, Extended rate till 31st of Mar 2025
A34: 973 | B34: 2025 | C34: WRC | D34: PSA BDP | E34: BAYER COVESTRO LANXESS | F34: Updated/ renewed 2025 | G34: 45838 | H34: 45839 | I34: 45930 | J34: =VLOOKUP(D34,Droplist!A:C,3,0) -> Jakob Bluhme | K34: BAYER COVESTRO | L34: AWARDED | M34: =IF(L34<>"AWARDED",L34,IF(NOT(ISNUMBER(T34)),L34,IF(T34>=700,"PRIME",IF(T34>=250,"MAINTENANCE",L34)))) -> PRIME | O34: 4200 | P34: 385 | Q34: =O34/P34 -> 10.909091 | R34: 1800 | S34: 150 | T34: 1698.6 | V34: Santiago (15-Sep-2025): Volume already in place for the this NAC
A35: 974 | B35: 2025 | C35: WRC | D35: CRANE WORLDWIDE | E35: CUMMINS | F35: NEW quote 2025 | G35: 45651 | H35: 45658 | I35: 45747 | J35: =VLOOKUP(D35,Droplist!A:C,3,0) -> Mette B. Karapetian | L35: NOT AWARDED | M35: =IF(L35<>"AWARDED",L35,IF(NOT(ISNUMBER(T35)),L35,IF(T35>=700,"PRIME",IF(T35>=250,"MAINTENANCE",L35)))) -> NOT AWARDED | N35: Rates high, 45% difference on average | O35: 6268 | P35: 47 | Q35: =O35/P35 -> 133.3617 | T35: 6.943 | U35: 12.068
A36: 975 | B36: 2025 | C36: WRC | D36: GEODIS | E36: SEB | F36: NEW quote 2025 | G36: 45659 | H36: 45659 | I36: 45747 | J36: =VLOOKUP(D36,Droplist!A:C,3,0) -> Martin Schulz | L36: NOT AWARDED | M36: =IF(L36<>"AWARDED",L36,IF(NOT(ISNUMBER(T36)),L36,IF(T36>=700,"PRIME",IF(T36>=250,"MAINTENANCE",L36)))) -> NOT AWARDED | N36: Geodis advised they received award for FCL biz only with no LCL volume. | O36: 1725 | P36: 319 | Q36: =O36/P36 -> 5.4075235 | V36: SEJ 02.03.25 - NO AWARD. Geodis did not get LCL volumes this time however may have opportunity for spot biz which will be based on global tariff and local spot handling. without member involvement
A37: 976 | B37: 2025 | C37: WRC | D37: LESCHACO | E37: ALLNEX | F37: NEW quote 2025 | G37: 45664 | H37: 45689 | I37: 45838 | J37: =VLOOKUP(D37,Droplist!A:C,3,0) -> Martin Schulz | K37: ALLNEX | L37: AWARDED/EXPIRED | M37: =IF(L37<>"AWARDED",L37,IF(NOT(ISNUMBER(T37)),L37,IF(T37>=700,"PRIME",IF(T37>=250,"MAINTENANCE",L37)))) -> AWARDED/EXPIRED | O37: 2617 | P37: 380 | Q37: =O37/P37 -> 6.8868421 | R37: 1400 | S37: 120 | T37: 224.669 | U37: 45.459 | V37: awared for DE only . NB 26 Jan. Rates been extended till end of January 2026. Replaced by NAC Chemical Account 2026
A38: 977 | B38: 2025 | C38: WRC | D38: CRANE WORLDWIDE | E38: TE CONNECTIVITY | F38: NEW quote 2025 | G38: 45664 | H38: 45665 | I38: 45838 | J38: =VLOOKUP(D38,Droplist!A:C,3,0) -> Mette B. Karapetian | L38: NOT AWARDED | M38: =IF(L38<>"AWARDED",L38,IF(NOT(ISNUMBER(T38)),L38,IF(T38>=700,"PRIME",IF(T38>=250,"MAINTENANCE",L38)))) -> NOT AWARDED | N38: Customer is not awarded | O38: 15325 | P38: 290 | Q38: =O38/P38 -> 52.844828 | V38: 95571 Tons / 3 months. Correction SC dd 26 March, volume quoted 15325 cbm.
A39: 978 | B39: 2025 | C39: WRC | D39: ROHLIG | E39: ANSELL | F39: NEW quote 2025 | G39: 45980 | H39: 45992 | I39: 46022 | J39: =VLOOKUP(D39,Droplist!A:C,3,0) -> Martin Schulz | K39: ANSELL | L39: AWARDED | M39: =IF(L39<>"AWARDED",L39,IF(NOT(ISNUMBER(T39)),L39,IF(T39>=700,"PRIME",IF(T39>=250,"MAINTENANCE",L39)))) -> MAINTENANCE | O39: 3308 | P39: 107 | Q39: =O39/P39 -> 30.915888 | R39: Not Provided by Customer | S39: Not Provided by Customer | T39: 273.977
A40: 979 | B40: 2025 | C40: WRC | D40: NOATUM | E40: REGAL REXNORD | F40: NEW quote 2025 | G40: 45911 | H40: 45911 | I40: 46022 | J40: =VLOOKUP(D40,Droplist!A:C,3,0) -> Jakob Bluhme / Tom Hine | L40: NOT AWARDED | M40: =IF(L40<>"AWARDED",L40,IF(NOT(ISNUMBER(T40)),L40,IF(T40>=700,"PRIME",IF(T40>=250,"MAINTENANCE",L40)))) -> NOT AWARDED | N40: Client now wants to issue a new RFQ later on in the year. No longer an active RFQ | O40: 6000 | P40: 225 | Q40: =O40/P40 -> 26.666667 | V40: POC, without member involvement; H1-2025 was not awarded (Client now wants to issue a new RFQ later on in the year. No longer an active RFQ).
A41: 980 | B41: 2025 | C41: WRC | D41: CRANE WORLDWIDE | E41: MEDTRONIC | F41: NEW quote 2025 | G41: 45666 | H41: 45672 | I41: 46022 | J41: =VLOOKUP(D41,Droplist!A:C,3,0) -> Mette B. Karapetian | L41: NOT AWARDED | M41: =IF(L41<>"AWARDED",L41,IF(NOT(ISNUMBER(T41)),L41,IF(T41>=700,"PRIME",IF(T41>=250,"MAINTENANCE",L41)))) -> NOT AWARDED | N41: No Feedback provided by customer | O41: 1226 | P41: 86 | Q41: =O41/P41 -> 14.255814
A42: 981 | B42: 2025 | C42: WRC | D42: DACHSER | E42: MAHLE | F42: NEW quote 2025 | G42: 45923 | H42: 45931 | I42: 46022 | J42: =VLOOKUP(D42,Droplist!A:C,3,0) -> Martin Schulz | K42: MAHLE | L42: AWARDED | M42: =IF(L42<>"AWARDED",L42,IF(NOT(ISNUMBER(T42)),L42,IF(T42>=700,"PRIME",IF(T42>=250,"MAINTENANCE",L42)))) -> PRIME | O42: 6423 | P42: 79 | Q42: =O42/P42 -> 81.303797 | R42: 6423 | S42: 535 | T42: 965.358 | U42: 205.123 | V42: Extended rate till 30th of June 2025
A43: 982 | B43: 2025 | C43: WRC | D43: FLEXPORT | E43: BOSCH | F43: NEW quote 2025 | G43: 45917 | H43: 45931 | I43: 46022 | J43: =VLOOKUP(D43,Droplist!A:C,3,0) -> Jens Pottschul | K43: BOSCH | L43: AWARDED | M43: =IF(L43<>"AWARDED",L43,IF(NOT(ISNUMBER(T43)),L43,IF(T43>=700,"PRIME",IF(T43>=250,"MAINTENANCE",L43)))) -> MAINTENANCE | O43: 11202 | P43: 75 | Q43: =O43/P43 -> 149.36 | R43: 1080 | S43: 80 | T43: 582.524 | U43: 200.696
A44: 983 | B44: 2025 | C44: WRC | D44: YUSEN | E44: FAST RETAILING | F44: NEW quote 2025 | G44: 45848 | H44: 45901 | I44: 46142 | J44: =VLOOKUP(D44,Droplist!A:C,3,0) -> Jens Pottschul | K44: FAST RETAILING | L44: AWARDED | M44: =IF(L44<>"AWARDED",L44,IF(NOT(ISNUMBER(T44)),L44,IF(T44>=700,"PRIME",IF(T44>=250,"MAINTENANCE",L44)))) -> AWARDED | O44: 1310 | P44: 237 | Q44: =O44/P44 -> 5.5274262 | R44: Not provided | S44: Not provided | T44: 88.154 | V44: 6 LANES AWARDED
A45: 984 | B45: 2025 | C45: WRC | D45: HELLMANN | E45: TELTONIKA | F45: NEW quote 2025 | G45: 45671 | H45: 45672 | I45: 45747 | J45: =VLOOKUP(D45,Droplist!A:C,3,0) -> Martin Schulz | L45: NOT AWARDED | M45: =IF(L45<>"AWARDED",L45,IF(NOT(ISNUMBER(T45)),L45,IF(T45>=700,"PRIME",IF(T45>=250,"MAINTENANCE",L45)))) -> NOT AWARDED | N45: customer decided not to move forward with the TDK NAC at this time | O45: 8000 | P45: 10 | Q45: =O45/P45 -> 800
A46: 985 | B46: 2025 | C46: WRC | D46: KLN | E46: ELECTROLUX | F46: NEW quote 2025 | G46: 45673 | H46: 45673 | I46: 46022 | J46: =VLOOKUP(D46,Droplist!A:C,3,0) -> Jens Pottschul | L46: NOT AWARDED | M46: =IF(L46<>"AWARDED",L46,IF(NOT(ISNUMBER(T46)),L46,IF(T46>=700,"PRIME",IF(T46>=250,"MAINTENANCE",L46)))) -> NOT AWARDED | N46: No Feedback provided by customer | O46: 23245 | P46: 1157 | Q46: =O46/P46 -> 20.090752
A47: 986 | B47: 2025 | C47: WRC | D47: CARGO PARTNER | E47: GKN | F47: NEW quote 2025 | G47: 45924 | H47: 45931 | I47: 46022 | J47: =VLOOKUP(D47,Droplist!A:C,3,0) -> Dennis Frankowski | K47: GKN | L47: AWARDED | M47: =IF(L47<>"AWARDED",L47,IF(NOT(ISNUMBER(T47)),L47,IF(T47>=700,"PRIME",IF(T47>=250,"MAINTENANCE",L47)))) -> MAINTENANCE | O47: 19000 | P47: 131 | Q47: =O47/P47 -> 145.03817 | R47: 2400 | S47: 200 | T47: 511.391 | U47: 37.401 | V47: Requoted Q2-2025 rate
A48: 987 | B48: 2025 | C48: WRC | D48: YUSEN | E48: DISNEY | F48: NEW quote 2025 | G48: 45679 | H48: 45679 | I48: 45961 | J48: =VLOOKUP(D48,Droplist!A:C,3,0) -> Jens Pottschul | L48: NOT AWARDED | M48: =IF(L48<>"AWARDED",L48,IF(NOT(ISNUMBER(T48)),L48,IF(T48>=700,"PRIME",IF(T48>=250,"MAINTENANCE",L48)))) -> NOT AWARDED | N48: No feedback from owner | O48: 60449 | P48: 303 | Q48: =O48/P48 -> 199.50165 | V48: 24 JUN 2024: Updated as Not Awarded due to effective date passed 3 months. YUSEN advised - we just submitted round 2 for both tenders, the turnaround time was pretty short, about a week for Flex and slightly less for Disney. If/when we hear back, we’ll let you know. // HL 03MAY2025 Update - For Flexport, there’s several divisions that have separate tenders that run more or less concurrently. Right now, they are focusing on 1 that’s FCL centered. The one we worked on has taken a back seat to that bid and they will address once the FCL bid is settled.
A49: 988 | B49: 2025 | C49: WRC | D49: YUSEN | E49: WATSON | F49: NEW quote 2025 | G49: 45674 | H49: 45674 | I49: 45838 | J49: =VLOOKUP(D49,Droplist!A:C,3,0) -> Jens Pottschul | L49: NOT AWARDED | M49: =IF(L49<>"AWARDED",L49,IF(NOT(ISNUMBER(T49)),L49,IF(T49>=700,"PRIME",IF(T49>=250,"MAINTENANCE",L49)))) -> NOT AWARDED | N49: No Feedback provided by customer | O49: 3280 | P49: 43 | Q49: =O49/P49 -> 76.27907 | V49: 17 MAY 2025: Updated as Not Awarded due to effective date passed 3 months. / SC (8-Apr-2025): Pending feedback from customer / POC, without member involvement
A50: 989 | B50: 2025 | C50: WRC | D50: OIA | E50: AGCO | F50: NEW quote 2025 | G50: 45821 | H50: 45839 | I50: 46022 | J50: =VLOOKUP(D50,Droplist!A:C,3,0) -> Kevin Taylor | K50: AGCO | L50: AWARDED | M50: =IF(L50<>"AWARDED",L50,IF(NOT(ISNUMBER(T50)),L50,IF(T50>=700,"PRIME",IF(T50>=250,"MAINTENANCE",L50)))) -> AWARDED | O50: 964 | P50: 63 | Q50: =O50/P50 -> 15.301587 | R50: 400 | S50: Not provided | T50: 218.883 | U50: 73.233 | V50: Round 2 (30-JAN-2025): With member involvement // Round 1 (6-JAN-2025): POC without member involvement // OIA Awarded 400 CBM on the NAC.
A51: 990 | B51: 2025 | C51: WRC | D51: LOGWIN | E51: QVC | F51: NEW quote 2025 | G51: 45679 | H51: 45679 | I51: 45838 | J51: =VLOOKUP(D51,Droplist!A:C,3,0) -> Martin Schulz | L51: NOT AWARDED | M51: =IF(L51<>"AWARDED",L51,IF(NOT(ISNUMBER(T51)),L51,IF(T51>=700,"PRIME",IF(T51>=250,"MAINTENANCE",L51)))) -> NOT AWARDED | N51: No feedback from owner | O51: 5800 | P51: 36 | Q51: =O51/P51 -> 161.11111
A52: 991 | B52: 2025 | C52: WRC | D52: JAS | E52: ZF | F52: Updated/ renewed 2025 | G52: 45932 | H52: 45932 | I52: 46022 | J52: =VLOOKUP(D52,Droplist!A:C,3,0) -> Chris Crowder | K52: ZF | L52: AWARDED | M52: =IF(L52<>"AWARDED",L52,IF(NOT(ISNUMBER(T52)),L52,IF(T52>=700,"PRIME",IF(T52>=250,"MAINTENANCE",L52)))) -> MAINTENANCE | O52: 49000 | P52: 643 | Q52: =O52/P52 -> 76.205288 | R52: 4000 | S52: Not provided | T52: 691.42 | U52: 86.482
A53: 992 | B53: 2025 | C53: WRC | D53: GEODIS | E53: DISNEY | F53: NEW quote 2025 | G53: 45679 | H53: 45679 | I53: 45961 | J53: =VLOOKUP(D53,Droplist!A:C,3,0) -> Martin Schulz | L53: NOT AWARDED | M53: =IF(L53<>"AWARDED",L53,IF(NOT(ISNUMBER(T53)),L53,IF(T53>=700,"PRIME",IF(T53>=250,"MAINTENANCE",L53)))) -> NOT AWARDED | N53: No Feedback provided by customer | O53: 60448 | P53: 303 | Q53: =O53/P53 -> 199.49835 | V53: 17 MAY 2025: Updated as Not Awarded due to effective date passed 3 months. / Geodis Disney just went into Round2 internally
A54: 993 | B54: 2025 | C54: WRC | D54: LOGWIN | E54: IDS | F54: NEW quote 2025 | G54: 45680 | H54: 45717 | I54: 46022 | J54: =VLOOKUP(D54,Droplist!A:C,3,0) -> Martin Schulz | L54: NOT AWARDED | M54: =IF(L54<>"AWARDED",L54,IF(NOT(ISNUMBER(T54)),L54,IF(T54>=700,"PRIME",IF(T54>=250,"MAINTENANCE",L54)))) -> NOT AWARDED | N54: No Feedback provided by customer | O54: 736 | P54: 58 | Q54: =O54/P54 -> 12.689655 | V54: 19 JUL 2025: Updated as Not Awarded due to effective date passed 3 months // As of 4th July, no feedback frm customer yet
A55: 994 | B55: 2025 | C55: WRC | D55: GEODIS | E55: GETINGE | F55: NEW quote 2025 | G55: 45930 | H55: 45931 | I55: 46022 | J55: =VLOOKUP(D55,Droplist!A:C,3,0) -> Martin Schulz | K55: GETINGE | L55: AWARDED/EXPIRED | M55: =IF(L55<>"AWARDED",L55,IF(NOT(ISNUMBER(T55)),L55,IF(T55>=700,"PRIME",IF(T55>=250,"MAINTENANCE",L55)))) -> AWARDED/EXPIRED | O55: 3007 | P55: 154 | Q55: =O55/P55 -> 19.525974 | R55: 250 | S55: Not provided | T55: 171.922 | U55: 4.707 | V55: 4 December - Geodis advises this NAC will expire and transfer to FAK tariff 1 Dec 25 awaiting details for Q1-2026 processing 29 sept SEJ - pending Q4 round 2 finalization and award - May require extention of rates until finalized 1st week of October -SEJ 02.03.25: will receive feedback around FEb 7th 25 for second round processing / SEJ 26.25.25 Geodis advised that they have processed round 2 in which they will receive feedback on by week 10 (first week of March) Existing biz for Geodis and looks positive for WWA to gain business as WWA is 1st choice from Geodis on this business - soft close positive. 03.27.25 in negotiations SEJ: 8 APRIL - WWA Awarded Backup status on 24 Lanes - total volume approx 1300 cbm/yearly. NAC, validity 6 months equivalent to 650 cbm for these lanes with potential to locally develop. Anticipate 1/3 volume during these 6 months as Backup carrier - Monthly review on volumes will take place
A56: 995 | B56: 2025 | C56: WRC | D56: LOGWIN | E56: RALPH LAUREN | F56: NEW quote 2025 | G56: 45736 | H56: 45736 | I56: 46022 | J56: =VLOOKUP(D56,Droplist!A:C,3,0) -> Martin Schulz | L56: NOT AWARDED | M56: =IF(L56<>"AWARDED",L56,IF(NOT(ISNUMBER(T56)),L56,IF(T56>=700,"PRIME",IF(T56>=250,"MAINTENANCE",L56)))) -> NOT AWARDED | N56: No Feedback provided by customer | O56: 6927 | P56: 124 | Q56: =O56/P56 -> 55.862903 | V56: 19 JUL 2025: Updated as Not Awarded due to effective date passed 3 months // As of 4th July, no feedback frm customer yet
A57: 996 | B57: 2025 | C57: WRC | D57: GEODIS | E57: RALPH LAUREN | F57: NEW quote 2025 | G57: 45862 | H57: 45870 | I57: 46022 | J57: =VLOOKUP(D57,Droplist!A:C,3,0) -> Martin Schulz | L57: NOT AWARDED | M57: =IF(L57<>"AWARDED",L57,IF(NOT(ISNUMBER(T57)),L57,IF(T57>=700,"PRIME",IF(T57>=250,"MAINTENANCE",L57)))) -> NOT AWARDED | N57: No feedback from owner | O57: 6927 | P57: 13 | Q57: =O57/P57 -> 532.84615 | V57: 17 MAY 2025: Updated as Not Awarded due to effective date passed 3 months. / SEJ 02.03.25: will receive feedback around FEb 14th 25 for second round processing
A58: 997 | B58: 2025 | C58: REGIONAL | D58: CEVA | E58: GENERAL MOTORS | F58: NEW quote 2025 | G58: 45896 | H58: 45901 | I58: 45991 | J58: =VLOOKUP(D58,Droplist!A:C,3,0) -> Jakob Bluhme | K58: GENERAL MOTORS | L58: AWARDED | M58: =IF(L58<>"AWARDED",L58,IF(NOT(ISNUMBER(T58)),L58,IF(T58>=700,"PRIME",IF(T58>=250,"MAINTENANCE",L58)))) -> AWARDED | O58: Not provided by owner | P58: 9 | Q58: =O58/P58 -> #VALUE! | R58: Not provided | S58: Not provided | T58: 0.32 | U58: 0.05
A59: 1013 | B59: 2025 | C59: WRC | D59: CARGO PARTNER | E59: BRAUN | F59: NEW quote 2025 | G59: 45684 | H59: 45689 | I59: 45747 | J59: =VLOOKUP(D59,Droplist!A:C,3,0) -> Dennis Frankowski | L59: NOT AWARDED | M59: =IF(L59<>"AWARDED",L59,IF(NOT(ISNUMBER(T59)),L59,IF(T59>=700,"PRIME",IF(T59>=250,"MAINTENANCE",L59)))) -> NOT AWARDED | N59: Validity already passed | O59: 346.914 | P59: 49 | Q59: =O59/P59 -> 7.0798776 | V59: POC, without member involvement
A60: 1014 | B60: 2025 | C60: WRC | D60: CARGO PARTNER | E60: FLEXTRONICS | F60: NEW quote 2025 | G60: 45695 | H60: 45695 | I60: 46022 | J60: =VLOOKUP(D60,Droplist!A:C,3,0) -> Dennis Frankowski | L60: NOT AWARDED | M60: =IF(L60<>"AWARDED",L60,IF(NOT(ISNUMBER(T60)),L60,IF(T60>=700,"PRIME",IF(T60>=250,"MAINTENANCE",L60)))) -> NOT AWARDED | N60: No Feedback provided by customer | O60: 37580 | P60: 548 | Q60: =O60/P60 -> 68.576642 | V60: 17 MAY 2025: Updated as Not Awarded due to effective date passed 3 months./ last follow up with custmer 19 Feb - as per customer, no feedback yet
A61: 1015 | B61: 2025 | C61: WRC | D61: CARGO PARTNER | E61: HARMAN | F61: NEW quote 2025 | G61: 45742 | H61: 45748 | I61: 45777 | J61: =VLOOKUP(D61,Droplist!A:C,3,0) -> Dennis Frankowski | L61: NOT AWARDED | M61: =IF(L61<>"AWARDED",L61,IF(NOT(ISNUMBER(T61)),L61,IF(T61>=700,"PRIME",IF(T61>=250,"MAINTENANCE",L61)))) -> NOT AWARDED | N61: No feedback from owner | O61: 3193 | P61: 38 | Q61: =O61/P61 -> 84.026316 | V61: 8 April - follow up with customer. pending feedback.
A62: 1016 | B62: 2025 | C62: WRC | D62: CRANE WORLDWIDE | E62: HARMAN | F62: NEW quote 2025 | G62: 45701 | H62: 45703 | I62: 46022 | J62: =VLOOKUP(D62,Droplist!A:C,3,0) -> Mette B. Karapetian | L62: NOT AWARDED | M62: =IF(L62<>"AWARDED",L62,IF(NOT(ISNUMBER(T62)),L62,IF(T62>=700,"PRIME",IF(T62>=250,"MAINTENANCE",L62)))) -> NOT AWARDED | N62: No Feedback provided by customer | O62: 69471 | P62: 1675 | Q62: =O62/P62 -> 41.475224
A63: 1017 | B63: 2025 | C63: WRC | D63: DACHSER | E63: BOHLER | F63: NEW quote 2025 | G63: 45923 | H63: 45931 | I63: 46022 | J63: =VLOOKUP(D63,Droplist!A:C,3,0) -> Martin Schulz | K63: BOEHLER | L63: AWARDED | M63: =IF(L63<>"AWARDED",L63,IF(NOT(ISNUMBER(T63)),L63,IF(T63>=700,"PRIME",IF(T63>=250,"MAINTENANCE",L63)))) -> PRIME | O63: 1450 | P63: 71 | Q63: =O63/P63 -> 20.422535 | R63: 5300 | S63: 444 | T63: 965.902 | U63: 125.736 | V63: 16075 tons quoted
A64: 1018 | B64: 2025 | C64: WRC | D64: FR. MEYERS & SOHN (FMS) | E64: REHAU | F64: NEW quote 2025 | G64: 45694 | H64: 45694 | I64: 45838 | J64: =VLOOKUP(D64,Droplist!A:C,3,0) -> Nadine Beer/ Martin Schulz | L64: NOT AWARDED | M64: =IF(L64<>"AWARDED",L64,IF(NOT(ISNUMBER(T64)),L64,IF(T64>=700,"PRIME",IF(T64>=250,"MAINTENANCE",L64)))) -> NOT AWARDED | N64: Reason unknown, status still pending after effective date passed. | O64: 6500 | P64: 32 | Q64: =O64/P64 -> 203.125
A65: 1019 | B65: 2025 | C65: WRC | D65: GEODIS | E65: HITACHI | F65: NEW quote 2025 | G65: 45688 | H65: 45689 | I65: 45930 | J65: =VLOOKUP(D65,Droplist!A:C,3,0) -> Martin Schulz | L65: NOT AWARDED | M65: =IF(L65<>"AWARDED",L65,IF(NOT(ISNUMBER(T65)),L65,IF(T65>=700,"PRIME",IF(T65>=250,"MAINTENANCE",L65)))) -> NOT AWARDED | N65: No Feedback provided by customer | O65: 22400 | P65: 134 | Q65: =O65/P65 -> 167.16418 | T65: 734.052 | V65: 17 MAY 2025: Updated as Not Awarded due to effective date passed 3 months. / SEJ 26.02.25 Geodis in round 2 Hitatchi only accepting 1 all in rate CFS/CFS reveiwing with Geodis further. LOCAL NAC seems only LOCAL for 2024 SEJ investigating
A66: 1020 | B66: 2025 | C66: WRC | D66: FRACHT FWO | E66: COCA COLA | F66: NEW quote 2025 | G66: 45706 | H66: 45717 | I66: 46022 | J66: =VLOOKUP(D66,Droplist!A:C,3,0) -> Chris Crowder | K66: COCA COLA | L66: AWARDED | M66: =IF(L66<>"AWARDED",L66,IF(NOT(ISNUMBER(T66)),L66,IF(T66>=700,"PRIME",IF(T66>=250,"MAINTENANCE",L66)))) -> AWARDED | O66: 8744.023 | P66: 883 | Q66: =O66/P66 -> 9.9026308 | R66: 3264.7 | S66: 272.05833 | T66: 11.845 | U66: 5.47 | V66: FRACHT Advised "We submitted R2 on Friday and we are pending feedback. I will keep you updated". // 29MAY2025 HL - We just submitted door rates for the Round 2 lanes to Fracht. // 01JUL2025 We were advise today that we were awarded the NAC.
A67: 1021 | B67: 2025 | C67: WRC | D67: HELLMANN | E67: TDK | F67: NEW quote 2025 | G67: 45694 | H67: 45703 | I67: 45747 | J67: =VLOOKUP(D67,Droplist!A:C,3,0) -> Martin Schulz | L67: NOT AWARDED | M67: =IF(L67<>"AWARDED",L67,IF(NOT(ISNUMBER(T67)),L67,IF(T67>=700,"PRIME",IF(T67>=250,"MAINTENANCE",L67)))) -> NOT AWARDED | N67: customer decided not to move forward with the TDK NAC at this time | O67: 37619 | P67: 251 | Q67: =O67/P67 -> 149.87649 | T67: 51.991
A68: 1022 | B68: 2025 | C68: WRC | D68: KLN | E68: AVERY DENNISON | F68: NEW quote 2025 | G68: 45924 | H68: 45924 | I68: 46112 | J68: =VLOOKUP(D68,Droplist!A:C,3,0) -> Jens Pottschul | L68: NOT AWARDED | M68: =IF(L68<>"AWARDED",L68,IF(NOT(ISNUMBER(T68)),L68,IF(T68>=700,"PRIME",IF(T68>=250,"MAINTENANCE",L68)))) -> NOT AWARDED | N68: No Feedback provided by customer | O68: 3124 | P68: 1050 | Q68: =O68/P68 -> 2.9752381 | V68: 29 SEP 2025: POC 2.0 Exclusive, without member involvement 17 MAY 2025: Updated as Not Awarded due to effective date passed 3 months. / (MG) 9 APRIL 2025, as per customer, no feedback from their client yet. POC, without member involvement
A69: 1023 | B69: 2025 | C69: WRC | D69: KLN | E69: FLEXTRONICS | F69: NEW quote 2025 | G69: 45691 | H69: 45692 | I69: 45838 | J69: =VLOOKUP(D69,Droplist!A:C,3,0) -> Jens Pottschul | L69: NOT AWARDED | M69: =IF(L69<>"AWARDED",L69,IF(NOT(ISNUMBER(T69)),L69,IF(T69>=700,"PRIME",IF(T69>=250,"MAINTENANCE",L69)))) -> NOT AWARDED | N69: Flex uses “Flex payor site” as a package to compare the competitiveness (not by lanes). | O69: 18275 | P69: 446 | Q69: =O69/P69 -> 40.975336
A70: 1024 | B70: 2025 | C70: WRC | D70: KLN | E70: ASOS | F70: NEW quote 2025 | G70: 45699 | H70: 45699 | I70: 45838 | J70: =VLOOKUP(D70,Droplist!A:C,3,0) -> Jens Pottschul | L70: NOT AWARDED | M70: =IF(L70<>"AWARDED",L70,IF(NOT(ISNUMBER(T70)),L70,IF(T70>=700,"PRIME",IF(T70>=250,"MAINTENANCE",L70)))) -> NOT AWARDED | N70: No feedback from owner | O70: 830 | P70: 54 | Q70: =O70/P70 -> 15.37037 | V70: 24 JUN 2024: Updated as Not Awarded due to effective date passed 3 months. POC, without member involvement, last follow up with Customer 24 Feb, as per customer, still pending
A71: 1025 | B71: 2025 | C71: WRC | D71: K & N | E71: GENERAL ELECTRIC - GSA | F71: NEW quote 2025 | G71: 45685 | H71: 45689 | I71: 45747 | J71: =VLOOKUP(D71,Droplist!A:C,3,0) -> Martin Schulz | K71: GSA | L71: AWARDED/EXPIRED | M71: =IF(L71<>"AWARDED",L71,IF(NOT(ISNUMBER(T71)),L71,IF(T71>=700,"PRIME",IF(T71>=250,"MAINTENANCE",L71)))) -> AWARDED/EXPIRED | O71: 6168 | P71: 105 | Q71: =O71/P71 -> 58.742857 | T71: 111.159
A72: 1026 | B72: 2025 | C72: WRC | D72: K & N | E72: ZF | F72: NEW quote 2025 | G72: 45693 | H72: 45714 | I72: 45838 | J72: =VLOOKUP(D72,Droplist!A:C,3,0) -> Martin Schulz | K72: ZF | L72: AWARDED/EXPIRED | M72: =IF(L72<>"AWARDED",L72,IF(NOT(ISNUMBER(T72)),L72,IF(T72>=700,"PRIME",IF(T72>=250,"MAINTENANCE",L72)))) -> AWARDED/EXPIRED | O72: 8544 | P72: 119 | Q72: =O72/P72 -> 71.798319 | T72: 215.833 | U72: 44.207 | V72: Awarded 32 lanes/Backup 20 lanes
A73: 1027 | B73: 2025 | C73: WRC | D73: K & N | E73: DSM FIRMENICH | F73: NEW quote 2025 | G73: 45712 | H73: 45748 | I73: 46112 | J73: =VLOOKUP(D73,Droplist!A:C,3,0) -> Martin Schulz | L73: NOT AWARDED | M73: =IF(L73<>"AWARDED",L73,IF(NOT(ISNUMBER(T73)),L73,IF(T73>=700,"PRIME",IF(T73>=250,"MAINTENANCE",L73)))) -> NOT AWARDED | N73: No Feedback provided by customer | O73: 4413 | P73: 74 | Q73: =O73/P73 -> 59.635135 | V73: Validty passed. last follow up with custmer 7 march - no feedback from customer as of 8 April
A74: 1028 | B74: 2025 | C74: WRC | D74: LESCHACO | E74: CARGILL | F74: NEW quote 2025 | G74: 45790 | H74: 45839 | I74: 45930 | J74: =VLOOKUP(D74,Droplist!A:C,3,0) -> Martin Schulz | L74: NOT AWARDED | M74: =IF(L74<>"AWARDED",L74,IF(NOT(ISNUMBER(T74)),L74,IF(T74>=700,"PRIME",IF(T74>=250,"MAINTENANCE",L74)))) -> NOT AWARDED | N74: Leschaco is only back up for few lanes, no volumes to be expected, new updat per September | O74: 7200 | P74: 236 | Q74: =O74/P74 -> 30.508475 | V74: Award should follow start of April 2025
A75: 1029 | B75: 2025 | C75: WRC | D75: LOGWIN | E75: BRAUN | F75: NEW quote 2025 | G75: 45691 | H75: 45717 | I75: 46022 | J75: =VLOOKUP(D75,Droplist!A:C,3,0) -> Martin Schulz | L75: NOT AWARDED | M75: =IF(L75<>"AWARDED",L75,IF(NOT(ISNUMBER(T75)),L75,IF(T75>=700,"PRIME",IF(T75>=250,"MAINTENANCE",L75)))) -> NOT AWARDED | N75: No Feedback provided by customer | O75: 2372 | P75: 64 | Q75: =O75/P75 -> 37.0625 | V75: 19 JUL 2025: Updated as Not Awarded due to effective date passed 3 months // As of 4th July, no feedback frm customer yet
A76: 1030 | B76: 2025 | C76: WRC | D76: LOGWIN | E76: SOLENIS | F76: NEW quote 2025 | G76: 45695 | H76: 45695 | I76: 45838 | J76: =VLOOKUP(D76,Droplist!A:C,3,0) -> Martin Schulz | K76: SOLENIS | L76: AWARDED/EXPIRED | M76: =IF(L76<>"AWARDED",L76,IF(NOT(ISNUMBER(T76)),L76,IF(T76>=700,"PRIME",IF(T76>=250,"MAINTENANCE",L76)))) -> AWARDED/EXPIRED | O76: 236.937 | P76: 36 | Q76: =O76/P76 -> 6.5815833 | R76: 600 | S76: 50 | T76: 95.424 | U76: 24.303 | V76: quoted 236937 kgs
A77: 1031 | B77: 2025 | C77: WRC | D77: LOGWIN | E77: SCHNEIDER | F77: NEW quote 2025 | G77: 45702 | H77: 45705 | I77: 46022 | J77: =VLOOKUP(D77,Droplist!A:C,3,0) -> Martin Schulz | L77: NOT AWARDED | M77: =IF(L77<>"AWARDED",L77,IF(NOT(ISNUMBER(T77)),L77,IF(T77>=700,"PRIME",IF(T77>=250,"MAINTENANCE",L77)))) -> NOT AWARDED | N77: Reason unknown, status still pending after effective date passed. | O77: 1400 | P77: 55 | Q77: =O77/P77 -> 25.454545
A78: 1032 | B78: 2025 | C78: WRC | D78: NOATUM | E78: LENOVO | F78: NEW quote 2025 | G78: 45691 | H78: 45691 | I78: 45838 | J78: =VLOOKUP(D78,Droplist!A:C,3,0) -> Jakob Bluhme / Tom Hine | L78: NOT AWARDED | M78: =IF(L78<>"AWARDED",L78,IF(NOT(ISNUMBER(T78)),L78,IF(T78>=700,"PRIME",IF(T78>=250,"MAINTENANCE",L78)))) -> NOT AWARDED | N78: Lost out on rate to Expeditors & KAN. | O78: 1928 | P78: 210 | Q78: =O78/P78 -> 9.1809524 | V78: POC, without member involvement
A79: 1033 | B79: 2025 | C79: WRC | D79: NOATUM | E79: SEG | F79: NEW quote 2025 | G79: 45695 | H79: 45703 | I79: 46022 | J79: =VLOOKUP(D79,Droplist!A:C,3,0) -> Jakob Bluhme / Tom Hine | L79: NOT AWARDED | M79: =IF(L79<>"AWARDED",L79,IF(NOT(ISNUMBER(T79)),L79,IF(T79>=700,"PRIME",IF(T79>=250,"MAINTENANCE",L79)))) -> NOT AWARDED | N79: Lost and not awarded, purely rate based. | O79: 45247 | P79: 587 | Q79: =O79/P79 -> 77.081772
A80: 1034 | B80: 2025 | C80: WRC | D80: NOATUM | E80: TENNECO | F80: NEW quote 2025 | G80: 45723 | H80: 45723 | I80: 45869 | J80: =VLOOKUP(D80,Droplist!A:C,3,0) -> Jakob Bluhme / Tom Hine | L80: NOT AWARDED | M80: =IF(L80<>"AWARDED",L80,IF(NOT(ISNUMBER(T80)),L80,IF(T80>=700,"PRIME",IF(T80>=250,"MAINTENANCE",L80)))) -> NOT AWARDED | N80: No Feedback provided by customer | O80: 36773 | P80: 818 | Q80: =O80/P80 -> 44.954768 | V80: 19 JUL 2025: Updated as Not Awarded due to effective date passed 3 months// Tom (28-Apr-2025): Round 3 feedback pending right now.
A81: 1035 | B81: 2025 | C81: WRC | D81: ROHLIG | E81: DISNEY | F81: NEW quote 2025 | G81: 45681 | H81: 45679 | I81: 45961 | J81: =VLOOKUP(D81,Droplist!A:C,3,0) -> Martin Schulz | L81: NOT AWARDED | M81: =IF(L81<>"AWARDED",L81,IF(NOT(ISNUMBER(T81)),L81,IF(T81>=700,"PRIME",IF(T81>=250,"MAINTENANCE",L81)))) -> NOT AWARDED | N81: No Feedback provided by customer | O81: 5767 | P81: 68 | Q81: =O81/P81 -> 84.808824 | V81: Applied same as Yusen NAC Disney rate
A82: 1036 | B82: 2025 | C82: WRC | D82: UPS | E82: DISNEY | F82: NEW quote 2025 | G82: 45681 | H82: 45679 | I82: 45961 | J82: =VLOOKUP(D82,Droplist!A:C,3,0) -> Roberta MacLeod-Stuart | L82: NOT AWARDED | M82: =IF(L82<>"AWARDED",L82,IF(NOT(ISNUMBER(T82)),L82,IF(T82>=700,"PRIME",IF(T82>=250,"MAINTENANCE",L82)))) -> NOT AWARDED | N82: No Feedback provided by customer | O82: 60448 | P82: 303 | Q82: =O82/P82 -> 199.49835 | V82: 17 MAY 2025: Updated as Not Awarded due to effective date passed 3 months. 4-8-2025 RMS Email to UPS to ask for status. Pending replicate rates from Yusen yet further complete NS lanes and add OFR Haz
A83: 1037 | B83: 2025 | C83: WRC | D83: YUSEN | E83: FLEXTRONICS | F83: NEW quote 2025 | G83: 45691 | H83: 45691 | I83: 46022 | J83: =VLOOKUP(D83,Droplist!A:C,3,0) -> Jens Pottschul | L83: NOT AWARDED | M83: =IF(L83<>"AWARDED",L83,IF(NOT(ISNUMBER(T83)),L83,IF(T83>=700,"PRIME",IF(T83>=250,"MAINTENANCE",L83)))) -> NOT AWARDED | N83: No feedback from owner | O83: 6183 | P83: 192 | Q83: =O83/P83 -> 32.203125 | V83: 24 JUN 2024: Updated as Not Awarded due to effective date passed 3 months. YUSEN advised - we just submitted round 2 for both tenders, the turnaround time was pretty short, about a week for Flex and slightly less for Disney. If/when we hear back, we’ll let you know. // HL 03MAY2025 Update - For Disney, our colleague in Miami was spearheading and we actually received a similar email today asking for a status update. I reached out to him on the side and asked him to comment and I’m awaiting his feedback.
A84: 1038 | B84: 2025 | C84: WRC | D84: AIT | E84: DELL | F84: NEW quote 2025 | G84: 45674 | H84: 45674 | I84: 45838 | J84: =VLOOKUP(D84,Droplist!A:C,3,0) -> Sylvia Lathouwers | L84: NOT AWARDED | M84: =IF(L84<>"AWARDED",L84,IF(NOT(ISNUMBER(T84)),L84,IF(T84>=700,"PRIME",IF(T84>=250,"MAINTENANCE",L84)))) -> NOT AWARDED | N84: No feedback from owner | O84: 3230 | P84: 1669 | Q84: =O84/P84 -> 1.9352906 | V84: 17 MAY 2025: Updated as Not Awarded due to effective date passed 3 months. / POC, without member involvement
A85: 1039 | B85: 2025 | C85: WRC | D85: CRANE WORLDWIDE | E85: AMAZON WEB SERVICES | F85: NEW quote 2025 | G85: 45714 | H85: 45748 | I85: 46112 | J85: =VLOOKUP(D85,Droplist!A:C,3,0) -> Mette B. Karapetian | L85: NOT AWARDED | M85: =IF(L85<>"AWARDED",L85,IF(NOT(ISNUMBER(T85)),L85,IF(T85>=700,"PRIME",IF(T85>=250,"MAINTENANCE",L85)))) -> NOT AWARDED | N85: No feedback from owner | O85: 1675 | P85: 368 | Q85: =O85/P85 -> 4.5516304 | T85: 1.4
A86: 1040 | B86: 2025 | C86: REGIONAL | D86: CRANE WORLDWIDE | E86: GEA | F86: NEW quote 2025 | G86: 45919 | H86: 45919 | I86: 46112 | J86: =VLOOKUP(D86,Droplist!A:C,3,0) -> Mette B. Karapetian | L86: NOT AWARDED | M86: =IF(L86<>"AWARDED",L86,IF(NOT(ISNUMBER(T86)),L86,IF(T86>=700,"PRIME",IF(T86>=250,"MAINTENANCE",L86)))) -> NOT AWARDED | N86: No Feedback provided by customer | O86: 1968 | P86: 231 | Q86: =O86/P86 -> 8.5194805 | V86: 18 NOV 2025: Updated as Not Awarded due to effective date passed 3 months HL 30SEP2025 - Customer advise pending awarded R2, without member involvement handled by STi/SM Round 1 (19-SEP-2025): POC 2.0 Exclusive, without member involvement handled by WRC 24 JUN 2024: Updated as Not Awarded due to effective date passed 3 months. POC, without member involvement for valid 21 Feb to 31 Jul 2025
A87: 1041 | B87: 2025 | C87: WRC | D87: LOGWIN | E87: AUTOLIV | F87: NEW quote 2025 | G87: 45712 | H87: 45717 | I87: 46022 | J87: =VLOOKUP(D87,Droplist!A:C,3,0) -> Martin Schulz | L87: NOT AWARDED | M87: =IF(L87<>"AWARDED",L87,IF(NOT(ISNUMBER(T87)),L87,IF(T87>=700,"PRIME",IF(T87>=250,"MAINTENANCE",L87)))) -> NOT AWARDED | N87: No Feedback provided by customer | O87: 1573.17 | P87: 31 | Q87: =O87/P87 -> 50.747419 | V87: 19 JUL 2025: Updated as Not Awarded due to effective date passed 3 months// 2024 Volume were for ex Latam to Eu
A88: 1042 | B88: 2025 | C88: WRC | D88: LOGWIN | E88: BEELINE | F88: NEW quote 2025 | G88: 45890 | H88: 45931 | I88: 46112 | J88: =VLOOKUP(D88,Droplist!A:C,3,0) -> Martin Schulz | K88: BEELINE | L88: AWARDED | M88: =IF(L88<>"AWARDED",L88,IF(NOT(ISNUMBER(T88)),L88,IF(T88>=700,"PRIME",IF(T88>=250,"MAINTENANCE",L88)))) -> MAINTENANCE | O88: 1400 | P88: 66 | Q88: =O88/P88 -> 21.212121 | R88: 1800 | S88: 150 | T88: 404.527 | V88: 15 Dec. 2025 NB: Rates been extended till 31st of January, 2026. Unfortunately Beeline only nominated Logwin as back up this time.
A89: 1043 | B89: 2025 | C89: WRC | D89: LOGWIN | E89: SCHOEFFEL | F89: NEW quote 2025 | G89: 45708 | H89: 45708 | I89: 46022 | J89: =VLOOKUP(D89,Droplist!A:C,3,0) -> Martin Schulz | L89: NOT AWARDED | M89: =IF(L89<>"AWARDED",L89,IF(NOT(ISNUMBER(T89)),L89,IF(T89>=700,"PRIME",IF(T89>=250,"MAINTENANCE",L89)))) -> NOT AWARDED | N89: No Feedback provided by customer | O89: 600 | P89: 248 | Q89: =O89/P89 -> 2.4193548
A90: 1044 | B90: 2025 | C90: WRC | D90: OIA | E90: DELL | F90: NEW quote 2025 | G90: 45734 | H90: 45734 | I90: 45838 | J90: =VLOOKUP(D90,Droplist!A:C,3,0) -> Kevin Taylor | L90: NOT AWARDED | M90: =IF(L90<>"AWARDED",L90,IF(NOT(ISNUMBER(T90)),L90,IF(T90>=700,"PRIME",IF(T90>=250,"MAINTENANCE",L90)))) -> NOT AWARDED | N90: No feedback from owner | O90: 3254 | P90: 1669 | Q90: =O90/P90 -> 1.9496705 | V90: ROUND 2 (18-MAR-2025) - With member involvement // ROUND 1 (17-FEB-2025) - POC, without member involvement // HL advised 28APR2025 NAC just made it to Round 2
A91: 1045 | B91: 2025 | C91: WRC | D91: OIA | E91: APTIV | F91: NEW quote 2025 | G91: 45712 | H91: 45712 | I91: 45838 | J91: =VLOOKUP(D91,Droplist!A:C,3,0) -> Kevin Taylor | L91: NOT AWARDED | M91: =IF(L91<>"AWARDED",L91,IF(NOT(ISNUMBER(T91)),L91,IF(T91>=700,"PRIME",IF(T91>=250,"MAINTENANCE",L91)))) -> NOT AWARDED | N91: 7/27/2025 They did not win LCL, only FCL from the customer | O91: 19204 | P91: 322 | Q91: =O91/P91 -> 59.639752 | V91: 24 JUN 2024: Updated as Not Awarded due to effective date passed 3 months. KT 4/8/2025 Customer still pending results // 09JUN2025 OIA advised NAC is STILL Pending Result.
A92: 1046 | B92: 2025 | C92: WRC | D92: DP WORLD | E92: EATON | F92: NEW quote 2025 | G92: 45715 | H92: 45748 | I92: 46112 | J92: =VLOOKUP(D92,Droplist!A:C,3,0) -> Martin Schulz | L92: NOT AWARDED | M92: =IF(L92<>"AWARDED",L92,IF(NOT(ISNUMBER(T92)),L92,IF(T92>=700,"PRIME",IF(T92>=250,"MAINTENANCE",L92)))) -> NOT AWARDED | N92: No Feedback provided by customer | O92: 61464 | P92: 832 | Q92: =O92/P92 -> 73.875 | V92: SM(17-Mar-2025):No Feedback provided by customer
A93: 1095 | B93: 2025 | C93: WRC | D93: DSV | E93: DOW | F93: NEW quote 2025 | G93: 45723 | H93: 45748 | I93: 46022 | J93: =VLOOKUP(D93,Droplist!A:C,3,0) -> #N/A | K93: DOW | L93: AWARDED | M93: =IF(L93<>"AWARDED",L93,IF(NOT(ISNUMBER(T93)),L93,IF(T93>=700,"PRIME",IF(T93>=250,"MAINTENANCE",L93)))) -> PRIME | O93: 1530 | P93: 876 | Q93: =O93/P93 -> 1.7465753 | R93: 1500 | S93: 130 | T93: 1317.036 | U93: 241.901 | V93: WRC handled Q2-2025
A94: 1174 | B94: 2025 | C94: REGIONAL | D94: CEVA | E94: LVMH | F94: NEW quote 2025 | G94: 45938 | H94: 45931 | I94: 46053 | J94: =VLOOKUP(D94,Droplist!A:C,3,0) -> Jakob Bluhme | K94: LVMH | L94: AWARDED | M94: =IF(L94<>"AWARDED",L94,IF(NOT(ISNUMBER(T94)),L94,IF(T94>=700,"PRIME",IF(T94>=250,"MAINTENANCE",L94)))) -> AWARDED | O94: 3310 | P94: 93 | Q94: =O94/P94 -> 35.591398 | R94: 1644 | S94: 130
A95: 1175 | B95: 2025 | C95: WRC | D95: CEVA | E95: STANLEY BLACK & DECKER | F95: NEW quote 2025 | G95: 45729 | H95: 45748 | I95: 46053 | J95: =VLOOKUP(D95,Droplist!A:C,3,0) -> Jakob Bluhme | K95: SBD | L95: AWARDED | M95: =IF(L95<>"AWARDED",L95,IF(NOT(ISNUMBER(T95)),L95,IF(T95>=700,"PRIME",IF(T95>=250,"MAINTENANCE",L95)))) -> AWARDED | O95: 1862 | P95: 268 | Q95: =O95/P95 -> 6.9477612 | R95: 270 | S95: 30 | U95: 1.212 | V95: Awarded 86 lanes/ Backup 182 lanes
A96: 1176 | B96: 2025 | C96: WRC | D96: CEVA | E96: SIEMENS | F96: NEW quote 2025 | G96: 45726 | H96: 45748 | I96: 45838 | J96: =VLOOKUP(D96,Droplist!A:C,3,0) -> Jakob Bluhme | L96: NOT AWARDED | M96: =IF(L96<>"AWARDED",L96,IF(NOT(ISNUMBER(T96)),L96,IF(T96>=700,"PRIME",IF(T96>=250,"MAINTENANCE",L96)))) -> NOT AWARDED | N96: Not competitive enough | O96: 3902 | P96: 170 | Q96: =O96/P96 -> 22.952941
A97: 1177 | B97: 2025 | C97: WRC | D97: CEVA | E97: SABIC | F97: NEW quote 2025 | G97: 45728 | H97: 45728 | I97: 45838 | J97: =VLOOKUP(D97,Droplist!A:C,3,0) -> Jakob Bluhme | L97: NOT AWARDED | M97: =IF(L97<>"AWARDED",L97,IF(NOT(ISNUMBER(T97)),L97,IF(T97>=700,"PRIME",IF(T97>=250,"MAINTENANCE",L97)))) -> NOT AWARDED | N97: No feedback from owner | O97: 1000 | P97: 84 | Q97: =O97/P97 -> 11.904762 | V97: Not awarded: Not provided by the customer
A98: 1178 | B98: 2025 | C98: WRC | D98: CRANE WORLDWIDE | E98: ADTRAN | F98: NEW quote 2025 | G98: 45722 | H98: 45722 | I98: 45900 | J98: =VLOOKUP(D98,Droplist!A:C,3,0) -> Mette B. Karapetian | L98: NOT AWARDED | M98: =IF(L98<>"AWARDED",L98,IF(NOT(ISNUMBER(T98)),L98,IF(T98>=700,"PRIME",IF(T98>=250,"MAINTENANCE",L98)))) -> NOT AWARDED | N98: No Feedback provided by customer | O98: 2821 | P98: 62 | Q98: =O98/P98 -> 45.5 | V98: POC, without member involvement
A99: 1179 | B99: 2025 | C99: WRC | D99: DACHSER | E99: LIEBHERR | F99: NEW quote 2025 | G99: 45819 | H99: 45839 | I99: 45930 | J99: =VLOOKUP(D99,Droplist!A:C,3,0) -> Martin Schulz | K99: LIEBHERR | L99: AWARDED/EXPIRED | M99: =IF(L99<>"AWARDED",L99,IF(NOT(ISNUMBER(T99)),L99,IF(T99>=700,"PRIME",IF(T99>=250,"MAINTENANCE",L99)))) -> AWARDED/EXPIRED | O99: 2761 | P99: 5 | Q99: =O99/P99 -> 552.2 | R99: 2761 | S99: 230 | T99: 227.343 | U99: 12.876
A100: 1180 | B100: 2025 | C100: WRC | D100: FEDEX | E100: AVERY DENNISON | F100: NEW quote 2025 | G100: 45722 | H100: 45722 | I100: 45807 | J100: =VLOOKUP(D100,Droplist!A:C,3,0) -> Bruce Ericson | L100: NOT AWARDED | M100: =IF(L100<>"AWARDED",L100,IF(NOT(ISNUMBER(T100)),L100,IF(T100>=700,"PRIME",IF(T100>=250,"MAINTENANCE",L100)))) -> NOT AWARDED | N100: No feedback from owner | O100: 500 | P100: 69 | Q100: =O100/P100 -> 7.2463768 | V100: POC, without member involvement
...

Sheet NAC Award - Missing response
A1: WWA OWNER NO REPLY / UPATE / DELAY TO THE NAC OVERVIEW 2024 / 2025 / 2026
A2: OWNER | B2: GLOBAL ACCOUNT | C2: GLOBAL / NAC | D2: NAC | E2: MONTH | F2: REPORT DATE | G2: YEAR | H2: ISSUE DESCRIPTION | I2: EMAIL SUBJECT | J2: CATEGORY | K2: COUNT
A3: Helen Li | B3: various | C3: NAC | D3: overview | E3: JANUARY | F3: 45320 | G3: 2024 | H3: Reply rcvd on 29th of Jan after reminder, deadline was 19th of Jan. EOB | I3: Updated WWA NAC Overview - November, 2023 | J3: Delayed communication / missing info | K3: 1
A4: Shu Rong Lau | B4: various | C4: NAC | D4: overview | E4: JANUARY | F4: 45315 | G4: 2024 | H4: Reply rcvd on 24th of Jan after reminder, deadline was 19th of Jan. EOB, still incomplete | I4: Updated WWA NAC Overview - November, 2023 | J4: Delayed communication / missing info | K4: 1
A5: Helen Li | B5: various | C5: NAC | D5: overview | E5: FEBRUARY | F5: 45345 | G5: 2024 | H5: NAC overview update deadline was 19th of Feb., received 23rd of Feb. | I5: Updated WWA NAC overview - December, 2023 | J5: Delayed communication / missing info | K5: 1
A6: Shu Rong Lau | B6: various | C6: NAC | D6: overview | E6: APRIL | F6: 45407 | G6: 2024 | H6: Incomplete updates of the WWA NAC overview | I6: Updated WWA NAC overview - March, 2024 | J6: Incorrect / incomplete data shared | K6: 1
A7: Bruce Ericson | B7: various | C7: NAC | D7: overview | E7: APRIL | F7: 45401 | G7: 2024 | H7: No update/no response to NAC overview update for Mar. 2024 | I7: Updated WWA NAC overview - December, 2023 | J7: Incomplete / missing data | K7: 1
A8: Chris Crowder | B8: various | C8: NAC | D8: overview | E8: APRIL | F8: 45401 | G8: 2024 | H8: No update/no response to NAC overview update for Mar. 2024 | I8: Updated WWA NAC overview - December, 2023 | J8: Incomplete / missing data | K8: 1
A9: Jacqueline Chong | B9: various | C9: NAC | D9: overview | E9: APRIL | F9: 45401 | G9: 2024 | H9: No update/no response to NAC overview update for Mar. 2024 | I9: Updated WWA NAC overview - December, 2023 | J9: Incomplete / missing data | K9: 1
A10: Martin Schulz | B10: various | C10: NAC | D10: overview | E10: APRIL | F10: 45401 | G10: 2024 | H10: No update/no response to NAC overview update for Mar. 2024 | I10: Updated WWA NAC overview - December, 2023 | J10: Incomplete / missing data | K10: 1
